Workbook
Name CRF: #REF!
Name DiscountRate: #REF!
Name FacilityLifetime: #REF!
Name GeneralDataManufacturingLocations: #REF!
Name MaterialData316SSStandardDensity: #REF!
Name MaterialDataA36CSStandardDensity: #REF!
Name MaterialDataB4CNaturalTheoreticalDensity: #REF!
Name MaterialDataConcreteNominalSolidDensity: #REF!
Name MaterialDataGeneralInsulationStandardDensity: #REF!
Name MaterialDataGR22StandardDensity: #REF!
Name MaterialDataInconel718StandardDensity: #REF!
Name UC_m_in: #REF!

Sheet Cost Database
A1: Account | B1: Level | C1: Account Name | D1: Account Title | E1: Standard Cost Equation? | F1: Optional Variable | G1: Optional Value | H1: Sec Optional Variable | I1: Sec Optional Value | J1: Fixed Cost ($) | K1: Unit Cost | L1: Unit Cost (units) | M1: Scaling Variable | N1: Scaling Variable Ref Value | O1: Units | P1: Exponent | Q1: Dollar Year | R1: Type | S1: Source | T1: Ref | U1: Link | V1: Notes | W1: FOAK to NOAK Multiplier Type | X1: Fixed Cost Low End | Y1: Fixed Cost High End | Z1: Fixed Cost Distribution | AA1: Unit Cost Low End | AB1: Unit Cost High End | AC1: Unit Cost Distribution | AD1: Exponent std | AE1: Exponent Max | AF1: Exponent Min | AG1: Exponent Distribution
A2: 10 | B2: =IF(ISNUMBER(A2), IF(AND(A2=INT(A2), MOD(A2, 10) = 0), 0, IF(AND(A2=INT(A2), LEN(A2)=2), 1, IF(AND(A2=INT(A2), LEN(A2)=3), 2, LEN(A2) - FIND(".", A2) + 2) ) ), "") -> 0 | C2: Capitalized Pre-Construction Costs | D2: =REPT(" ", B2*2) & C2 -> Capitalized Pre-Construction Costs
A3: 11 | B3: =IF(ISNUMBER(A3), IF(AND(A3=INT(A3), MOD(A3, 10) = 0), 0, IF(AND(A3=INT(A3), LEN(A3)=2), 1, IF(AND(A3=INT(A3), LEN(A3)=3), 2, LEN(A3) - FIND(".", A3) + 2) ) ), "") -> 1 | C3: Land Cost | D3: =REPT(" ", B3*2) & C3 -> Land Cost | E3: standard | K3: 3800 | L3: $/acres | M3: Land Area | O3: acres | Q3: 2022 | R3: General | S3: The average cost per acre for rural land in 2022 from the US Department of Agriculture | T3: Abou-Jaoude, A., Lohse, C. S., Larsen, L. M., Guaita, N., Trivedi, I., Joseck, F. C., ... & Stein, A. (2024). Meta-analysis of advanced nuclear reactor cost estimations (No. INL/RPT-24-77048-Rev001). Idaho National Laboratory (INL), Idaho Falls, ID (United States). | U3: https://inldigitallibrary.inl.gov/sites/sti/sti/Sort_107010.pdf | W3: No Learning | X3: =0.9*$J3 -> 0 | Y3: =1.5*J3 -> 0 | Z3: Lognormal | AA3: =0.9*K3 -> 3420 | AB3: =1.3*K3 -> 4940 | AC3: Lognormal | AD3: 0.1 | AE3: 1 | AF3: 0 | AG3: Truncated Normal
A4: 12 | B4: =IF(ISNUMBER(A4), IF(AND(A4=INT(A4), MOD(A4, 10) = 0), 0, IF(AND(A4=INT(A4), LEN(A4)=2), 1, IF(AND(A4=INT(A4), LEN(A4)=3), 2, LEN(A4) - FIND(".", A4) + 2) ) ), "") -> 1 | C4: Site Permits | D4: =REPT(" ", B4*2) & C4 -> Site Permits | E4: standard | K4: =10.03*1000 -> 10030 | L4: $/MWe | M4: Power MWe | O4: MWe | Q4: 2022 | R4: Labor | S4: Data from SMR MHTGRs | W4: No Learning | X4: =0.9*$J4 -> 0 | Y4: =1.5*J4 -> 0 | Z4: Lognormal | AA4: =0.9*K4 -> 9027 | AB4: =1.3*K4 -> 13039 | AC4: Lognormal | AD4: 0.1 | AE4: 1 | AF4: 0 | AG4: Truncated Normal
A5: 13 | B5: =IF(ISNUMBER(A5), IF(AND(A5=INT(A5), MOD(A5, 10) = 0), 0, IF(AND(A5=INT(A5), LEN(A5)=2), 1, IF(AND(A5=INT(A5), LEN(A5)=3), 2, LEN(A5) - FIND(".", A5) + 2) ) ), "") -> 1 | C5: Plant Licensing | D5: =REPT(" ", B5*2) & C5 -> Plant Licensing | E5: standard | J5: =0.5*(X5+Y5) -> 28113008 | Q5: 2025 | R5: Labor | S5: NRC Website | T5: According to NRC, the number of hours range from 108K to 257K hours https://www.nrc.gov/docs/ML2301/ML23018A174.pdf For the hourly rate: 154$/hour https://www.federalregister.gov/documents/2026/06/16/2026-12067/fee-schedules-fee-recovery-for-fiscal-year-2026 | U5: https://art.inl.gov/NGNP/INL%20Documents/Year%202012/Assessment%20of%20High%20Temperature%20Gas-Cooled%20Reactor%20-%20HTGR%20-%20Capital%20and%20Operating%20Costs.pdf | W5: Licensing Learning | X5: =154*108000 -> 16632000 | Y5: =154*257104 -> 39594016 | Z5: Uniform | AA5: =0.9*K5 -> 0 | AB5: =1.3*K5 -> 0 | AC5: Lognormal | AD5: 0.1 | AE5: 1 | AF5: 0 | AG5: Truncated Normal
A6: 14 | B6: =IF(ISNUMBER(A6), IF(AND(A6=INT(A6), MOD(A6, 10) = 0), 0, IF(AND(A6=INT(A6), LEN(A6)=2), 1, IF(AND(A6=INT(A6), LEN(A6)=3), 2, LEN(A6) - FIND(".", A6) + 2) ) ), "") -> 1 | C6: Plant Permits | D6: =REPT(" ", B6*2) & C6 -> Plant Permits | E6: standard | J6: 3000000 | Q6: 2009 | R6: Labor | S6: NGNP project | T6: Gandrik, A., B. Wallace, L. Demick, S. Melancon and M. Patterson (2011). "Assessment of high temperature gas-cooled reactor (HTGR) capital and operating costs." Idaho National Laboratory, TEV-1196, Idaho Falls, ID. | W6: No Learning | X6: =0.9*$J6 -> 2700000 | Y6: =1.5*J6 -> 4500000 | Z6: Lognormal | AA6: =0.9*K6 -> 0 | AB6: =1.3*K6 -> 0 | AC6: Lognormal | AD6: 0.1 | AE6: 1 | AF6: 0 | AG6: Truncated Normal
A7: 15 | B7: =IF(ISNUMBER(A7), IF(AND(A7=INT(A7), MOD(A7, 10) = 0), 0, IF(AND(A7=INT(A7), LEN(A7)=2), 1, IF(AND(A7=INT(A7), LEN(A7)=3), 2, LEN(A7) - FIND(".", A7) + 2) ) ), "") -> 1 | C7: Plant Studies | D7: =REPT(" ", B7*2) & C7 -> Plant Studies | E7: standard | J7: =MARVEL_Cost!C4 -> 5210451 | Q7: 2024 | R7: Labor | S7: MARVEL Project (Labor-adjusted Cost) | T7: Hanna, B. N., Gonzaga de Oliveira, R. G., Mohammad Al Dawood, K. A., Patterson, M. D., Abou Jaoude, A., & Garcia, S. (2024). Technoeconomic Evaluation of Microreactor Using Detailed Bottom-up Estimate (No. INL/RPT-24-80433-Rev000). Idaho National Laboratory (INL), Idaho Falls, ID (United States). | U7: https://inldigitallibrary.inl.gov/sites/sti/sti/Sort_129862.pdf | V7: MARVEL's data were updated | W7: No Learning | X7: =0.9*$J7 -> 4689405.9 | Y7: =1.5*J7 -> 7815676.5 | Z7: Lognormal | AA7: =0.9*K7 -> 0 | AB7: =1.3*K7 -> 0 | AC7: Lognormal | AD7: 0.1 | AE7: 1 | AF7: 0 | AG7: Truncated Normal
A8: 20 | B8: =IF(ISNUMBER(A8), IF(AND(A8=INT(A8), MOD(A8, 10) = 0), 0, IF(AND(A8=INT(A8), LEN(A8)=2), 1, IF(AND(A8=INT(A8), LEN(A8)=3), 2, LEN(A8) - FIND(".", A8) + 2) ) ), "") -> 0 | C8: Capitalized Direct Costs | D8: =REPT(" ", B8*2) & C8 -> Capitalized Direct Costs
A9: 21 | B9: =IF(ISNUMBER(A9), IF(AND(A9=INT(A9), MOD(A9, 10) = 0), 0, IF(AND(A9=INT(A9), LEN(A9)=2), 1, IF(AND(A9=INT(A9), LEN(A9)=3), 2, LEN(A9) - FIND(".", A9) + 2) ) ), "") -> 1 | C9: Structures and Improvements | D9: =REPT(" ", B9*2) & C9 -> Structures and Improvements
A10: 211 | B10: =IF(ISNUMBER(A10), IF(AND(A10=INT(A10), MOD(A10, 10) = 0), 0, IF(AND(A10=INT(A10), LEN(A10)=2), 1, IF(AND(A10=INT(A10), LEN(A10)=3), 2, LEN(A10) - FIND(".", A10) + 2) ) ), "") -> 2 | C10: Site Preparation/ Yard Work | D10: =REPT(" ", B10*2) & C10 -> Site Preparation/ Yard Work
A11: 211.1 | B11: =IF(ISNUMBER(A11), IF(AND(A11=INT(A11), MOD(A11, 10) = 0), 0, IF(AND(A11=INT(A11), LEN(A11)=2), 1, IF(AND(A11=INT(A11), LEN(A11)=3), 2, LEN(A11) - FIND(".", A11) + 2) ) ), "") -> 3 | C11: Cleaning and Grubbing | D11: =REPT(" ", B11*2) & C11 -> Cleaning and Grubbing | E11: standard | K11: =4408.18*1.33 -> 5862.8794 | L11: $/acres | M11: Land Area | O11: acres | Q11: 2024 | R11: Lab and Equip | S11: RSMeans software: a tool that primarily provides costs for non-nuclear work Nuclear Multiplier have been applied to adjust the costs for nuclear-site-related work | T11: GORDIAN. (2024). "RSMeans data. & Delene, J. G. and I. Hudson, C. R. (1993). Cost estimate guidelines for advanced nuclear power technologies. United States, Oak Ridge National Lab. (ORNL), Oak Ridge, TN (United States): Medium: ED; Size: 159 p. | U11: https://www.rsmeans.com/ & https://www.osti.gov/biblio/10176857 | W11: Onsite Learning | X11: =0.9*$J11 -> 0 | Y11: =1.5*J11 -> 0 | Z11: Lognormal | AA11: =0.9*K11 -> 5276.5915 | AB11: =1.3*K11 -> 7621.7432 | AC11: Lognormal | AD11: 0.1 | AE11: 1 | AF11: 0 | AG11: Truncated Normal
A12: 211.2 | B12: =IF(ISNUMBER(A12), IF(AND(A12=INT(A12), MOD(A12, 10) = 0), 0, IF(AND(A12=INT(A12), LEN(A12)=2), 1, IF(AND(A12=INT(A12), LEN(A12)=3), 2, LEN(A12) - FIND(".", A12) + 2) ) ), "") -> 3 | C12: Stripping Topsoil | D12: =REPT(" ", B12*2) & C12 -> Stripping Topsoil | E12: standard | K12: =2565.2*1.33 -> 3411.716 | L12: $/acres | M12: Land Area | O12: acres | Q12: 2024 | R12: Lab and Equip | W12: Onsite Learning | X12: =0.9*$J12 -> 0 | Y12: =1.5*J12 -> 0 | Z12: Lognormal | AA12: =0.9*K12 -> 3070.5444 | AB12: =1.3*K12 -> 4435.2308 | AC12: Lognormal | AD12: 0.1 | AE12: 1 | AF12: 0 | AG12: Truncated Normal
A13: 211.3 | B13: =IF(ISNUMBER(A13), IF(AND(A13=INT(A13), MOD(A13, 10) = 0), 0, IF(AND(A13=INT(A13), LEN(A13)=2), 1, IF(AND(A13=INT(A13), LEN(A13)=3), 2, LEN(A13) - FIND(".", A13) + 2) ) ), "") -> 3 | C13: Excavation | D13: =REPT(" ", B13*2) & C13 -> Excavation | E13: standard | K13: =22.86*1.4 -> 32.004 | L13: $/m^3 | M13: Excavation Volume | O13: m^3 | Q13: 2024 | R13: Lab and Equip | W13: Onsite Learning | X13: =0.9*$J13 -> 0 | Y13: =1.5*J13 -> 0 | Z13: Lognormal | AA13: =0.9*K13 -> 28.8036 | AB13: =1.3*K13 -> 41.6052 | AC13: Lognormal | AD13: 0.1 | AE13: 1 | AF13: 0 | AG13: Truncated Normal
A14: 211.4 | B14: =IF(ISNUMBER(A14), IF(AND(A14=INT(A14), MOD(A14, 10) = 0), 0, IF(AND(A14=INT(A14), LEN(A14)=2), 1, IF(AND(A14=INT(A14), LEN(A14)=3), 2, LEN(A14) - FIND(".", A14) + 2) ) ), "") -> 3 | C14: Roads | D14: =REPT(" ", B14*2) & C14 -> Roads | E14: standard | K14: =0.7*7873200*1.609/1000 -> 8867.5852 | L14: $/m | M14: GEN Road Length | O14: m | Q14: 2025 | R14: General | S14: MC30 Cost Estimation of Microreactor Facilities Inital Draft 5-6-2026.pdf, less 30% | W14: Onsite Learning | X14: =0.9*$J14 -> 0 | Y14: =1.5*J14 -> 0 | Z14: Lognormal | AA14: =0.9*K14 -> 7980.8266 | AB14: =1.3*K14 -> 11527.861 | AC14: Lognormal | AD14: 0.1 | AE14: 1 | AF14: 0 | AG14: Truncated Normal
A15: 211.9 | B15: =IF(ISNUMBER(A15), IF(AND(A15=INT(A15), MOD(A15, 10) = 0), 0, IF(AND(A15=INT(A15), LEN(A15)=2), 1, IF(AND(A15=INT(A15), LEN(A15)=3), 2, LEN(A15) - FIND(".", A15) + 2) ) ), "") -> 3 | C15: Security Fencing | D15: =REPT(" ", B15*2) & C15 -> Security Fencing
A16: 211.91 | B16: =IF(ISNUMBER(A16), IF(AND(A16=INT(A16), MOD(A16, 10) = 0), 0, IF(AND(A16=INT(A16), LEN(A16)=2), 1, IF(AND(A16=INT(A16), LEN(A16)=3), 2, LEN(A16) - FIND(".", A16) + 2) ) ), "") -> 4 | C16: Security Fencing Limited | D16: =REPT(" ", B16*2) & C16 -> Security Fencing Limited | E16: standard | K16: =0.7*273.38*3.2808 -> 627.83357 | L16: $/m | M16: Limited Perimeter | O16: m | Q16: 2025 | R16: General | S16: MC30 Cost Estimation of Microreactor Facilities Inital Draft 5-6-2026.pdf, less 30% | W16: Onsite Learning | X16: =0.9*$J16 -> 0 | Y16: =1.5*J16 -> 0 | Z16: Lognormal | AA16: =0.9*K16 -> 565.05022 | AB16: =1.3*K16 -> 816.18364 | AC16: Lognormal | AD16: 0.1 | AE16: 1 | AF16: 0 | AG16: Truncated Normal
A17: 211.93 | B17: =IF(ISNUMBER(A17), IF(AND(A17=INT(A17), MOD(A17, 10) = 0), 0, IF(AND(A17=INT(A17), LEN(A17)=2), 1, IF(AND(A17=INT(A17), LEN(A17)=3), 2, LEN(A17) - FIND(".", A17) + 2) ) ), "") -> 4 | C17: Security Fencing Protected | D17: =REPT(" ", B17*2) & C17 -> Security Fencing Protected | E17: standard | K17: =0.7*15183.17*3.2808 -> 34869.061 | L17: $/m | M17: Protected Perimeter | O17: m | Q17: 2025 | R17: General | S17: MC30 Cost Estimation of Microreactor Facilities Inital Draft 5-6-2026.pdf, less 30% | W17: Onsite Learning | X17: =0.9*$J17 -> 0 | Y17: =1.5*J17 -> 0 | Z17: Lognormal | AA17: =0.9*K17 -> 31382.155 | AB17: =1.3*K17 -> 45329.779 | AC17: Lognormal | AD17: 0.1 | AE17: 1 | AF17: 0 | AG17: Truncated Normal
A18: 212 | B18: =IF(ISNUMBER(A18), IF(AND(A18=INT(A18), MOD(A18, 10) = 0), 0, IF(AND(A18=INT(A18), LEN(A18)=2), 1, IF(AND(A18=INT(A18), LEN(A18)=3), 2, LEN(A18) - FIND(".", A18) + 2) ) ), "") -> 2 | C18: Reactor Island Civil Structures | D18: =REPT(" ", B18*2) & C18 -> Reactor Island Civil Structures
A19: 212.1 | B19: =IF(ISNUMBER(A19), IF(AND(A19=INT(A19), MOD(A19, 10) = 0), 0, IF(AND(A19=INT(A19), LEN(A19)=2), 1, IF(AND(A19=INT(A19), LEN(A19)=3), 2, LEN(A19) - FIND(".", A19) + 2) ) ), "") -> 3 | C19: Reactor Building Slab Roof | D19: =REPT(" ", B19*2) & C19 -> Reactor Building Slab Roof | E19: standard | K19: =1200 *1.53 -> 1836 | L19: $/m^3 | M19: Reactor Building Slab Roof Volume | O19: m^3 | Q19: 2024 | R19: Lab and Mat and Equip | S19: RSMeans software: a tool that primarily provides costs for non-nuclear work Nuclear Multiplier have been applied to adjust the costs for nuclear-site-related work | T19: GORDIAN. (2024). "RSMeans data. & Delene, J. G. and I. Hudson, C. R. (1993). Cost estimate guidelines for advanced nuclear power technologies. United States, Oak Ridge National Lab. (ORNL), Oak Ridge, TN (United States): Medium: ED; Size: 159 p. | U19: https://www.rsmeans.com/ & https://www.osti.gov/biblio/10176857 | W19: Onsite Learning | X19: =0.9*$J19 -> 0 | Y19: =1.5*J19 -> 0 | Z19: Lognormal | AA19: =0.9*K19 -> 1652.4 | AB19: =1.3*K19 -> 2386.8 | AC19: Lognormal | AD19: 0.1 | AE19: 1 | AF19: 0 | AG19: Truncated Normal
A20: 212.2 | B20: =IF(ISNUMBER(A20), IF(AND(A20=INT(A20), MOD(A20, 10) = 0), 0, IF(AND(A20=INT(A20), LEN(A20)=2), 1, IF(AND(A20=INT(A20), LEN(A20)=3), 2, LEN(A20) - FIND(".", A20) + 2) ) ), "") -> 3 | C20: Reactor Building Basement | D20: =REPT(" ", B20*2) & C20 -> Reactor Building Basement | E20: standard | K20: =943.9*1.53 -> 1444.167 | L20: $/m^3 | M20: Reactor Building Basement Volume | O20: m^3 | Q20: 2024 | R20: Lab and Mat and Equip | W20: Onsite Learning | X20: =0.9*$J20 -> 0 | Y20: =1.5*J20 -> 0 | Z20: Lognormal | AA20: =0.9*K20 -> 1299.7503 | AB20: =1.3*K20 -> 1877.4171 | AC20: Lognormal | AD20: 0.1 | AE20: 1 | AF20: 0 | AG20: Truncated Normal
A21: 212.3 | B21: =IF(ISNUMBER(A21), IF(AND(A21=INT(A21), MOD(A21, 10) = 0), 0, IF(AND(A21=INT(A21), LEN(A21)=2), 1, IF(AND(A21=INT(A21), LEN(A21)=3), 2, LEN(A21) - FIND(".", A21) + 2) ) ), "") -> 3 | C21: Reactor Building Walls | D21: =REPT(" ", B21*2) & C21 -> Reactor Building Walls | E21: standard | K21: =721.21*1.53 -> 1103.4513 | L21: $/m^3 | M21: Reactor Building Exterior Walls Volume | O21: m^3 | Q21: 2024 | R21: Lab and Mat and Equip | W21: Onsite Learning | X21: =0.9*$J21 -> 0 | Y21: =1.5*J21 -> 0 | Z21: Lognormal | AA21: =0.9*K21 -> 993.10617 | AB21: =1.3*K21 -> 1434.4867 | AC21: Lognormal | AD21: 0.1 | AE21: 1 | AF21: 0 | AG21: Truncated Normal
A22: 212.4 | B22: =IF(ISNUMBER(A22), IF(AND(A22=INT(A22), MOD(A22, 10) = 0), 0, IF(AND(A22=INT(A22), LEN(A22)=2), 1, IF(AND(A22=INT(A22), LEN(A22)=3), 2, LEN(A22) - FIND(".", A22) + 2) ) ), "") -> 3 | C22: Reactor Building Liner | D22: =REPT(" ", B22*2) & C22 -> Reactor Building Liner | E22: standard | K22: =60848829/9373 -> 6491.9267 | L22: $/m^2 | M22: Reactor Building Superstructure Area | N22: 9373 | O22: m^2 | P22: 1 | Q22: 2018 | R22: Lab and Mat and Equip | S22: Stewart W.R., Shirvan K., "Capital cost estimation for advanced nuclear power plants," Renewable and Sustainable Energy Reviews, Nov. 2021, 111880 | T22: Stewart W.R., Shirvan K., "Capital cost estimation for advanced nuclear power plants," Renewable and Sustainable Energy Reviews, Nov. 2021, 111880 | U22: https://doi.org/10.1016/j.rser.2021.111880 | W22: Onsite Learning | X22: =0.9*$J22 -> 0 | Y22: =1.5*J22 -> 0 | Z22: Lognormal | AA22: =0.9*K22 -> 5842.734 | AB22: =1.3*K22 -> 8439.5047 | AC22: Lognormal | AD22: 0.1 | AE22: 1 | AF22: 0 | AG22: Truncated Normal
A23: 212.5 | B23: =IF(ISNUMBER(A23), IF(AND(A23=INT(A23), MOD(A23, 10) = 0), 0, IF(AND(A23=INT(A23), LEN(A23)=2), 1, IF(AND(A23=INT(A23), LEN(A23)=3), 2, LEN(A23) - FIND(".", A23) + 2) ) ), "") -> 3 | C23: Reactor Building HVAC | D23: =REPT(" ", B23*2) & C23 -> Reactor Building HVAC | E23: standard | K23: =5917967/N23 -> 1731.9189 | L23: $/MWt | M23: Power MWt | N23: 3417 | O23: MWt | P23: 0.8 | Q23: 2018 | R23: Lab and Mat and Equip | S23: Stewart W.R., Shirvan K., "Capital cost estimation for advanced nuclear power plants," Renewable and Sustainable Energy Reviews, Nov. 2021, 111880 | T23: Stewart W.R., Shirvan K., "Capital cost estimation for advanced nuclear power plants," Renewable and Sustainable Energy Reviews, Nov. 2021, 111880 | U23: https://doi.org/10.1016/j.rser.2021.111880 | W23: Onsite Learning | X23: =0.9*$J23 -> 0 | Y23: =1.5*J23 -> 0 | Z23: Lognormal | AA23: =0.9*K23 -> 1558.727 | AB23: =1.3*K23 -> 2251.4946 | AC23: Lognormal | AD23: 0.1 | AE23: 1 | AF23: 0 | AG23: Truncated Normal
A24: 213 | B24: =IF(ISNUMBER(A24), IF(AND(A24=INT(A24), MOD(A24, 10) = 0), 0, IF(AND(A24=INT(A24), LEN(A24)=2), 1, IF(AND(A24=INT(A24), LEN(A24)=3), 2, LEN(A24) - FIND(".", A24) + 2) ) ), "") -> 2 | C24: Main Function Buildings | D24: =REPT(" ", B24*2) & C24 -> Main Function Buildings
A25: 213.1 | B25: =IF(ISNUMBER(A25), IF(AND(A25=INT(A25), MOD(A25, 10) = 0), 0, IF(AND(A25=INT(A25), LEN(A25)=2), 1, IF(AND(A25=INT(A25), LEN(A25)=3), 2, LEN(A25) - FIND(".", A25) + 2) ) ), "") -> 3 | C25: Energy conversion Building | D25: =REPT(" ", B25*2) & C25 -> Energy conversion Building
A26: 213.11 | B26: =IF(ISNUMBER(A26), IF(AND(A26=INT(A26), MOD(A26, 10) = 0), 0, IF(AND(A26=INT(A26), LEN(A26)=2), 1, IF(AND(A26=INT(A26), LEN(A26)=3), 2, LEN(A26) - FIND(".", A26) + 2) ) ), "") -> 4 | C26: Energy Conversion Building Slab Roof | D26: =REPT(" ", B26*2) & C26 -> Energy Conversion Building Slab Roof | E26: standard | K26: =1200 -> 1200 | L26: $/m^3 | M26: Turbine Building Slab Roof Volume | O26: m^3 | Q26: 2024 | R26: Lab and Mat and Equip | S26: RSMeans software: a tool that primarily provides costs for non-nuclear work | T26: GORDIAN. (2024). "RSMeans data. & Delene, J. G. and I. Hudson, C. R. (1993). Cost estimate guidelines for advanced nuclear power technologies. United States, Oak Ridge National Lab. (ORNL), Oak Ridge, TN (United States): Medium: ED; Size: 159 p. | U26: https://www.rsmeans.com/ & https://www.osti.gov/biblio/10176857 | W26: Onsite Learning | X26: =0.9*$J26 -> 0 | Y26: =1.5*J26 -> 0 | Z26: Lognormal | AA26: =0.9*K26 -> 1080 | AB26: =1.3*K26 -> 1560 | AC26: Lognormal | AD26: 0.1 | AE26: 1 | AF26: 0 | AG26: Truncated Normal
A27: 213.12 | B27: =IF(ISNUMBER(A27), IF(AND(A27=INT(A27), MOD(A27, 10) = 0), 0, IF(AND(A27=INT(A27), LEN(A27)=2), 1, IF(AND(A27=INT(A27), LEN(A27)=3), 2, LEN(A27) - FIND(".", A27) + 2) ) ), "") -> 4 | C27: Energy Conversion Building Basement | D27: =REPT(" ", B27*2) & C27 -> Energy Conversion Building Basement | E27: standard | K27: =943.9 -> 943.9 | L27: $/m^3 | M27: Turbine Building Basement Volume | O27: m^3 | Q27: 2024 | R27: Lab and Mat and Equip | W27: Onsite Learning | X27: =0.9*$J27 -> 0 | Y27: =1.5*J27 -> 0 | Z27: Lognormal | AA27: =0.9*K27 -> 849.51 | AB27: =1.3*K27 -> 1227.07 | AC27: Lognormal | AD27: 0.1 | AE27: 1 | AF27: 0 | AG27: Truncated Normal
A28: 213.13 | B28: =IF(ISNUMBER(A28), IF(AND(A28=INT(A28), MOD(A28, 10) = 0), 0, IF(AND(A28=INT(A28), LEN(A28)=2), 1, IF(AND(A28=INT(A28), LEN(A28)=3), 2, LEN(A28) - FIND(".", A28) + 2) ) ), "") -> 4 | C28: Energy Conversion Building Walls | D28: =REPT(" ", B28*2) & C28 -> Energy Conversion Building Walls | E28: standard | K28: =721.21 -> 721.21 | L28: $/m^3 | M28: Turbine Building Exterior Walls Volume | O28: m^3 | Q28: 2024 | R28: Lab and Mat and Equip | W28: Onsite Learning | X28: =0.9*$J28 -> 0 | Y28: =1.5*J28 -> 0 | Z28: Lognormal | AA28: =0.9*K28 -> 649.089 | AB28: =1.3*K28 -> 937.573 | AC28: Lognormal | AD28: 0.1 | AE28: 1 | AF28: 0 | AG28: Truncated Normal
A29: 213.2 | B29: =IF(ISNUMBER(A29), IF(AND(A29=INT(A29), MOD(A29, 10) = 0), 0, IF(AND(A29=INT(A29), LEN(A29)=2), 1, IF(AND(A29=INT(A29), LEN(A29)=3), 2, LEN(A29) - FIND(".", A29) + 2) ) ), "") -> 3 | C29: Control building | D29: =REPT(" ", B29*2) & C29 -> Control building
A30: 213.21 | B30: =IF(ISNUMBER(A30), IF(AND(A30=INT(A30), MOD(A30, 10) = 0), 0, IF(AND(A30=INT(A30), LEN(A30)=2), 1, IF(AND(A30=INT(A30), LEN(A30)=3), 2, LEN(A30) - FIND(".", A30) + 2) ) ), "") -> 4 | C30: Control Building Slab Roof | D30: =REPT(" ", B30*2) & C30 -> Control Building Slab Roof | E30: standard | K30: =1200 -> 1200 | L30: $/m^3 | M30: Control Building Slab Roof Volume | O30: m^3 | Q30: 2024 | R30: Lab and Mat and Equip | S30: RSMeans software: a tool that primarily provides costs for non-nuclear work | T30: GORDIAN. (2024). "RSMeans data. & Delene, J. G. and I. Hudson, C. R. (1993). Cost estimate guidelines for advanced nuclear power technologies. United States, Oak Ridge National Lab. (ORNL), Oak Ridge, TN (United States): Medium: ED; Size: 159 p. | U30: https://www.rsmeans.com/ & https://www.osti.gov/biblio/10176857 | W30: Onsite Learning | X30: =0.9*$J30 -> 0 | Y30: =1.5*J30 -> 0 | Z30: Lognormal | AA30: =0.9*K30 -> 1080 | AB30: =1.3*K30 -> 1560 | AC30: Lognormal | AD30: 0.1 | AE30: 1 | AF30: 0 | AG30: Truncated Normal
A31: 213.22 | B31: =IF(ISNUMBER(A31), IF(AND(A31=INT(A31), MOD(A31, 10) = 0), 0, IF(AND(A31=INT(A31), LEN(A31)=2), 1, IF(AND(A31=INT(A31), LEN(A31)=3), 2, LEN(A31) - FIND(".", A31) + 2) ) ), "") -> 4 | C31: Control Building Basement | D31: =REPT(" ", B31*2) & C31 -> Control Building Basement | E31: standard | K31: =943.9 -> 943.9 | L31: $/m^3 | M31: Control Building Basement Volume | O31: m^3 | Q31: 2024 | R31: Lab and Mat and Equip | W31: Onsite Learning | X31: =0.9*$J31 -> 0 | Y31: =1.5*J31 -> 0 | Z31: Lognormal | AA31: =0.9*K31 -> 849.51 | AB31: =1.3*K31 -> 1227.07 | AC31: Lognormal | AD31: 0.1 | AE31: 1 | AF31: 0 | AG31: Truncated Normal
A32: 213.23 | B32: =IF(ISNUMBER(A32), IF(AND(A32=INT(A32), MOD(A32, 10) = 0), 0, IF(AND(A32=INT(A32), LEN(A32)=2), 1, IF(AND(A32=INT(A32), LEN(A32)=3), 2, LEN(A32) - FIND(".", A32) + 2) ) ), "") -> 4 | C32: Control Building Walls | D32: =REPT(" ", B32*2) & C32 -> Control Building Walls | E32: standard | K32: =721.21 -> 721.21 | L32: $/m^3 | M32: Control Building Exterior Walls Volume | O32: m^3 | Q32: 2024 | R32: Lab and Mat and Equip | W32: Onsite Learning | X32: =0.9*$J32 -> 0 | Y32: =1.5*J32 -> 0 | Z32: Lognormal | AA32: =0.9*K32 -> 649.089 | AB32: =1.3*K32 -> 937.573 | AC32: Lognormal | AD32: 0.1 | AE32: 1 | AF32: 0 | AG32: Truncated Normal
A33: 213.3 | B33: =IF(ISNUMBER(A33), IF(AND(A33=INT(A33), MOD(A33, 10) = 0), 0, IF(AND(A33=INT(A33), LEN(A33)=2), 1, IF(AND(A33=INT(A33), LEN(A33)=3), 2, LEN(A33) - FIND(".", A33) + 2) ) ), "") -> 3 | C33: Integrated Heat Exchanger Building | D33: =REPT(" ", B33*2) & C33 -> Integrated Heat Exchanger Building | F33: reactor type | G33: GCMR
A34: 213.31 | B34: =IF(ISNUMBER(A34), IF(AND(A34=INT(A34), MOD(A34, 10) = 0), 0, IF(AND(A34=INT(A34), LEN(A34)=2), 1, IF(AND(A34=INT(A34), LEN(A34)=3), 2, LEN(A34) - FIND(".", A34) + 2) ) ), "") -> 4 | C34: Integrated Heat Exchanger Building Slab Roof | D34: =REPT(" ", B34*2) & C34 -> Integrated Heat Exchanger Building Slab Roof | E34: standard | F34: reactor type | G34: GCMR | K34: =1200 -> 1200 | L34: $/m^3 | M34: Integrated Heat Exchanger Building Slab Roof Volume | O34: m^3 | Q34: 2024 | R34: Lab and Mat and Equip | S34: RSMeans software: a tool that primarily provides costs for non-nuclear work | T34: GORDIAN. (2024). "RSMeans data. & Delene, J. G. and I. Hudson, C. R. (1993). Cost estimate guidelines for advanced nuclear power technologies. United States, Oak Ridge National Lab. (ORNL), Oak Ridge, TN (United States): Medium: ED; Size: 159 p. | U34: https://www.rsmeans.com/ & https://www.osti.gov/biblio/10176857 | W34: Onsite Learning | X34: =0.9*$J34 -> 0 | Y34: =1.5*J34 -> 0 | Z34: Lognormal | AA34: =0.9*K34 -> 1080 | AB34: =1.3*K34 -> 1560 | AC34: Lognormal | AD34: 0.1 | AE34: 1 | AF34: 0 | AG34: Truncated Normal
A35: 213.32 | B35: =IF(ISNUMBER(A35), IF(AND(A35=INT(A35), MOD(A35, 10) = 0), 0, IF(AND(A35=INT(A35), LEN(A35)=2), 1, IF(AND(A35=INT(A35), LEN(A35)=3), 2, LEN(A35) - FIND(".", A35) + 2) ) ), "") -> 4 | C35: Integrated Heat Exchanger Building Basement | D35: =REPT(" ", B35*2) & C35 -> Integrated Heat Exchanger Building Basement | E35: standard | F35: reactor type | G35: GCMR | K35: =943.9 -> 943.9 | L35: $/m^3 | M35: Integrated Heat Exchanger Building Basement Volume | O35: m^3 | Q35: 2024 | R35: Lab and Mat and Equip | W35: Onsite Learning | X35: =0.9*$J35 -> 0 | Y35: =1.5*J35 -> 0 | Z35: Lognormal | AA35: =0.9*K35 -> 849.51 | AB35: =1.3*K35 -> 1227.07 | AC35: Lognormal | AD35: 0.1 | AE35: 1 | AF35: 0 | AG35: Truncated Normal
A36: 213.33 | B36: =IF(ISNUMBER(A36), IF(AND(A36=INT(A36), MOD(A36, 10) = 0), 0, IF(AND(A36=INT(A36), LEN(A36)=2), 1, IF(AND(A36=INT(A36), LEN(A36)=3), 2, LEN(A36) - FIND(".", A36) + 2) ) ), "") -> 4 | C36: Integrated Heat Exchanger Building Walls | D36: =REPT(" ", B36*2) & C36 -> Integrated Heat Exchanger Building Walls | E36: standard | F36: reactor type | G36: GCMR | K36: =721.21 -> 721.21 | L36: $/m^3 | M36: Integrated Heat Exchanger Building Exterior Walls Volume | O36: m^3 | Q36: 2024 | R36: Lab and Mat and Equip | W36: Onsite Learning | X36: =0.9*$J36 -> 0 | Y36: =1.5*J36 -> 0 | Z36: Lognormal | AA36: =0.9*K36 -> 649.089 | AB36: =1.3*K36 -> 937.573 | AC36: Lognormal | AD36: 0.1 | AE36: 1 | AF36: 0 | AG36: Truncated Normal
A37: 213.34 | B37: =IF(ISNUMBER(A37), IF(AND(A37=INT(A37), MOD(A37, 10) = 0), 0, IF(AND(A37=INT(A37), LEN(A37)=2), 1, IF(AND(A37=INT(A37), LEN(A37)=3), 2, LEN(A37) - FIND(".", A37) + 2) ) ), "") -> 4 | C37: Integrated Heat Exchanger Building Liner | D37: =REPT(" ", B37*2) & C37 -> Integrated Heat Exchanger Building Liner | E37: standard | F37: reactor type | G37: GCMR | K37: =60848829/9373 -> 6491.9267 | L37: $/m^2 | M37: Integrated Heat Exchanger Building Superstructure Area | N37: 9373 | O37: m^2 | P37: 1 | Q37: 2018 | R37: Lab and Mat and Equip | S37: Stewart W.R., Shirvan K., "Capital cost estimation for advanced nuclear power plants," Renewable and Sustainable Energy Reviews, Nov. 2021, 111880 | T37: Stewart W.R., Shirvan K., "Capital cost estimation for advanced nuclear power plants," Renewable and Sustainable Energy Reviews, Nov. 2021, 111880 | U37: https://doi.org/10.1016/j.rser.2021.111880 | W37: Onsite Learning | X37: =0.9*$J37 -> 0 | Y37: =1.5*J37 -> 0 | Z37: Lognormal | AA37: =0.9*K37 -> 5842.734 | AB37: =1.3*K37 -> 8439.5047 | AC37: Lognormal | AD37: 0.1 | AE37: 1 | AF37: 0 | AG37: Truncated Normal
A38: 214 | B38: =IF(ISNUMBER(A38), IF(AND(A38=INT(A38), MOD(A38, 10) = 0), 0, IF(AND(A38=INT(A38), LEN(A38)=2), 1, IF(AND(A38=INT(A38), LEN(A38)=3), 2, LEN(A38) - FIND(".", A38) + 2) ) ), "") -> 2 | C38: Buildings to Support Main Function | D38: =REPT(" ", B38*2) & C38 -> Buildings to Support Main Function
A39: 214.1 | B39: =IF(ISNUMBER(A39), IF(AND(A39=INT(A39), MOD(A39, 10) = 0), 0, IF(AND(A39=INT(A39), LEN(A39)=2), 1, IF(AND(A39=INT(A39), LEN(A39)=3), 2, LEN(A39) - FIND(".", A39) + 2) ) ), "") -> 3 | C39: Fuel Management Buildings | D39: =REPT(" ", B39*2) & C39 -> Fuel Management Buildings
A40: 214.11 | B40: =IF(ISNUMBER(A40), IF(AND(A40=INT(A40), MOD(A40, 10) = 0), 0, IF(AND(A40=INT(A40), LEN(A40)=2), 1, IF(AND(A40=INT(A40), LEN(A40)=3), 2, LEN(A40) - FIND(".", A40) + 2) ) ), "") -> 4 | C40: Refueling Building | D40: =REPT(" ", B40*2) & C40 -> Refueling Building
A41: 214.111 | B41: =IF(ISNUMBER(A41), IF(AND(A41=INT(A41), MOD(A41, 10) = 0), 0, IF(AND(A41=INT(A41), LEN(A41)=2), 1, IF(AND(A41=INT(A41), LEN(A41)=3), 2, LEN(A41) - FIND(".", A41) + 2) ) ), "") -> 5 | C41: Refueling Building Slab Roof | D41: =REPT(" ", B41*2) & C41 -> Refueling Building Slab Roof | E41: standard | K41: =1200 *1.53 -> 1836 | L41: $/m^3 | M41: Refueling Building Slab Roof Volume | O41: m^3 | Q41: 2024 | R41: Lab and Mat and Equip | S41: RSMeans software: a tool that primarily provides costs for non-nuclear work Nuclear Multiplier have been applied to adjust the costs for nuclear-site-related work | T41: GORDIAN. (2024). "RSMeans data. & Delene, J. G. and I. Hudson, C. R. (1993). Cost estimate guidelines for advanced nuclear power technologies. United States, Oak Ridge National Lab. (ORNL), Oak Ridge, TN (United States): Medium: ED; Size: 159 p. | U41: https://www.rsmeans.com/ & https://www.osti.gov/biblio/10176857 | W41: Onsite Learning | X41: =0.9*$J41 -> 0 | Y41: =1.5*J41 -> 0 | AA41: =0.9*K41 -> 1652.4 | AB41: =1.3*K41 -> 2386.8 | AC41: Lognormal | AD41: 0.1 | AE41: 1 | AF41: 0 | AG41: Truncated Normal
A42: 214.112 | B42: =IF(ISNUMBER(A42), IF(AND(A42=INT(A42), MOD(A42, 10) = 0), 0, IF(AND(A42=INT(A42), LEN(A42)=2), 1, IF(AND(A42=INT(A42), LEN(A42)=3), 2, LEN(A42) - FIND(".", A42) + 2) ) ), "") -> 5 | C42: Refueling Building Basement | D42: =REPT(" ", B42*2) & C42 -> Refueling Building Basement | E42: standard | K42: =943.9*1.53 -> 1444.167 | L42: $/m^3 | M42: Refueling Building Basement Volume | O42: m^3 | Q42: 2024 | R42: Lab and Mat and Equip | W42: Onsite Learning | X42: =0.9*$J42 -> 0 | Y42: =1.5*J42 -> 0 | Z42: Lognormal | AA42: =0.9*K42 -> 1299.7503 | AB42: =1.3*K42 -> 1877.4171 | AC42: Lognormal | AD42: 0.1 | AE42: 1 | AF42: 0 | AG42: Truncated Normal
A43: 214.113 | B43: =IF(ISNUMBER(A43), IF(AND(A43=INT(A43), MOD(A43, 10) = 0), 0, IF(AND(A43=INT(A43), LEN(A43)=2), 1, IF(AND(A43=INT(A43), LEN(A43)=3), 2, LEN(A43) - FIND(".", A43) + 2) ) ), "") -> 5 | C43: Refueling Building Walls | D43: =REPT(" ", B43*2) & C43 -> Refueling Building Walls | E43: standard | K43: =721.21*1.53 -> 1103.4513 | L43: $/m^3 | M43: Refueling Building Exterior Walls Volume | O43: m^3 | Q43: 2024 | R43: Lab and Mat and Equip | W43: Onsite Learning | X43: =0.9*$J43 -> 0 | Y43: =1.5*J43 -> 0 | Z43: Lognormal | AA43: =0.9*K43 -> 993.10617 | AB43: =1.3*K43 -> 1434.4867 | AC43: Lognormal | AD43: 0.1 | AE43: 1 | AF43: 0 | AG43: Truncated Normal
A44: 214.12 | B44: =IF(ISNUMBER(A44), IF(AND(A44=INT(A44), MOD(A44, 10) = 0), 0, IF(AND(A44=INT(A44), LEN(A44)=2), 1, IF(AND(A44=INT(A44), LEN(A44)=3), 2, LEN(A44) - FIND(".", A44) + 2) ) ), "") -> 4 | C44: Spent Fuel Building | D44: =REPT(" ", B44*2) & C44 -> Spent Fuel Building
A45: 214.121 | B45: =IF(ISNUMBER(A45), IF(AND(A45=INT(A45), MOD(A45, 10) = 0), 0, IF(AND(A45=INT(A45), LEN(A45)=2), 1, IF(AND(A45=INT(A45), LEN(A45)=3), 2, LEN(A45) - FIND(".", A45) + 2) ) ), "") -> 5 | C45: Spent Fuel Building Slab Roof | D45: =REPT(" ", B45*2) & C45 -> Spent Fuel Building Slab Roof | E45: standard | K45: =1200 *1.53 -> 1836 | L45: $/m^3 | M45: Spent Fuel Building Slab Roof Volume | O45: m^3 | Q45: 2024 | R45: Lab and Mat and Equip | S45: RSMeans software: a tool that primarily provides costs for non-nuclear work Nuclear Multiplier have been applied to adjust the costs for nuclear-site-related work | T45: GORDIAN. (2024). "RSMeans data. & Delene, J. G. and I. Hudson, C. R. (1993). Cost estimate guidelines for advanced nuclear power technologies. United States, Oak Ridge National Lab. (ORNL), Oak Ridge, TN (United States): Medium: ED; Size: 159 p. | U45: https://www.rsmeans.com/ & https://www.osti.gov/biblio/10176857 | W45: Onsite Learning | X45: =0.9*$J45 -> 0 | Y45: =1.5*J45 -> 0 | Z45: Lognormal | AA45: =0.9*K45 -> 1652.4 | AB45: =1.3*K45 -> 2386.8 | AC45: Lognormal | AD45: 0.1 | AE45: 1 | AF45: 0 | AG45: Truncated Normal
A46: 214.122 | B46: =IF(ISNUMBER(A46), IF(AND(A46=INT(A46), MOD(A46, 10) = 0), 0, IF(AND(A46=INT(A46), LEN(A46)=2), 1, IF(AND(A46=INT(A46), LEN(A46)=3), 2, LEN(A46) - FIND(".", A46) + 2) ) ), "") -> 5 | C46: Spent Fuel Building Basement | D46: =REPT(" ", B46*2) & C46 -> Spent Fuel Building Basement | E46: standard | K46: =943.9*1.53 -> 1444.167 | L46: $/m^3 | M46: Spent Fuel Building Basement Volume | O46: m^3 | Q46: 2024 | R46: Lab and Mat and Equip | W46: Onsite Learning | X46: =0.9*$J46 -> 0 | Y46: =1.5*J46 -> 0 | Z46: Lognormal | AA46: =0.9*K46 -> 1299.7503 | AB46: =1.3*K46 -> 1877.4171 | AC46: Lognormal | AD46: 0.1 | AE46: 1 | AF46: 0 | AG46: Truncated Normal
A47: 214.123 | B47: =IF(ISNUMBER(A47), IF(AND(A47=INT(A47), MOD(A47, 10) = 0), 0, IF(AND(A47=INT(A47), LEN(A47)=2), 1, IF(AND(A47=INT(A47), LEN(A47)=3), 2, LEN(A47) - FIND(".", A47) + 2) ) ), "") -> 5 | C47: Spent Fuel Building Walls | D47: =REPT(" ", B47*2) & C47 -> Spent Fuel Building Walls | E47: standard | K47: =721.21*1.53 -> 1103.4513 | L47: $/m^3 | M47: Spent Fuel Building Exterior Walls Volume | O47: m^3 | Q47: 2024 | R47: Lab and Mat and Equip | W47: Onsite Learning | X47: =0.9*$J47 -> 0 | Y47: =1.5*J47 -> 0 | Z47: Lognormal | AA47: =0.9*K47 -> 993.10617 | AB47: =1.3*K47 -> 1434.4867 | AC47: Lognormal | AD47: 0.1 | AE47: 1 | AF47: 0 | AG47: Truncated Normal
A48: 214.2 | B48: =IF(ISNUMBER(A48), IF(AND(A48=INT(A48), MOD(A48, 10) = 0), 0, IF(AND(A48=INT(A48), LEN(A48)=2), 1, IF(AND(A48=INT(A48), LEN(A48)=3), 2, LEN(A48) - FIND(".", A48) + 2) ) ), "") -> 3 | C48: Cool down buildings | D48: =REPT(" ", B48*2) & C48 -> Cool down buildings
A49: 214.21 | B49: =IF(ISNUMBER(A49), IF(AND(A49=INT(A49), MOD(A49, 10) = 0), 0, IF(AND(A49=INT(A49), LEN(A49)=2), 1, IF(AND(A49=INT(A49), LEN(A49)=3), 2, LEN(A49) - FIND(".", A49) + 2) ) ), "") -> 4 | C49: Cool down building | D49: =REPT(" ", B49*2) & C49 -> Cool down building | E49: standard | J49: =0.7*4708424 -> 3295896.8 | Q49: 2025 | R49: Lab and Mat and Equip | S49: fixed cost for now - could work on scaling | T49: MC30 Cost Estimation of Microreactor Facilities Rev 1 Draft Backup Info 8-5-2026.xlsx, less 30% | W49: Onsite Learning | X49: =0.9*$J49 -> 2966307.1 | Y49: =1.5*J49 -> 4943845.2 | Z49: Lognormal | AA49: =0.9*K49 -> 0 | AB49: =1.3*K49 -> 0 | AC49: Lognormal | AD49: 0.1 | AE49: 1 | AF49: 0 | AG49: Truncated Normal
A50: 214.3 | B50: =IF(ISNUMBER(A50), IF(AND(A50=INT(A50), MOD(A50, 10) = 0), 0, IF(AND(A50=INT(A50), LEN(A50)=2), 1, IF(AND(A50=INT(A50), LEN(A50)=3), 2, LEN(A50) - FIND(".", A50) + 2) ) ), "") -> 3 | C50: Security buildings | D50: =REPT(" ", B50*2) & C50 -> Security buildings
A51: 214.31 | B51: =IF(ISNUMBER(A51), IF(AND(A51=INT(A51), MOD(A51, 10) = 0), 0, IF(AND(A51=INT(A51), LEN(A51)=2), 1, IF(AND(A51=INT(A51), LEN(A51)=3), 2, LEN(A51) - FIND(".", A51) + 2) ) ), "") -> 4 | C51: Guard station | D51: =REPT(" ", B51*2) & C51 -> Guard station | E51: standard | J51: =0.7*1681584 -> 1177108.8 | Q51: 2025 | R51: Lab and Mat and Equip | T51: MC30 Cost Estimation of Microreactor Facilities Rev 1 Draft Backup Info 8-5-2026.xlsx, less 30% | W51: Onsite Learning | X51: =0.9*$J51 -> 1059397.9 | Y51: =1.5*J51 -> 1765663.2 | Z51: Lognormal | AA51: =0.9*K51 -> 0 | AB51: =1.3*K51 -> 0 | AC51: Lognormal | AD51: 0.1 | AE51: 1 | AF51: 0 | AG51: Truncated Normal
A52: 214.4 | B52: =IF(ISNUMBER(A52), IF(AND(A52=INT(A52), MOD(A52, 10) = 0), 0, IF(AND(A52=INT(A52), LEN(A52)=2), 1, IF(AND(A52=INT(A52), LEN(A52)=3), 2, LEN(A52) - FIND(".", A52) + 2) ) ), "") -> 3 | C52: Staff support buildings | D52: =REPT(" ", B52*2) & C52 -> Staff support buildings
A53: 214.41 | B53: =IF(ISNUMBER(A53), IF(AND(A53=INT(A53), MOD(A53, 10) = 0), 0, IF(AND(A53=INT(A53), LEN(A53)=2), 1, IF(AND(A53=INT(A53), LEN(A53)=3), 2, LEN(A53) - FIND(".", A53) + 2) ) ), "") -> 4 | C53: Staff quarters | D53: =REPT(" ", B53*2) & C53 -> Staff quarters | E53: standard | J53: =0.7*952657 -> 666859.9 | Q53: 2025 | R53: Lab and Mat and Equip | S53: fixed cost for now - could work on scaling | T53: MC30 Cost Estimation of Microreactor Facilities Rev 1 Draft Backup Info 8-5-2026.xlsx, less 30% | W53: Onsite Learning | X53: =0.9*$J53 -> 600173.91 | Y53: =1.5*J53 -> 1000289.8 | Z53: Lognormal | AA53: =0.9*K53 -> 0 | AB53: =1.3*K53 -> 0 | AC53: Lognormal | AD53: 0.1 | AE53: 1 | AF53: 0 | AG53: Truncated Normal
A54: 214.7 | B54: =IF(ISNUMBER(A54), IF(AND(A54=INT(A54), MOD(A54, 10) = 0), 0, IF(AND(A54=INT(A54), LEN(A54)=2), 1, IF(AND(A54=INT(A54), LEN(A54)=3), 2, LEN(A54) - FIND(".", A54) + 2) ) ), "") -> 3 | C54: Emergency and Start-up Power Systems Building | D54: =REPT(" ", B54*2) & C54 -> Emergency and Start-up Power Systems Building
A55: 214.71 | B55: =IF(ISNUMBER(A55), IF(AND(A55=INT(A55), MOD(A55, 10) = 0), 0, IF(AND(A55=INT(A55), LEN(A55)=2), 1, IF(AND(A55=INT(A55), LEN(A55)=3), 2, LEN(A55) - FIND(".", A55) + 2) ) ), "") -> 4 | C55: Emergency Building | D55: =REPT(" ", B55*2) & C55 -> Emergency Building
A56: 214.711 | B56: =IF(ISNUMBER(A56), IF(AND(A56=INT(A56), MOD(A56, 10) = 0), 0, IF(AND(A56=INT(A56), LEN(A56)=2), 1, IF(AND(A56=INT(A56), LEN(A56)=3), 2, LEN(A56) - FIND(".", A56) + 2) ) ), "") -> 5 | C56: Emergency Building Slab Roof | D56: =REPT(" ", B56*2) & C56 -> Emergency Building Slab Roof | E56: standard | K56: =1200 -> 1200 | L56: $/m^3 | M56: Emergency Building Slab Roof Volume | O56: m^3 | Q56: 2024 | R56: Lab and Mat and Equip | S56: RSMeans software: a tool that primarily provides costs for non-nuclear work | T56: GORDIAN. (2024). "RSMeans data. & Delene, J. G. and I. Hudson, C. R. (1993). Cost estimate guidelines for advanced nuclear power technologies. United States, Oak Ridge National Lab. (ORNL), Oak Ridge, TN (United States): Medium: ED; Size: 159 p. | U56: https://www.rsmeans.com/ & https://www.osti.gov/biblio/10176857 | W56: Onsite Learning | X56: =0.9*$J56 -> 0 | Y56: =1.5*J56 -> 0 | Z56: Lognormal | AA56: =0.9*K56 -> 1080 | AB56: =1.3*K56 -> 1560 | AC56: Lognormal | AD56: 0.1 | AE56: 1 | AF56: 0 | AG56: Truncated Normal
A57: 214.712 | B57: =IF(ISNUMBER(A57), IF(AND(A57=INT(A57), MOD(A57, 10) = 0), 0, IF(AND(A57=INT(A57), LEN(A57)=2), 1, IF(AND(A57=INT(A57), LEN(A57)=3), 2, LEN(A57) - FIND(".", A57) + 2) ) ), "") -> 5 | C57: Emergency Building Basement | D57: =REPT(" ", B57*2) & C57 -> Emergency Building Basement | E57: standard | K57: =943.9 -> 943.9 | L57: $/m^3 | M57: Emergency Building Basement Volume | O57: m^3 | Q57: 2024 | R57: Lab and Mat and Equip | W57: Onsite Learning | X57: =0.9*$J57 -> 0 | Y57: =1.5*J57 -> 0 | Z57: Lognormal | AA57: =0.9*K57 -> 849.51 | AB57: =1.3*K57 -> 1227.07 | AC57: Lognormal | AD57: 0.1 | AE57: 1 | AF57: 0 | AG57: Truncated Normal
A58: 214.713 | B58: =IF(ISNUMBER(A58), IF(AND(A58=INT(A58), MOD(A58, 10) = 0), 0, IF(AND(A58=INT(A58), LEN(A58)=2), 1, IF(AND(A58=INT(A58), LEN(A58)=3), 2, LEN(A58) - FIND(".", A58) + 2) ) ), "") -> 5 | C58: Emergency Building Walls | D58: =REPT(" ", B58*2) & C58 -> Emergency Building Walls | E58: standard | K58: =721.21 -> 721.21 | L58: $/m^3 | M58: Emergency Building Exterior Walls Volume | O58: m^3 | Q58: 2024 | R58: Lab and Mat and Equip | W58: Onsite Learning | X58: =0.9*$J58 -> 0 | Y58: =1.5*J58 -> 0 | Z58: Lognormal | AA58: =0.9*K58 -> 649.089 | AB58: =1.3*K58 -> 937.573 | AC58: Lognormal | AD58: 0.1 | AE58: 1 | AF58: 0 | AG58: Truncated Normal
A59: 214.72 | B59: =IF(ISNUMBER(A59), IF(AND(A59=INT(A59), MOD(A59, 10) = 0), 0, IF(AND(A59=INT(A59), LEN(A59)=2), 1, IF(AND(A59=INT(A59), LEN(A59)=3), 2, LEN(A59) - FIND(".", A59) + 2) ) ), "") -> 4 | C59: Backup Power Outdoor | D59: =REPT(" ", B59*2) & C59 -> Backup Power Outdoor
A60: 214.721 | B60: =IF(ISNUMBER(A60), IF(AND(A60=INT(A60), MOD(A60, 10) = 0), 0, IF(AND(A60=INT(A60), LEN(A60)=2), 1, IF(AND(A60=INT(A60), LEN(A60)=3), 2, LEN(A60) - FIND(".", A60) + 2) ) ), "") -> 5 | C60: Diesel Generator | D60: =REPT(" ", B60*2) & C60 -> Diesel Generator | E60: standard | K60: =MARVEL_Cost!C11/N60 -> 2717311.6 | L60: $/MWt | M60: Power MWt | N60: ='Design Variables'!B3/1000 -> 0.083 | O60: MWt | P60: 0.7 | Q60: 2024 | R60: Equipment | S60: MARVEL (for the cost of the diesel generator) The exponent is based on the work by Koruoush considering cost scaling from nuclear ad non nuclear power plants. When using the power as scaling variable, the exponent ranges between 0..6 and 0.8 so 0.7 is used here | T60: Hanna, B. N., Gonzaga de Oliveira, R. G., Mohammad Al Dawood, K. A., Patterson, M. D., Abou Jaoude, A., & Garcia, S. (2024). Technoeconomic Evaluation of Microreactor Using Detailed Bottom-up Estimate (No. INL/RPT-24-80433-Rev000). Idaho National Laboratory (INL), Idaho Falls, ID (United States). Stewart, W. R., & Shirvan, K. (2022). Capital cost estimation for advanced nuclear power plants. Renewable and Sustainable Energy Reviews, 155, 111880. | U60: https://inldigitallibrary.inl.gov/sites/sti/sti/Sort_129862.pdf https://www.sciencedirect.com/science/article/pii/S1364032121011473 | W60: Factory Other | X60: =0.9*$J60 -> 0 | Y60: =1.5*J60 -> 0 | Z60: Lognormal | AA60: =0.9*K60 -> 2445580.4 | AB60: =1.3*K60 -> 3532505 | AC60: Lognormal | AD60: 0.1 | AE60: 1 | AF60: 0 | AG60: Truncated Normal
A61: 214.722 | B61: =IF(ISNUMBER(A61), IF(AND(A61=INT(A61), MOD(A61, 10) = 0), 0, IF(AND(A61=INT(A61), LEN(A61)=2), 1, IF(AND(A61=INT(A61), LEN(A61)=3), 2, LEN(A61) - FIND(".", A61) + 2) ) ), "") -> 5 | C61: Diesel Generator Concrete Pad | D61: =REPT(" ", B61*2) & C61 -> Diesel Generator Concrete Pad | E61: standard | J61: =0.7*29761 -> 20832.7 | Q61: 2025 | R61: Lab and Mat and Equip | T61: MC30 Cost Estimation of Microreactor Facilities Rev 1 Draft Backup Info 8-5-2026.xlsx, less 30% | W61: Onsite Learning | Z61: Lognormal | AA61: =0.9*K61 -> 0 | AB61: =1.3*K61 -> 0 | AC61: Lognormal | AD61: 0.2 | AE61: 1 | AF61: 0 | AG61: Truncated Normal
A62: 214.8 | B62: =IF(ISNUMBER(A62), IF(AND(A62=INT(A62), MOD(A62, 10) = 0), 0, IF(AND(A62=INT(A62), LEN(A62)=2), 1, IF(AND(A62=INT(A62), LEN(A62)=3), 2, LEN(A62) - FIND(".", A62) + 2) ) ), "") -> 3 | C62: Auxilliary Building | D62: =REPT(" ", B62*2) & C62 -> Auxilliary Building
A63: 214.81 | B63: =IF(ISNUMBER(A63), IF(AND(A63=INT(A63), MOD(A63, 10) = 0), 0, IF(AND(A63=INT(A63), LEN(A63)=2), 1, IF(AND(A63=INT(A63), LEN(A63)=3), 2, LEN(A63) - FIND(".", A63) + 2) ) ), "") -> 4 | C63: Maniplator Building | D63: =REPT(" ", B63*2) & C63 -> Maniplator Building
A64: 214.811 | B64: =IF(ISNUMBER(A64), IF(AND(A64=INT(A64), MOD(A64, 10) = 0), 0, IF(AND(A64=INT(A64), LEN(A64)=2), 1, IF(AND(A64=INT(A64), LEN(A64)=3), 2, LEN(A64) - FIND(".", A64) + 2) ) ), "") -> 5 | C64: Manipulator Building Slab Roof | D64: =REPT(" ", B64*2) & C64 -> Manipulator Building Slab Roof | E64: standard | K64: =1200 -> 1200 | L64: $/m^3 | M64: Manipulator Building Slab Roof Volume | O64: m^3 | Q64: 2024 | R64: Lab and Mat and Equip | S64: RSMeans software: a tool that primarily provides costs for non-nuclear work | T64: GORDIAN. (2024). "RSMeans data. & Delene, J. G. and I. Hudson, C. R. (1993). Cost estimate guidelines for advanced nuclear power technologies. United States, Oak Ridge National Lab. (ORNL), Oak Ridge, TN (United States): Medium: ED; Size: 159 p. | U64: https://www.rsmeans.com/ & https://www.osti.gov/biblio/10176857 | V64: Added a custom building for GCMR based on CAD drawing | W64: Onsite Learning | X64: =0.9*$J64 -> 0 | Y64: =1.5*J64 -> 0 | Z64: Lognormal | AA64: =0.9*K64 -> 1080 | AB64: =1.3*K64 -> 1560 | AC64: Lognormal | AD64: 0.1 | AE64: 1 | AF64: 0 | AG64: Truncated Normal
A65: 214.812 | B65: =IF(ISNUMBER(A65), IF(AND(A65=INT(A65), MOD(A65, 10) = 0), 0, IF(AND(A65=INT(A65), LEN(A65)=2), 1, IF(AND(A65=INT(A65), LEN(A65)=3), 2, LEN(A65) - FIND(".", A65) + 2) ) ), "") -> 5 | C65: ManipulatorBuilding Basement | D65: =REPT(" ", B65*2) & C65 -> ManipulatorBuilding Basement | E65: standard | K65: =943.9 -> 943.9 | L65: $/m^3 | M65: Manipulator Building Basement Volume | O65: m^3 | Q65: 2024 | R65: Lab and Mat and Equip | W65: Onsite Learning | X65: =0.9*$J65 -> 0 | Y65: =1.5*J65 -> 0 | Z65: Lognormal | AA65: =0.9*K65 -> 849.51 | AB65: =1.3*K65 -> 1227.07 | AC65: Lognormal | AD65: 0.1 | AE65: 1 | AF65: 0 | AG65: Truncated Normal
A66: 214.813 | B66: =IF(ISNUMBER(A66), IF(AND(A66=INT(A66), MOD(A66, 10) = 0), 0, IF(AND(A66=INT(A66), LEN(A66)=2), 1, IF(AND(A66=INT(A66), LEN(A66)=3), 2, LEN(A66) - FIND(".", A66) + 2) ) ), "") -> 5 | C66: Manipulator Building Exterior Walls | D66: =REPT(" ", B66*2) & C66 -> Manipulator Building Exterior Walls | E66: standard | K66: =721.21 -> 721.21 | L66: $/m^3 | M66: Manipulator Building Exterior Walls Volume | O66: m^3 | Q66: 2024 | R66: Lab and Mat and Equip | W66: Onsite Learning | X66: =0.9*$J66 -> 0 | Y66: =1.5*J66 -> 0 | Z66: Lognormal | AA66: =0.9*K66 -> 649.089 | AB66: =1.3*K66 -> 937.573 | AC66: Lognormal | AD66: 0.1 | AE66: 1 | AF66: 0 | AG66: Truncated Normal
A67: 214.9 | B67: =IF(ISNUMBER(A67), IF(AND(A67=INT(A67), MOD(A67, 10) = 0), 0, IF(AND(A67=INT(A67), LEN(A67)=2), 1, IF(AND(A67=INT(A67), LEN(A67)=3), 2, LEN(A67) - FIND(".", A67) + 2) ) ), "") -> 3 | C67: Encompassing Buildings | D67: =REPT(" ", B67*2) & C67 -> Encompassing Buildings
A68: 214.91 | B68: =IF(ISNUMBER(A68), IF(AND(A68=INT(A68), MOD(A68, 10) = 0), 0, IF(AND(A68=INT(A68), LEN(A68)=2), 1, IF(AND(A68=INT(A68), LEN(A68)=3), 2, LEN(A68) - FIND(".", A68) + 2) ) ), "") -> 4 | C68: Overarching steel building | D68: =REPT(" ", B68*2) & C68 -> Overarching steel building | E68: standard | J68: =0.7*42394117 -> 29675882 | L68: $/m^2 | N68: 2896 | O68: m^2 | Q68: 2025 | R68: Lab and Mat and Equip | T68: MC30 Cost Estimation of Microreactor Facilities Rev 1 Draft Backup Info 8-5-2026.xlsx, less 30% | W68: Onsite Learning | X68: =0.9*$J68 -> 26708294 | Y68: =1.5*J68 -> 44513823 | Z68: Lognormal | AA68: =0.9*K68 -> 0 | AB68: =1.3*K68 -> 0 | AC68: Lognormal | AD68: 0.1 | AE68: 1 | AF68: 0 | AG68: Truncated Normal
A69: 215 | B69: =IF(ISNUMBER(A69), IF(AND(A69=INT(A69), MOD(A69, 10) = 0), 0, IF(AND(A69=INT(A69), LEN(A69)=2), 1, IF(AND(A69=INT(A69), LEN(A69)=3), 2, LEN(A69) - FIND(".", A69) + 2) ) ), "") -> 2 | C69: Supply Chain Buildings | D69: =REPT(" ", B69*2) & C69 -> Supply Chain Buildings
A70: 215.1 | B70: =IF(ISNUMBER(A70), IF(AND(A70=INT(A70), MOD(A70, 10) = 0), 0, IF(AND(A70=INT(A70), LEN(A70)=2), 1, IF(AND(A70=INT(A70), LEN(A70)=3), 2, LEN(A70) - FIND(".", A70) + 2) ) ), "") -> 3 | C70: Storage Building | D70: =REPT(" ", B70*2) & C70 -> Storage Building
A71: 215.11 | B71: =IF(ISNUMBER(A71), IF(AND(A71=INT(A71), MOD(A71, 10) = 0), 0, IF(AND(A71=INT(A71), LEN(A71)=2), 1, IF(AND(A71=INT(A71), LEN(A71)=3), 2, LEN(A71) - FIND(".", A71) + 2) ) ), "") -> 4 | C71: Storage Building Slab Roof | D71: =REPT(" ", B71*2) & C71 -> Storage Building Slab Roof | E71: standard | K71: =1200 -> 1200 | L71: $/m^3 | M71: Storage Building Slab Roof Volume | O71: m^3 | Q71: 2024 | R71: Lab and Mat and Equip | S71: RSMeans software: a tool that primarily provides costs for non-nuclear work | T71: GORDIAN. (2024). "RSMeans data. & Delene, J. G. and I. Hudson, C. R. (1993). Cost estimate guidelines for advanced nuclear power technologies. United States, Oak Ridge National Lab. (ORNL), Oak Ridge, TN (United States): Medium: ED; Size: 159 p. | U71: https://www.rsmeans.com/ & https://www.osti.gov/biblio/10176857 | W71: Onsite Learning | X71: =0.9*$J71 -> 0 | Y71: =1.5*J71 -> 0 | Z71: Lognormal | AA71: =0.9*K71 -> 1080 | AB71: =1.3*K71 -> 1560 | AC71: Lognormal | AD71: 0.1 | AE71: 1 | AF71: 0 | AG71: Truncated Normal
A72: 215.12 | B72: =IF(ISNUMBER(A72), IF(AND(A72=INT(A72), MOD(A72, 10) = 0), 0, IF(AND(A72=INT(A72), LEN(A72)=2), 1, IF(AND(A72=INT(A72), LEN(A72)=3), 2, LEN(A72) - FIND(".", A72) + 2) ) ), "") -> 4 | C72: Storage Building Basement | D72: =REPT(" ", B72*2) & C72 -> Storage Building Basement | E72: standard | K72: =943.9 -> 943.9 | L72: $/m^3 | M72: Storage Building Basement Volume | O72: m^3 | Q72: 2024 | R72: Lab and Mat and Equip | W72: Onsite Learning | X72: =0.9*$J72 -> 0 | Y72: =1.5*J72 -> 0 | Z72: Lognormal | AA72: =0.9*K72 -> 849.51 | AB72: =1.3*K72 -> 1227.07 | AC72: Lognormal | AD72: 0.1 | AE72: 1 | AF72: 0 | AG72: Truncated Normal
A73: 215.13 | B73: =IF(ISNUMBER(A73), IF(AND(A73=INT(A73), MOD(A73, 10) = 0), 0, IF(AND(A73=INT(A73), LEN(A73)=2), 1, IF(AND(A73=INT(A73), LEN(A73)=3), 2, LEN(A73) - FIND(".", A73) + 2) ) ), "") -> 4 | C73: Storage Building Walls | D73: =REPT(" ", B73*2) & C73 -> Storage Building Walls | E73: standard | K73: =721.21 -> 721.21 | L73: $/m^3 | M73: Storage Building Exterior Walls Volume | O73: m^3 | Q73: 2024 | R73: Lab and Mat and Equip | W73: Onsite Learning | X73: =0.9*$J73 -> 0 | Y73: =1.5*J73 -> 0 | Z73: Lognormal | AA73: =0.9*K73 -> 649.089 | AB73: =1.3*K73 -> 937.573 | AC73: Lognormal | AD73: 0.1 | AE73: 1 | AF73: 0 | AG73: Truncated Normal
A74: 215.4 | B74: =IF(ISNUMBER(A74), IF(AND(A74=INT(A74), MOD(A74, 10) = 0), 0, IF(AND(A74=INT(A74), LEN(A74)=2), 1, IF(AND(A74=INT(A74), LEN(A74)=3), 2, LEN(A74) - FIND(".", A74) + 2) ) ), "") -> 3 | C74: Radwaste Building | D74: =REPT(" ", B74*2) & C74 -> Radwaste Building
A75: 215.41 | B75: =IF(ISNUMBER(A75), IF(AND(A75=INT(A75), MOD(A75, 10) = 0), 0, IF(AND(A75=INT(A75), LEN(A75)=2), 1, IF(AND(A75=INT(A75), LEN(A75)=3), 2, LEN(A75) - FIND(".", A75) + 2) ) ), "") -> 4 | C75: Radwaste Building Slab Roof | D75: =REPT(" ", B75*2) & C75 -> Radwaste Building Slab Roof | E75: standard | K75: =1200 *1.53 -> 1836 | L75: $/m^3 | M75: Radwaste Building Slab Roof Volume | O75: m^3 | Q75: 2024 | R75: Lab and Mat and Equip | S75: RSMeans software: a tool that primarily provides costs for non-nuclear work Nuclear Multiplier have been applied to adjust the costs for nuclear-site-related work | T75: GORDIAN. (2024). "RSMeans data. & Delene, J. G. and I. Hudson, C. R. (1993). Cost estimate guidelines for advanced nuclear power technologies. United States, Oak Ridge National Lab. (ORNL), Oak Ridge, TN (United States): Medium: ED; Size: 159 p. | U75: https://www.rsmeans.com/ & https://www.osti.gov/biblio/10176857 | W75: Onsite Learning | X75: =0.9*$J75 -> 0 | Y75: =1.5*J75 -> 0 | Z75: Lognormal | AA75: =0.9*K75 -> 1652.4 | AB75: =1.3*K75 -> 2386.8 | AC75: Lognormal | AD75: 0.1 | AE75: 1 | AF75: 0 | AG75: Truncated Normal
A76: 215.42 | B76: =IF(ISNUMBER(A76), IF(AND(A76=INT(A76), MOD(A76, 10) = 0), 0, IF(AND(A76=INT(A76), LEN(A76)=2), 1, IF(AND(A76=INT(A76), LEN(A76)=3), 2, LEN(A76) - FIND(".", A76) + 2) ) ), "") -> 4 | C76: Radwaste Building Basement | D76: =REPT(" ", B76*2) & C76 -> Radwaste Building Basement | E76: standard | K76: =943.9*1.53 -> 1444.167 | L76: $/m^3 | M76: Radwaste Building Basement Volume | O76: m^3 | Q76: 2024 | R76: Lab and Mat and Equip | W76: Onsite Learning | X76: =0.9*$J76 -> 0 | Y76: =1.5*J76 -> 0 | Z76: Lognormal | AA76: =0.9*K76 -> 1299.7503 | AB76: =1.3*K76 -> 1877.4171 | AC76: Lognormal | AD76: 0.1 | AE76: 1 | AF76: 0 | AG76: Truncated Normal
A77: 215.43 | B77: =IF(ISNUMBER(A77), IF(AND(A77=INT(A77), MOD(A77, 10) = 0), 0, IF(AND(A77=INT(A77), LEN(A77)=2), 1, IF(AND(A77=INT(A77), LEN(A77)=3), 2, LEN(A77) - FIND(".", A77) + 2) ) ), "") -> 4 | C77: Radwaste Building Walls | D77: =REPT(" ", B77*2) & C77 -> Radwaste Building Walls | E77: standard | K77: =721.21*1.53 -> 1103.4513 | L77: $/m^3 | M77: Radwaste Building Exterior Walls Volume | O77: m^3 | Q77: 2024 | R77: Lab and Mat and Equip | W77: Onsite Learning | X77: =0.9*$J77 -> 0 | Y77: =1.5*J77 -> 0 | Z77: Lognormal | AA77: =0.9*K77 -> 993.10617 | AB77: =1.3*K77 -> 1434.4867 | AC77: Lognormal | AD77: 0.1 | AE77: 1 | AF77: 0 | AG77: Truncated Normal
A78: 215.5 | B78: =IF(ISNUMBER(A78), IF(AND(A78=INT(A78), MOD(A78, 10) = 0), 0, IF(AND(A78=INT(A78), LEN(A78)=2), 1, IF(AND(A78=INT(A78), LEN(A78)=3), 2, LEN(A78) - FIND(".", A78) + 2) ) ), "") -> 3 | C78: O&M support buildings | D78: =REPT(" ", B78*2) & C78 -> O&M support buildings
A79: 215.51 | B79: =IF(ISNUMBER(A79), IF(AND(A79=INT(A79), MOD(A79, 10) = 0), 0, IF(AND(A79=INT(A79), LEN(A79)=2), 1, IF(AND(A79=INT(A79), LEN(A79)=3), 2, LEN(A79) - FIND(".", A79) + 2) ) ), "") -> 4 | C79: O&M support building structure | D79: =REPT(" ", B79*2) & C79 -> O&M support building structure | J79: =0.7*2152027 -> 1506418.9 | Q79: 2025 | R79: Lab and Mat and Equip | S79: fixed cost for now - could work on scaling | T79: MC30 Cost Estimation of Microreactor Facilities Inital Draft 5-6-2026.pdf, average of O&M Support Building and O&M Warehouse, less 30% | W79: Onsite Learning | X79: =0.9*$J79 -> 1355777 | Y79: =1.5*J79 -> 2259628.3 | Z79: Lognormal | AA79: =0.9*K79 -> 0 | AB79: =1.3*K79 -> 0 | AC79: Lognormal | AD79: 0.0 | AE79: 1 | AF79: 0 | AG79: Truncated Normal
A80: 215.52 | B80: =IF(ISNUMBER(A80), IF(AND(A80=INT(A80), MOD(A80, 10) = 0), 0, IF(AND(A80=INT(A80), LEN(A80)=2), 1, IF(AND(A80=INT(A80), LEN(A80)=3), 2, LEN(A80) - FIND(".", A80) + 2) ) ), "") -> 4 | C80: O&M warehouse structure | D80: =REPT(" ", B80*2) & C80 -> O&M warehouse structure | E80: standard | J80: =0.7*3031087 -> 2121760.9 | Q80: 2025 | R80: Lab and Mat and Equip | S80: fixed cost for now - could work on scaling | T80: MC30 Cost Estimation of Microreactor Facilities Inital Draft 5-6-2026.pdf, average of O&M Support Building and O&M Warehouse, less 30% | W80: Onsite Learning | X80: =0.9*$J80 -> 1909584.8 | Y80: =1.5*J80 -> 3182641.3 | Z80: Lognormal | AA80: =0.9*K80 -> 0 | AB80: =1.3*K80 -> 0 | AC80: Lognormal | AD80: 0.1 | AE80: 1 | AF80: 0 | AG80: Truncated Normal
A81: 22 | B81: =IF(ISNUMBER(A81), IF(AND(A81=INT(A81), MOD(A81, 10) = 0), 0, IF(AND(A81=INT(A81), LEN(A81)=2), 1, IF(AND(A81=INT(A81), LEN(A81)=3), 2, LEN(A81) - FIND(".", A81) + 2) ) ), "") -> 1 | C81: Reactor System | D81: =REPT(" ", B81*2) & C81 -> Reactor System
A82: 221 | B82: =IF(ISNUMBER(A82), IF(AND(A82=INT(A82), MOD(A82, 10) = 0), 0, IF(AND(A82=INT(A82), LEN(A82)=2), 1, IF(AND(A82=INT(A82), LEN(A82)=3), 2, LEN(A82) - FIND(".", A82) + 2) ) ), "") -> 2 | C82: Reactor Components | D82: =REPT(" ", B82*2) & C82 -> Reactor Components
A83: 221.1 | B83: =IF(ISNUMBER(A83), IF(AND(A83=INT(A83), MOD(A83, 10) = 0), 0, IF(AND(A83=INT(A83), LEN(A83)=2), 1, IF(AND(A83=INT(A83), LEN(A83)=3), 2, LEN(A83) - FIND(".", A83) + 2) ) ), "") -> 3 | C83: Reactor Vessel and Accessories | D83: =REPT(" ", B83*2) & C83 -> Reactor Vessel and Accessories
A84: 221.11 | B84: =IF(ISNUMBER(A84), IF(AND(A84=INT(A84), MOD(A84, 10) = 0), 0, IF(AND(A84=INT(A84), LEN(A84)=2), 1, IF(AND(A84=INT(A84), LEN(A84)=3), 2, LEN(A84) - FIND(".", A84) + 2) ) ), "") -> 4 | C84: Reactor Support | D84: =REPT(" ", B84*2) & C84 -> Reactor Support | E84: standard | K84: =MARVEL_Cost!C16/N84 -> 311.55799 | L84: $/Kg | M84: Total Vessels Mass | N84: =1000*('Design Variables'!B52+'Design Variables'!B49) -> 2447 | O84: Kg | P84: 0.85 | Q84: 2018 | R84: Lab and Mat and Equip | S84: PWR12-ME | V84: Unit cost is the cost of support structure divided by the cost of guard vessel plus PCS | W84: Factory Primary Structure | X84: =0.9*$J84 -> 0 | Y84: =1.5*J84 -> 0 | Z84: Lognormal | AA84: =0.9*K84 -> 280.40219 | AB84: =1.3*K84 -> 405.02539 | AC84: Lognormal | AD84: 0.1 | AE84: 1 | AF84: 0 | AG84: Truncated Normal
A85: 221.12 | B85: =IF(ISNUMBER(A85), IF(AND(A85=INT(A85), MOD(A85, 10) = 0), 0, IF(AND(A85=INT(A85), LEN(A85)=2), 1, IF(AND(A85=INT(A85), LEN(A85)=3), 2, LEN(A85) - FIND(".", A85) + 2) ) ), "") -> 4 | C85: Outer Vessel Structure | D85: =REPT(" ", B85*2) & C85 -> Outer Vessel Structure | E85: standard | F85: Guard Vessel Material | G85: stainless_steel | K85: =MARVEL_Cost!C17/N85 -> 757.20769 | L85: $/Kg | M85: Guard Vessel Mass | N85: ='Design Variables'!B52*1000 -> 1587 | O85: Kg | Q85: 2017 | R85: Lab and Mat and Equip | S85: Ganda et al., 2018 | T85: Ganda, F., Hoffman, E., Taiwo, T. A., Kim, T. K., & Hansen, J. (2019). Report on the ACCERT cost algorithms tool (No. ANL/NSE-19/10). Argonne National Lab.(ANL), Argonne, IL (United States). | W85: Factory Primary Structure | X85: =0.9*$J85 -> 0 | Y85: =1.5*J85 -> 0 | Z85: Lognormal | AA85: =0.9*K85 -> 681.48692 | AB85: =1.3*K85 -> 984.36999 | AC85: Lognormal | AD85: 0.1 | AE85: 1 | AF85: 0 | AG85: Truncated Normal
A86: 221.12 | B86: =IF(ISNUMBER(A86), IF(AND(A86=INT(A86), MOD(A86, 10) = 0), 0, IF(AND(A86=INT(A86), LEN(A86)=2), 1, IF(AND(A86=INT(A86), LEN(A86)=3), 2, LEN(A86) - FIND(".", A86) + 2) ) ), "") -> 4 | C86: Outer Vessel Structure | D86: =REPT(" ", B86*2) & C86 -> Outer Vessel Structure | E86: standard | F86: Guard Vessel Material | G86: low_alloy_steel | K86: 154.08 | L86: $/Kg | M86: Guard Vessel Mass | Q86: 2017 | R86: Lab and Mat and Equip | S86: Ganda et al., 2018 | W86: Factory Primary Structure | X86: =0.9*$J86 -> 0 | Y86: =1.5*J86 -> 0 | Z86: Lognormal | AA86: =0.9*K86 -> 138.672 | AB86: =1.3*K86 -> 200.304 | AC86: Lognormal | AD86: 0.1 | AE86: 1 | AF86: 0 | AG86: Truncated Normal
A87: 221.12 | B87: =IF(ISNUMBER(A87), IF(AND(A87=INT(A87), MOD(A87, 10) = 0), 0, IF(AND(A87=INT(A87), LEN(A87)=2), 1, IF(AND(A87=INT(A87), LEN(A87)=3), 2, LEN(A87) - FIND(".", A87) + 2) ) ), "") -> 4 | C87: Outer Vessel Structure | D87: =REPT(" ", B87*2) & C87 -> Outer Vessel Structure | E87: standard | F87: Guard Vessel Material | G87: incoloy | K87: 444.08 | L87: $/Kg | M87: Guard Vessel Mass | Q87: 2017 | R87: Lab and Mat and Equip | S87: Ganda et al., 2018 | W87: Factory Primary Structure | X87: =0.9*$J87 -> 0 | Y87: =1.5*J87 -> 0 | Z87: Lognormal | AA87: =0.9*K87 -> 399.672 | AB87: =1.3*K87 -> 577.304 | AC87: Lognormal | AD87: 0.1 | AE87: 1 | AF87: 0 | AG87: Truncated Normal
A88: 221.13 | B88: =IF(ISNUMBER(A88), IF(AND(A88=INT(A88), MOD(A88, 10) = 0), 0, IF(AND(A88=INT(A88), LEN(A88)=2), 1, IF(AND(A88=INT(A88), LEN(A88)=3), 2, LEN(A88) - FIND(".", A88) + 2) ) ), "") -> 4 | C88: Inner Vessel Structure | D88: =REPT(" ", B88*2) & C88 -> Inner Vessel Structure | E88: standard | F88: Vessel Material | G88: stainless_steel | J88: =MARVEL_Cost!C37+MARVEL_Cost!C36 -> 3369444.6 | K88: =(MARVEL_Cost!C35)/N88 -> 1768.3558 | L88: $/Kg | M88: Vessel Mass | N88: =1000*'Design Variables'!B49 -> 860 | Q88: 2017 | R88: Lab and Mat and Equip | S88: Ganda et al., 2018 | V88: Unit cost if the PCS cost (in MARVEL) divided by the PCS mass in MARVEL | W88: Factory Primary Structure | X88: =0.9*$J88 -> 3032500.1 | Y88: =1.5*J88 -> 5054166.9 | Z88: Lognormal | AA88: =0.9*K88 -> 1591.5202 | AB88: =1.3*K88 -> 2298.8626 | AC88: Lognormal | AD88: 0.1 | AE88: 1 | AF88: 0 | AG88: Truncated Normal
A89: 221.13 | B89: =IF(ISNUMBER(A89), IF(AND(A89=INT(A89), MOD(A89, 10) = 0), 0, IF(AND(A89=INT(A89), LEN(A89)=2), 1, IF(AND(A89=INT(A89), LEN(A89)=3), 2, LEN(A89) - FIND(".", A89) + 2) ) ), "") -> 4 | C89: Inner Vessel Structure | D89: =REPT(" ", B89*2) & C89 -> Inner Vessel Structure | E89: standard | F89: Vessel Material | G89: low_alloy_steel | K89: 154.08 | L89: $/Kg | M89: Vessel Mass | Q89: 2017 | R89: Lab and Mat and Equip | S89: Ganda et al., 2018 | W89: Factory Primary Structure | X89: =0.9*$J89 -> 0 | Y89: =1.5*J89 -> 0 | Z89: Lognormal | AA89: =0.9*K89 -> 138.672 | AB89: =1.3*K89 -> 200.304 | AC89: Lognormal | AD89: 0.1 | AE89: 1 | AF89: 0 | AG89: Truncated Normal
A90: 221.13 | B90: =IF(ISNUMBER(A90), IF(AND(A90=INT(A90), MOD(A90, 10) = 0), 0, IF(AND(A90=INT(A90), LEN(A90)=2), 1, IF(AND(A90=INT(A90), LEN(A90)=3), 2, LEN(A90) - FIND(".", A90) + 2) ) ), "") -> 4 | C90: Inner Vessel Structure | D90: =REPT(" ", B90*2) & C90 -> Inner Vessel Structure | E90: standard | F90: Vessel Material | G90: incoloy | K90: 444.08 | L90: $/Kg | M90: Vessel Mass | Q90: 2017 | R90: Lab and Mat and Equip | S90: Ganda et al., 2018 | W90: Factory Primary Structure | X90: =0.9*$J90 -> 0 | Y90: =1.5*J90 -> 0 | Z90: Lognormal | AA90: =0.9*K90 -> 399.672 | AB90: =1.3*K90 -> 577.304 | AC90: Lognormal | AD90: 0.1 | AE90: 1 | AF90: 0 | AG90: Truncated Normal
A91: 221.2 | B91: =IF(ISNUMBER(A91), IF(AND(A91=INT(A91), MOD(A91, 10) = 0), 0, IF(AND(A91=INT(A91), LEN(A91)=2), 1, IF(AND(A91=INT(A91), LEN(A91)=3), 2, LEN(A91) - FIND(".", A91) + 2) ) ), "") -> 3 | C91: Reactor Control Devices | D91: =REPT(" ", B91*2) & C91 -> Reactor Control Devices
A92: 221.21 | B92: =IF(ISNUMBER(A92), IF(AND(A92=INT(A92), MOD(A92, 10) = 0), 0, IF(AND(A92=INT(A92), LEN(A92)=2), 1, IF(AND(A92=INT(A92), LEN(A92)=3), 2, LEN(A92) - FIND(".", A92) + 2) ) ), "") -> 4 | C92: Reactivity Control System | D92: =REPT(" ", B92*2) & C92 -> Reactivity Control System
A93: 221.211 | B93: =IF(ISNUMBER(A93), IF(AND(A93=INT(A93), MOD(A93, 10) = 0), 0, IF(AND(A93=INT(A93), LEN(A93)=2), 1, IF(AND(A93=INT(A93), LEN(A93)=3), 2, LEN(A93) - FIND(".", A93) + 2) ) ), "") -> 5 | C93: Reactivity Control System Fabrication | D93: =REPT(" ", B93*2) & C93 -> Reactivity Control System Fabrication | E93: standard | K93: =MARVEL_Cost!C21/'Design Variables'!B21 -> 347890 | L93: $/Drum | M93: Drum Count | Q93: 2024 | R93: Lab and Mat and Equip | S93: MARVEL Project | T93: Updated MARVEL Cost Estimate + Communication with MARVEL Team | U93: Gerstner, D., & Arafat, Y. (2023). MARVEL 90% Final Design Report (No. INL/RPT-23-74280-Rev000). Idaho National Laboratory (INL), Idaho Falls, ID (United States). Hanna, B. N., Gonzaga de Oliveira, R. G., Mohammad Al Dawood, K. A., Patterson, M. D., Abou Jaoude, A., & Garcia, S. (2024). Technoeconomic Evaluation of Microreactor Using Detailed Bottom-up Estimate (No. INL/RPT-24-80433-Rev000). Idaho National Laboratory (INL), Idaho Falls, ID (United States). | V93: The scaling variable here is the total mass of all the control drums | W93: Factory Drums | X93: =0.9*$J93 -> 0 | Y93: =1.5*J93 -> 0 | Z93: Lognormal | AA93: =0.9*K93 -> 313101 | AB93: =1.3*K93 -> 452257 | AC93: Lognormal | AD93: 0.1 | AE93: 1 | AF93: 0 | AG93: Truncated Normal
A94: 221.212 | B94: =IF(ISNUMBER(A94), IF(AND(A94=INT(A94), MOD(A94, 10) = 0), 0, IF(AND(A94=INT(A94), LEN(A94)=2), 1, IF(AND(A94=INT(A94), LEN(A94)=3), 2, LEN(A94) - FIND(".", A94) + 2) ) ), "") -> 5 | C94: Installation | D94: =REPT(" ", B94*2) & C94 -> Installation | E94: standard | K94: =MARVEL_Cost!C22/'Design Variables'!B21 -> 80665.75 | L94: $/Drum | M94: Drum Count | Q94: 2024 | R94: Lab and Equip | S94: MARVEL Project | W94: Factory Drums | X94: =0.9*$J94 -> 0 | Y94: =1.5*J94 -> 0 | Z94: Lognormal | AA94: =0.9*K94 -> 72599.175 | AB94: =1.3*K94 -> 104865.48 | AC94: Lognormal | AD94: 0.1 | AE94: 1 | AF94: 0 | AG94: Truncated Normal
A95: 221.213 | B95: =IF(ISNUMBER(A95), IF(AND(A95=INT(A95), MOD(A95, 10) = 0), 0, IF(AND(A95=INT(A95), LEN(A95)=2), 1, IF(AND(A95=INT(A95), LEN(A95)=3), 2, LEN(A95) - FIND(".", A95) + 2) ) ), "") -> 5 | C95: Control Drums Materials (Absorber) | D95: =REPT(" ", B95*2) & C95 -> Control Drums Materials (Absorber) | E95: standard | F95: Control Drum Absorber | G95: B4C_natural | K95: =400000/N95 -> 14285.714 | L95: $/Kg | M95: Control Drum Absorber Mass | N95: ='Design Variables'!B28+'Design Variables'!B29 -> 28 | O95: Kg | P95: 1 | Q95: 2024 | R95: Material | S95: MARVEL Project | W95: Factory Other | X95: =0.9*$J95 -> 0 | Y95: =1.5*J95 -> 0 | Z95: Lognormal | AA95: =0.9*K95 -> 12857.143 | AB95: =1.3*K95 -> 18571.429 | AC95: Lognormal | AD95: 0.1 | AE95: 1 | AF95: 0 | AG95: Truncated Normal
A96: 221.213 | B96: =IF(ISNUMBER(A96), IF(AND(A96=INT(A96), MOD(A96, 10) = 0), 0, IF(AND(A96=INT(A96), LEN(A96)=2), 1, IF(AND(A96=INT(A96), LEN(A96)=3), 2, LEN(A96) - FIND(".", A96) + 2) ) ), "") -> 5 | C96: Control Drums Materials (Absorber) | D96: =REPT(" ", B96*2) & C96 -> Control Drums Materials (Absorber) | E96: standard | F96: Control Drum Absorber | G96: B4C_enriched | K96: 10064 | L96: $/Kg | M96: Control Drum Absorber Mass | Q96: 2023 | R96: Material | S96: Prosser et al., 2023 | W96: Factory Other | X96: =0.9*$J96 -> 0 | Y96: =1.5*J96 -> 0 | Z96: Lognormal | AA96: =0.9*K96 -> 9057.6 | AB96: =1.3*K96 -> 13083.2 | AC96: Lognormal | AD96: 0.1 | AE96: 1 | AF96: 0 | AG96: Truncated Normal
A97: 221.214 | B97: =IF(ISNUMBER(A97), IF(AND(A97=INT(A97), MOD(A97, 10) = 0), 0, IF(AND(A97=INT(A97), LEN(A97)=2), 1, IF(AND(A97=INT(A97), LEN(A97)=3), 2, LEN(A97) - FIND(".", A97) + 2) ) ), "") -> 5 | C97: Control Drums Materials (Reflector) | D97: =REPT(" ", B97*2) & C97 -> Control Drums Materials (Reflector) | E97: standard | F97: Control Drum Reflector | G97: BeO | K97: =MARVEL_Cost!C27/N97 -> 10062.893 | L97: $/Kg | M97: Control Drum Reflector Mass | N97: ='Design Variables'!B17 -> 318 | O97: Kg | P97: 1 | Q97: 2024 | R97: Material | S97: MARVEL Project | W97: Factory BeO | X97: =0.9*$J97 -> 0 | Y97: =1.5*J97 -> 0 | Z97: Lognormal | AA97: =0.9*K97 -> 9056.6038 | AB97: =1.3*K97 -> 13081.761 | AC97: Lognormal | AD97: 0.1 | AE97: 1 | AF97: 0 | AG97: Truncated Normal
A98: 221.214 | B98: =IF(ISNUMBER(A98), IF(AND(A98=INT(A98), MOD(A98, 10) = 0), 0, IF(AND(A98=INT(A98), LEN(A98)=2), 1, IF(AND(A98=INT(A98), LEN(A98)=3), 2, LEN(A98) - FIND(".", A98) + 2) ) ), "") -> 5 | C98: Control Drums Materials (Reflector) | D98: =REPT(" ", B98*2) & C98 -> Control Drums Materials (Reflector) | E98: standard | F98: Control Drum Reflector | G98: Be | K98: =MARVEL_Cost!C28/N98 -> 44736.842 | L98: $/Kg | M98: Control Drum Reflector Mass | N98: =1000*'Design Variables'!B19 -> 19 | O98: Kg | P98: 1 | Q98: 2024 | R98: Material | S98: MARVEL Project | W98: Factory Be | X98: =0.9*$J98 -> 0 | Y98: =1.5*J98 -> 0 | Z98: Lognormal | AA98: =0.9*K98 -> 40263.158 | AB98: =1.3*K98 -> 58157.895 | AC98: Lognormal | AD98: 0.1 | AE98: 1 | AF98: 0 | AG98: Truncated Normal
A99: 221.214 | B99: =IF(ISNUMBER(A99), IF(AND(A99=INT(A99), MOD(A99, 10) = 0), 0, IF(AND(A99=INT(A99), LEN(A99)=2), 1, IF(AND(A99=INT(A99), LEN(A99)=3), 2, LEN(A99) - FIND(".", A99) + 2) ) ), "") -> 5 | C99: Control Drums Materials (Reflector) | D99: =REPT(" ", B99*2) & C99 -> Control Drums Materials (Reflector) | E99: standard | F99: Control Drum Reflector | G99: Graphite | K99: 80 | L99: $/Kg | M99: Control Drum Reflector Mass | Q99: 2022 | R99: Material | S99: Naranjo de Candido and Shirvan, 2022 | T99: Naranjo De Candido and Shirvan. (2022). Graphite Life-Cycle Cost Model for HTGRs, International High-Level Radioactive Waste Management Conference | W99: Factory Other | X99: =0.9*$J99 -> 0 | Y99: =1.5*J99 -> 0 | Z99: Lognormal | AA99: =0.9*K99 -> 72 | AB99: =1.3*K99 -> 104 | AC99: Lognormal | AD99: 0.1 | AE99: 1 | AF99: 0 | AG99: Truncated Normal
A100: 221.215 | B100: =IF(ISNUMBER(A100), IF(AND(A100=INT(A100), MOD(A100, 10) = 0), 0, IF(AND(A100=INT(A100), LEN(A100)=2), 1, IF(AND(A100=INT(A100), LEN(A100)=3), 2, LEN(A100) - FIND(".", A100) + 2) ) ), "") -> 5 | C100: Control System Drive Mechanism | D100: =REPT(" ", B100*2) & C100 -> Control System Drive Mechanism | E100: standard | K100: 74759 | L100: $/Drum | M100: Drum Count | Q100: 2023 | R100: Lab and Mat and Equip | S100: Prosser et al., 2023 | T100: First-Principles Cost Estimation of a Sodium Fast Reactor Nuclear Plant. INL/RPT-23-74316 Table 38, 39 | V100: Bottom-up Estimation of components with nuclear escalation + contingency | W100: Factory Drums | X100: =0.9*$J100 -> 0 | Y100: =1.5*J100 -> 0 | Z100: Lognormal | AA100: =0.9*K100 -> 67283.1 | AB100: =1.3*K100 -> 97186.7 | AC100: Lognormal | AD100: 0.1 | AE100: 1 | AF100: 0 | AG100: Truncated Normal
...

Sheet MARVEL_Cost
A1: Account ID | B1: Account Title | C1: TOTAL COST (2024 USD)
A3: 10 | B3: Capitalized Pre-Construction Costs | C3: =C4 -> 5210451
A4: 15 | B4: Plant Studies | C4: 5210451
A5: 20 | B5: Capitalized Direct Costs | C5: =C6+C13+C45+C48+C52+C54 -> 30295715
A6: 21 | B6: Structures and Improvements | C6: =C7+C8+C9+C10 -> 2799006.7
A7: 211 | B7: Site Preparation/Yard Work
A8: 212 | B8: Reactor Island Civil Structures | C8: 2573469.9
A9: 213 | B9: Main Function Buildings
A10: 214 | B10: Buildings to Support Main Function | C10: =SUM(C11) -> 225536.86
A11: 214.7 | B11: Emergency and Start-up Power Systems | C11: 225536.86
A12: 217 | B12: Miscellaneous Other Structures
A13: 22 | B13: Reactor System | C13: =C14+C32+C41+C42+C43+C44 -> 17586713
A14: 221 | B14: Reactor Components | C14: =C15+C19+C25 -> 8937296.6
A15: 221.1 | B15: Reactor vessel and accessories | C15: =C16+C17+C18 -> 2004852
A16: 221.11 | B16: Reactor support | C16: 762382.4
A17: 221.12 | B17: Outer vessel structure | C17: 1201688.6
A18: 221.13 | B18: Inner vessel structure | C18: 40781
A19: 221.2 | B19: Reactor control devices | C19: =C20 -> 2114223
A20: 221.21 | B20: Reactivity control system | C20: =SUM(C21:C23) -> 2114223
A21: 221.211 | B21: Reactivity Control System Fabrication | C21: 1391560
A22: 221.212 | B22: Installation | C22: 322663
A23: 221.213 | B23: Control Drums Materials (Absorber) | C23: 400000
A24: 221.214 | B24: Control Drums Materials (Reflector)
A25: 221.3 | B25: Non-fuel core internals | C25: =C26+C30+C31 -> 4818221.6
A26: 221.31 | B26: Reflector | C26: 4170231
A27: 221.311 | B27: Reflector (Materials: BeO) | C27: 3200000
A28: 221.312 | B28: Reflector (Materials: Be Metal) | C28: 850000
A29: 221.313 | B29: Reflector (installation | C29: 120231
A30: 221.32 | B30: Shield | C30: 647990.6
A31: 221.33 | B31: Moderator | C31: 0
A32: 222 | B32: Main Heat Transport System | C32: =C33+C34+C38+C39+C40 -> 5908950.6
A33: 222.1 | B33: Fluid circulation drive system | C33: 0
A34: 222.2 | B34: Reactor Heat Hransfer Piping System | C34: 4890230.6
A35: 222.21 | B35: Reactor Heat Hransfer Piping System (Mat) | C35: 1520786
A36: 222.22 | B36: Reactor Heat Hransfer Piping System (Fabrication) | C36: 3341486
A37: 222.23 | B37: Reactor Heat Hransfer Piping System (Installation) | C37: 27958.6
A38: 222.3 | B38: Heat Exchangers | C38: 0
A39: 222.4 | B39: Pressurizer System | C39: 0
A40: 222.5 | B40: Initial Heat Transfer Fluid Inventory | C40: 1018720
A41: 224 | B41: Radioactive Byproduct Processing Systems
A42: 226 | B42: Other Reactor Plant Equipment | C42: 456297
A43: 227 | B43: Reactor Instrumentation and Control (I&C) | C43: 2253208.4
A44: 228 | B44: Reactor Plant Miscellaneous Items | C44: 30960
A45: 23 | B45: Energy Conversion System | C45: =C46 -> 0
A46: 232 | B46: Energy Applications | C46: =C47 -> 0
A47: 232.1 | B47: Electricity Generation Systems | C47: 0
A48: 24 | B48: Electrical Equipment | C48: =C49+C50+C51 -> 73415.62
A49: 244 | B49: Protective Systems Equipment | C49: 1627.02
A50: 245 | B50: Electrical Raceway Systems | C50: 0
A51: 246 | B51: Power and Control Cables and Wiring | C51: 71788.6
A52: 25 | B52: Initial Fuel Inventory | C52: =C53 -> 9836580.5
A53: 254 | B53: First Core Fuel Assembly Fabrication | C53: 9836580.5
A54: 26 | B54: Miscellaneous Equipment
A55: 30 | B55: Capitalized Indirect Services Cost | C55: =C56+C58+C62+C65+C68 -> 6442742.5
A56: 31 | B56: Factory & Field Indirect Costs | C56: =C57 -> 1333020.8
A57: 317 | B57: Field Shops | C57: 1333020.8
A58: 33 | B58: Startup Costs | C58: =C59 -> 2407166.4
A59: 331 | B59: Commissioning and Trial Test Runs | C59: =C60+C61 -> 2407166.4
A60: 331.3 | B60: Initial Fuel Loading Operations | C60: 215000
A61: 331.5 | B61: Test Runs | C61: 2192166.4
A62: 34 | B62: Shipping and Transportation Costs | C62: =C63+C64 -> 1665282.8
A63: 341 | B63: Fuel Shipping and Transportation | C63: 1635355.8
A64: 345 | B64: Other Shipping and Transportation Costs | C64: 29927
A65: 35 | B65: Engineering Services | C65: =C66+C67 -> 620313.59
A66: 351 | B66: Off-Site | C66: 257261.4
A67: 352 | B67: On-Site | C67: 363052.19
A68: 36 | B68: PM/CM Services | C68: =C69+C70 -> 416958.94
A69: 361 | B69: Off-Site
A70: 362 | B70: On-Site | C70: 416958.94
A71: 40 | B71: Capitalized Training Costs | C71: =C72 -> 4169765
A72: 41 | B72: Staff Recruitment and Training | C72: 4169765
A73: 50 | B73: Capitalized Supplementary Costs | C73: =C74 -> 16408782
A74: 54 | B74: Decommissioning | C74: 16408782
A75: 60 | B75: Capitalized Financial Costs | C75: =C76 -> 6160606
A76: 61 | B76: Escalation | C76: 6160606
A77: 70 | B77: Annualized O&M Cost | C77: =C78 -> 2456659.2
A78: 71 | B78: O&M Staff | C78: 2456659.2
A79: Non-Recurrung Costs | B79: Non-Recurrung Costs | C79: 33779050

Sheet Design Variables
A1: Variable | B1: Value | C1: Units | D1: Description
A2: Overall System
A3: Thermal power | B3: 83 | C3: kWth | D3: —
A4: Electric Power | B4: 20 | C4: kWe
A5: Core outer radius | B5: 5.5 | C5: inches | D5: —
A6: Reflector outer radius | B6: 16.5 | C6: inches | D6: —
A7: Fuel
A8: Fuel mass | B8: 145.3 | C8: kg | D8: UZrH
A9: U Weight fraction | B9: 30 | C9: wt% | D9: U/UZrH
A10: U enrichment | B10: 19.75 | C10: wt% | D10: High-assay low-enriched uranium (HALEU)
A11: Pins | B11: 36 | C11: # | D11: —
A12: Reflector
A13: Outer reflector material | B13: BeO | C13: — | D13: 99% theoretical density
A14: Elements | B14: 124 | C14: # | D14: Quarter plates
A15: Reflector plate thickness | B15: 1 | C15: inches | D15: —
A16: Reflector plate volume | B16: 818.4 | C16: cm3/plate | D16: —
A17: Mass of BeO reflector | B17: 318 | C17: Kg
A18: Insert volume | B18: 570 | C18: cm3/plate | D18: —
A19: Mass of Be-metal reflector | B19: 0.019 | C19: MT | D19: —
A20: Control Elements
A21: Control drums | B21: 4 | C21: # | D21: —
A22: Shutdown rods | B22: 1 | C22: # | D22: —
A23: Control drum elements | B23: 124 | C23: # | D23: Discs
A24: Drum disc thickness | B24: 1 | C24: inches | D24: —
A25: Drum reflector volume | B25: 880.8 | C25: cm3/plate | D25: BeO 99%
A26: Mass of drum reflector | B26: 309 | C26: Kg | D26: —
A27: Drum poison volume | B27: 49.2 | C27: cm3/plate | D27: B4C
A28: Mass of drum poison | B28: 14 | C28: Kg | D28: —
A29: Mass of rod poison | B29: 14 | C29: Kg | D29: B4C
A30: Instruments and Controls
A31: Control cabinet | B31: 5 | D31: —
A32: Instrument cabinet | B32: 2 | D32: —
A33: Nuclear input/output (IO) | B33: 9 | D33: —
A34: Non-nuclear IO | B34: 213 | D34: —
A35: Stirling engine IO | B35: 48 | C35: — | D35: These should be excluded if there no stirling engine?
A36: TOTAL | B36: 277
A37: Shielding in Vessel
A38: Stainless Steel cans | B38: 54.2 | C38: Kg | D38: Stainless Steel cans of the boron carbide shielding material (SS316H)
A39: Gamma shield material | B39: 56.3 | C39: Kg | D39: Gamma shield material inside the guard vessel (of Tungsten)
A40: Neutron shield material in the guard vessel | B40: 39.7 | C40: Kg | D40: made of natural B4C powder and is located above the core (a donut around the core barrel)—
A41: Boron Carbine shielding | B41: 95.3 | C41: Kg | D41: made of natural B4C (called base shield) below the core
A42: Radial (lead) | B42: 2571.9 | C42: Kg | D42: lead
A43: Radial (WEP) | B43: 925.3 | C43: Kg | D43: made of Water Extended Polyster (WEP)
A44: Shielding in Pit
A45: Mass of the pit neutron shielding | B45: 8.3 | C45: MT | D45: Approximated 6-in.-thick covering whole pit and made of Water-extruded poly (WEP)
A46: Heat Transfer
A47: Mass of coolant | B47: 156 | C47: Kg | D47: —
A48: Number of loops | B48: 4 | C48: # | D48: —
A49: Mass of PCSs | B49: 0.86 | C49: MT | D49: SS316H
A50: Subassembly Structure Masses
A51: Reactor support frame | B51: 1.11 | C51: MT | D51: —
A52: Guard vessel | B52: 1.587 | C52: MT | D52: —

Sheet Inflation Adjustment
A1: Year | B1: General | C1: Labor | D1: Material | E1: Equipment | F1: Lab and Mat and Equip | G1: Lab and Equip
A2: 1978 | B2: 3.1209 | C2: 4.2536 | D2: 3.811 | E2: 5.3954 | F2: =(C2+D2+E2)/3 -> 4.4866667 | G2: =AVERAGE(C2,E2) -> 4.8245
A3: 1985 | B3: 2.53801 | C3: 3.3122863 | D3: 3.1461261 | E3: 4.0603969 | F3: =(C3+D3+E3)/3 -> 3.5062697 | G3: =AVERAGE(C3,E3) -> 3.6863416
A4: 1986 | B4: 2.4877976 | C4: 3.2086278 | D4: 3.1524765 | E4: 3.957082 | F4: =(C4+D4+E4)/3 -> 3.4393954 | G4: =AVERAGE(C4,E4) -> 3.5828549
A5: 1987 | B5: 2.4278243 | C5: 3.1112605 | D5: 3.0891631 | E5: 3.9210211 | F5: =(C5+D5+E5)/3 -> 3.3738149 | G5: =AVERAGE(C5,E5) -> 3.5161408
A6: 1988 | B6: 2.3451469 | C6: 2.989825 | D6: 2.9257907 | E6: 3.7360352 | F6: =(C6+D6+E6)/3 -> 3.217217 | G6: =AVERAGE(C6,E6) -> 3.3629301
A7: 1989 | B7: 2.2565183 | C7: 2.8925 | D7: 2.8323254 | E7: 3.5114259 | F7: =(C7+D7+E7)/3 -> 3.0787504 | G7: =AVERAGE(C7,E7) -> 3.2019629
A8: 1990 | B8: 2.1749312 | C8: 2.765278 | D8: 2.828971 | E8: 3.4175276 | F8: =(C8+D8+E8)/3 -> 3.0039255 | G8: =AVERAGE(C8,E8) -> 3.0914028
A9: 1991 | B9: 2.103917 | C9: 2.6561658 | D9: 2.8109546 | E9: 3.3052946 | F9: =(C9+D9+E9)/3 -> 2.9241383 | G9: =AVERAGE(C9,E9) -> 2.9807302
A10: 1992 | B10: 2.0570925 | C10: 2.5740904 | D10: 2.7621964 | E10: 3.1693577 | F10: =(C10+D10+E10)/3 -> 2.8352148 | G10: =AVERAGE(C10,E10) -> 2.871724
A11: 1993 | B11: 2.0094227 | C11: 2.4922663 | D11: 2.6313537 | E11: 2.9935069 | F11: =(C11+D11+E11)/3 -> 2.7057089 | G11: =AVERAGE(C11,E11) -> 2.7428866
A12: 1994 | B12: 1.967432 | C12: 2.4032889 | D12: 2.528144 | E12: 2.9062257 | F12: =(C12+D12+E12)/3 -> 2.6125529 | G12: =AVERAGE(C12,E12) -> 2.6547573
A13: 1995 | B13: 1.9269732 | C13: 2.3615592 | D13: 2.4372516 | E13: 2.8565425 | F13: =(C13+D13+E13)/3 -> 2.5517845 | G13: =AVERAGE(C13,E13) -> 2.6090509
... A43: 2025 | B43: 1 | C43: 1 | D43: 1 | E43: 1 | F43: =(C43+D43+E43)/3 -> 1 | G43: =AVERAGE(C43,E43) -> 1

Sheet Economics Parameters
A1: Parameter | B1: Value | C1: Note | D1: Reference | E1: Notes
A2: indirect to direct field-related cost | B2: 0.065389932
A3: FTEs Per Onsite Operator (24/7) | B3: 5
A4: FTEs Per Offsite Operator (24/7) | B4: 5
A5: FTEs Per Security Staff (24/7) | B5: 5
A6: Hours Per FTE | B6: 1800
A7: Work Hours Per Shift | B7: 10
A8: Maintenance to Direct Cost Ratio | B8: 0.03
A9: Onsite Learning | B9: 0.08 | C9: FOAK to NOAK Learning Rates | D9: Assessment of Factory Fabrication Considerations for Nuclear Microreactors 10.1080/00295450.2023.2206779 | E9: Calculated based on Refernce Paper + Gyutae's work. Refer to TEM Slides for rationale and methodology
A10: No Learning | B10: 0
A11: Licensing Learning | B11: 0.2 | C11: Nth of a kind licening was estimated to take 30-42 months https://www.nrc.gov/docs/ML2426/ML24268A310.pdf Now, it is estimated to take 6- 12 months https://www.govinfo.gov/content/pkg/FR-2026-05-01/pdf/2026-08550.pdf Therefor, the cost is estimated to be reduced 4 times (a factor of 0.25). Since MOUSE is using learning rates, this factor is converted to a learning rate of 0.2 assuming 100 units
A12: Factory Primary Structure | B12: 0.1844317 | C12: FOAK to NOAK Learning Rates
A13: Factory Drums | B13: 0.24138 | C13: FOAK to NOAK Learning Rates
A14: Factory Other | B14: 0.22962848 | C14: FOAK to NOAK Learning Rates
A15: Factory Be | B15: 0.41505378 | C15: FOAK to NOAK Learning Rates
A16: Factory BeO | B16: 0.39914906 | C16: FOAK to NOAK Learning Rates
A17: Non-nuclear off-the-shelf | B17: 0.05 | D17: Park, et al., Bottom-up levelized cost estimation of low-enriched and low-pressure nuclear batteries. Nuclear Engineering and Design. 2025. | E17: For off-the-shelf commercial components that are not produced in the FB Factory
A18: SER Account 30 to Account 20 Ratio | B18: 0.5 | E18: Account 30 is 50% of direct cost (Account 20).
A19: SER Account 716 to Accounts 711-715 Ratio | B19: 0.02 | E19: Continuing education and retraining.
A20: SER Account 717 to Accounts 711-715 Ratio | B20: 0.075 | E20: Management staff.
A21: SER Account 741 to Account 20 Ratio | B21: 0.005 | E21: Operating chemicals and lubricants.
A22: SER Account 742 to Account 20 Ratio | B22: 0.05 | E22: Spare parts.
A23: SER Account 743 to Account 20 Ratio | B23: 0.01 | E23: Utilities excluding electricity, supplies, and consumables.
A24: SER Account 747.1 to Accounts 741-743 Ratio | B24: 0.05 | E24: Annualized transportation costs.
A25: SER Account 747.4 to Account 20 Ratio | B25: 0.005 | E25: Annualized other supplies and utilities.
A26: MFG Account 223 to Reactor OCC per Testing Line Ratio | B26: 0.1 | E26: REVIEW NEEDED: provisional testing-building assumption.
A27: MFG Account 30 to Account 20 Ratio | B27: 0.5 | E27: Account 30 is 50% of direct cost.
A28: MFG Account 716 to Accounts 711-715 Ratio | B28: 0.02 | E28: Continuing education and retraining.
A29: MFG Account 717 to Accounts 711-715 Ratio | B29: 0.075 | E29: Management staff.
... A34: MFG Account 747.4 to Account 20 Ratio | B34: 0.005 | E34: Annualized other supplies and utilities.

Sheet Manufacturing Campus Database
A1: Account | B1: Level | C1: Account Name | D1: Account Title | E1: Standard Cost Equation? | F1: Count Scaling Variable | G1: Count per Variable | H1: Optional Variable | I1: Optional Value | J1: Fixed Cost ($) | K1: Unit Cost | L1: Unit Cost (units) | M1: Scaling Variable | N1: Scaling Variable Ref Value | O1: Units | P1: Exponent | Q1: Dollar Year | R1: Type | S1: Source | T1: Ref | U1: Link | V1: Notes | W1: FOAK to NOAK Multiplier Type | X1: Fixed Cost Low End | Y1: Fixed Cost High End | Z1: Fixed Cost Distribution | AA1: Unit Cost Low End | AB1: Unit Cost High End | AC1: Unit Cost Distribution | AD1: Exponent std | AE1: Exponent Max | AF1: Exponent Min | AG1: Exponent Distribution
A2: 10 | B2: =IF(ISNUMBER(A2), IF(AND(A2=INT(A2), MOD(A2, 10) = 0), 0, IF(AND(A2=INT(A2), LEN(A2)=2), 1, IF(AND(A2=INT(A2), LEN(A2)=3), 2, LEN(A2) - FIND(".", A2) + 2) ) ), "") -> 0 | C2: Capitalized Pre-Construction Costs | D2: =REPT(" ", B2*2) & C2 -> Capitalized Pre-Construction Costs
A3: 11 | B3: =IF(ISNUMBER(A3), IF(AND(A3=INT(A3), MOD(A3, 10) = 0), 0, IF(AND(A3=INT(A3), LEN(A3)=2), 1, IF(AND(A3=INT(A3), LEN(A3)=3), 2, LEN(A3) - FIND(".", A3) + 2) ) ), "") -> 1 | C3: Land Cost | D3: =REPT(" ", B3*2) & C3 -> Land Cost | E3: standard | F3: Constant | G3: 1 | K3: 3800 | L3: $/acres | M3: MFG Campus Land Area | O3: acres | Q3: 2022 | R3: General | S3: The average cost per acre for rural land in 2022 from the US Department of Agriculture | T3: Abou-Jaoude, A., Lohse, C. S., Larsen, L. M., Guaita, N., Trivedi, I., Joseck, F. C., ... & Stein, A. (2024). Meta-analysis of advanced nuclear reactor cost estimations (No. INL/RPT-24-77048-Rev001). Idaho National Laboratory (INL), Idaho Falls, ID (United States). | U3: https://inldigitallibrary.inl.gov/sites/sti/sti/Sort_107010.pdf | W3: No Learning | X3: =0.9*$J3 -> 0 | Y3: =1.5*J3 -> 0 | Z3: Lognormal | AA3: =0.9*K3 -> 3420 | AB3: =1.3*K3 -> 4940 | AC3: Lognormal | AD3: 0.1 | AE3: 1 | AF3: 0 | AG3: Truncated Normal
A4: 12 | B4: =IF(ISNUMBER(A4), IF(AND(A4=INT(A4), MOD(A4, 10) = 0), 0, IF(AND(A4=INT(A4), LEN(A4)=2), 1, IF(AND(A4=INT(A4), LEN(A4)=3), 2, LEN(A4) - FIND(".", A4) + 2) ) ), "") -> 1 | C4: Site Permits | D4: =REPT(" ", B4*2) & C4 -> Site Permits | E4: standard | F4: Constant | G4: 1 | K4: =10.03*1000 -> 10030 | L4: $/MWe | M4: MFG Campus Power | O4: MWe | Q4: 2022 | R4: Labor | S4: Data from SMR MHTGRs | W4: No Learning | X4: =0.9*$J4 -> 0 | Y4: =1.5*J4 -> 0 | Z4: Lognormal | AA4: =0.9*K4 -> 9027 | AB4: =1.3*K4 -> 13039 | AC4: Lognormal | AD4: 0.1 | AE4: 1 | AF4: 0 | AG4: Truncated Normal
A5: 13 | B5: =IF(ISNUMBER(A5), IF(AND(A5=INT(A5), MOD(A5, 10) = 0), 0, IF(AND(A5=INT(A5), LEN(A5)=2), 1, IF(AND(A5=INT(A5), LEN(A5)=3), 2, LEN(A5) - FIND(".", A5) + 2) ) ), "") -> 1 | C5: Plant Licensing | D5: =REPT(" ", B5*2) & C5 -> Plant Licensing | E5: standard | F5: Constant | G5: 1 | J5: =1000000*45 -> 45000000 | Q5: 2009 | R5: Labor | S5: NGNP project | T5: Gandrik, A., B. Wallace, L. Demick, S. Melancon and M. Patterson (2011). "Assessment of high temperature gas-cooled reactor (HTGR) capital and operating costs." Idaho National Laboratory, TEV-1196, Idaho Falls, ID. | U5: https://art.inl.gov/NGNP/INL%20Documents/Year%202012/Assessment%20of%20High%20Temperature%20Gas-Cooled%20Reactor%20-%20HTGR%20-%20Capital%20and%20Operating%20Costs.pdf | W5: No Learning | X5: =45*1000000 -> 45000000 | Y5: =70*1000000 -> 70000000 | Z5: Uniform | AA5: =0.9*K5 -> 0 | AB5: =1.3*K5 -> 0 | AC5: Lognormal | AD5: 0.1 | AE5: 1 | AF5: 0 | AG5: Truncated Normal
A6: 14 | B6: =IF(ISNUMBER(A6), IF(AND(A6=INT(A6), MOD(A6, 10) = 0), 0, IF(AND(A6=INT(A6), LEN(A6)=2), 1, IF(AND(A6=INT(A6), LEN(A6)=3), 2, LEN(A6) - FIND(".", A6) + 2) ) ), "") -> 1 | C6: Plant Permits | D6: =REPT(" ", B6*2) & C6 -> Plant Permits | E6: standard | F6: Constant | G6: 1 | J6: 3000000 | Q6: 2009 | R6: Labor | S6: NGNP project | W6: No Learning | X6: =0.9*$J6 -> 2700000 | Y6: =1.5*J6 -> 4500000 | Z6: Lognormal | AA6: =0.9*K6 -> 0 | AB6: =1.3*K6 -> 0 | AC6: Lognormal | AD6: 0.1 | AE6: 1 | AF6: 0 | AG6: Truncated Normal
A7: 15 | B7: =IF(ISNUMBER(A7), IF(AND(A7=INT(A7), MOD(A7, 10) = 0), 0, IF(AND(A7=INT(A7), LEN(A7)=2), 1, IF(AND(A7=INT(A7), LEN(A7)=3), 2, LEN(A7) - FIND(".", A7) + 2) ) ), "") -> 1 | C7: Plant Studies | D7: =REPT(" ", B7*2) & C7 -> Plant Studies | E7: standard | F7: Constant | G7: 1 | J7: =10*MARVEL_Cost!C4 -> 52104510 | Q7: 2024 | R7: Labor | S7: MARVEL Project (Labor-adjusted Cost) | T7: Hanna, B. N., Gonzaga de Oliveira, R. G., Mohammad Al Dawood, K. A., Patterson, M. D., Abou Jaoude, A., & Garcia, S. (2024). Technoeconomic Evaluation of Microreactor Using Detailed Bottom-up Estimate (No. INL/RPT-24-80433-Rev000). Idaho National Laboratory (INL), Idaho Falls, ID (United States). | U7: https://inldigitallibrary.inl.gov/sites/sti/sti/Sort_129862.pdf | V7: MARVEL's data were updated | W7: No Learning | X7: =0.9*$J7 -> 46894059 | Y7: =1.5*J7 -> 78156765 | Z7: Lognormal | AA7: =0.9*K7 -> 0 | AB7: =1.3*K7 -> 0 | AC7: Lognormal | AD7: 0.1 | AE7: 1 | AF7: 0 | AG7: Truncated Normal
A8: 20 | B8: =IF(ISNUMBER(A8), IF(AND(A8=INT(A8), MOD(A8, 10) = 0), 0, IF(AND(A8=INT(A8), LEN(A8)=2), 1, IF(AND(A8=INT(A8), LEN(A8)=3), 2, LEN(A8) - FIND(".", A8) + 2) ) ), "") -> 0 | C8: Capitalized Direct Costs | D8: =REPT(" ", B8*2) & C8 -> Capitalized Direct Costs | W8: 598
A9: 21 | B9: =IF(ISNUMBER(A9), IF(AND(A9=INT(A9), MOD(A9, 10) = 0), 0, IF(AND(A9=INT(A9), LEN(A9)=2), 1, IF(AND(A9=INT(A9), LEN(A9)=3), 2, LEN(A9) - FIND(".", A9) + 2) ) ), "") -> 1 | C9: Structures and Improvements | D9: =REPT(" ", B9*2) & C9 -> Structures and Improvements
A10: 211 | B10: =IF(ISNUMBER(A10), IF(AND(A10=INT(A10), MOD(A10, 10) = 0), 0, IF(AND(A10=INT(A10), LEN(A10)=2), 1, IF(AND(A10=INT(A10), LEN(A10)=3), 2, LEN(A10) - FIND(".", A10) + 2) ) ), "") -> 2 | C10: Site Preparation/ Yard Work | D10: =REPT(" ", B10*2) & C10 -> Site Preparation/ Yard Work
A11: 211.1 | B11: =IF(ISNUMBER(A11), IF(AND(A11=INT(A11), MOD(A11, 10) = 0), 0, IF(AND(A11=INT(A11), LEN(A11)=2), 1, IF(AND(A11=INT(A11), LEN(A11)=3), 2, LEN(A11) - FIND(".", A11) + 2) ) ), "") -> 3 | C11: Cleaning and Grubbing | D11: =REPT(" ", B11*2) & C11 -> Cleaning and Grubbing | E11: standard | F11: Constant | G11: 1 | K11: =4408.18*1.33 -> 5862.8794 | L11: $/acres | M11: MFG Campus Land Area | O11: acres | Q11: 2024 | R11: Lab and Equip | S11: RSMeans software: a tool that primarily provides costs for non-nuclear work Nuclear Multiplier have been applied to adjust the costs for nuclear-site-related work | T11: GORDIAN. (2024). "RSMeans data. & Delene, J. G. and I. Hudson, C. R. (1993). Cost estimate guidelines for advanced nuclear power technologies. United States, Oak Ridge National Lab. (ORNL), Oak Ridge, TN (United States): Medium: ED; Size: 159 p. | U11: https://www.rsmeans.com/ & https://www.osti.gov/biblio/10176857 | W11: No Learning | X11: =0.9*$J11 -> 0 | Y11: =1.5*J11 -> 0 | Z11: Lognormal | AA11: =0.9*K11 -> 5276.5915 | AB11: =1.3*K11 -> 7621.7432 | AC11: Lognormal | AD11: 0.1 | AE11: 1 | AF11: 0 | AG11: Truncated Normal
A12: 211.2 | B12: =IF(ISNUMBER(A12), IF(AND(A12=INT(A12), MOD(A12, 10) = 0), 0, IF(AND(A12=INT(A12), LEN(A12)=2), 1, IF(AND(A12=INT(A12), LEN(A12)=3), 2, LEN(A12) - FIND(".", A12) + 2) ) ), "") -> 3 | C12: Stripping Topsoil | D12: =REPT(" ", B12*2) & C12 -> Stripping Topsoil | E12: standard | F12: Constant | G12: 1 | K12: =2565.2*1.33 -> 3411.716 | L12: $/acres | M12: MFG Campus Land Area | O12: acres | Q12: 2024 | R12: Lab and Equip | W12: No Learning | X12: =0.9*$J12 -> 0 | Y12: =1.5*J12 -> 0 | Z12: Lognormal | AA12: =0.9*K12 -> 3070.5444 | AB12: =1.3*K12 -> 4435.2308 | AC12: Lognormal | AD12: 0.1 | AE12: 1 | AF12: 0 | AG12: Truncated Normal
A13: 211.4 | B13: =IF(ISNUMBER(A13), IF(AND(A13=INT(A13), MOD(A13, 10) = 0), 0, IF(AND(A13=INT(A13), LEN(A13)=2), 1, IF(AND(A13=INT(A13), LEN(A13)=3), 2, LEN(A13) - FIND(".", A13) + 2) ) ), "") -> 3 | C13: Roads | D13: =REPT(" ", B13*2) & C13 -> Roads | E13: standard | F13: Constant | G13: 1 | K13: =0.7*7873200*1.609/1000 -> 8867.5852 | L13: $/m | M13: MFG Road Length | N13: 1 | P13: 1 | Q13: 2025 | R13: General | S13: MC30 Cost Estimation of Microreactor Facilities Inital Draft 5-6-2026.pdf, less 30% | W13: No Learning | X13: =0.9*$J13 -> 0 | Y13: =1.5*J13 -> 0 | Z13: Lognormal | AA13: =0.9*K13 -> 7980.8266 | AB13: =1.3*K13 -> 11527.861 | AC13: Lognormal | AD13: 0.1 | AE13: 1 | AF13: 0 | AG13: Truncated Normal
A14: 211.9 | B14: =IF(ISNUMBER(A14), IF(AND(A14=INT(A14), MOD(A14, 10) = 0), 0, IF(AND(A14=INT(A14), LEN(A14)=2), 1, IF(AND(A14=INT(A14), LEN(A14)=3), 2, LEN(A14) - FIND(".", A14) + 2) ) ), "") -> 3 | C14: Security Fencing | D14: =REPT(" ", B14*2) & C14 -> Security Fencing
A15: 211.91 | B15: =IF(ISNUMBER(A15), IF(AND(A15=INT(A15), MOD(A15, 10) = 0), 0, IF(AND(A15=INT(A15), LEN(A15)=2), 1, IF(AND(A15=INT(A15), LEN(A15)=3), 2, LEN(A15) - FIND(".", A15) + 2) ) ), "") -> 4 | C15: Security Fencing Limited | D15: =REPT(" ", B15*2) & C15 -> Security Fencing Limited | E15: standard | F15: Constant | G15: 1 | K15: =0.7*273 -> 191.1 | L15: $/ft | M15: MFG Site Perimeter | Q15: 2025 | R15: Lab and Equip | S15: MC30 Cost Estimation of Microreactor Facilities Inital Draft 5-6-2026.pdf, less 30% | W15: No Learning | X15: =0.9*$J15 -> 0 | Y15: =1.5*J15 -> 0 | Z15: Lognormal | AA15: =0.9*K15 -> 171.99 | AB15: =1.3*K15 -> 248.43 | AC15: Lognormal | AD15: 0.1 | AE15: 1 | AF15: 0 | AG15: Truncated Normal
A16: 211.93 | B16: =IF(ISNUMBER(A16), IF(AND(A16=INT(A16), MOD(A16, 10) = 0), 0, IF(AND(A16=INT(A16), LEN(A16)=2), 1, IF(AND(A16=INT(A16), LEN(A16)=3), 2, LEN(A16) - FIND(".", A16) + 2) ) ), "") -> 4 | C16: Security Fencing Protected | D16: =REPT(" ", B16*2) & C16 -> Security Fencing Protected | E16: standard | F16: Constant | G16: 1 | K16: =0.7*15746 -> 11022.2 | L16: $/ft | M16: MFG Protected Perimeter | Q16: 2025 | R16: Lab and Equip | S16: MC30 Cost Estimation of Microreactor Facilities Inital Draft 5-6-2026.pdf, less 30% | W16: No Learning | X16: =0.9*$J16 -> 0 | Y16: =1.5*J16 -> 0 | Z16: Lognormal | AA16: =0.9*K16 -> 9919.98 | AB16: =1.3*K16 -> 14328.86 | AC16: Lognormal | AD16: 0.1 | AE16: 1 | AF16: 0 | AG16: Truncated Normal
A17: 214 | B17: =IF(ISNUMBER(A17), IF(AND(A17=INT(A17), MOD(A17, 10) = 0), 0, IF(AND(A17=INT(A17), LEN(A17)=2), 1, IF(AND(A17=INT(A17), LEN(A17)=3), 2, LEN(A17) - FIND(".", A17) + 2) ) ), "") -> 2 | C17: Servicing Facilities Structures | D17: =REPT(" ", B17*2) & C17 -> Servicing Facilities Structures
A18: 214.3 | B18: =IF(ISNUMBER(A18), IF(AND(A18=INT(A18), MOD(A18, 10) = 0), 0, IF(AND(A18=INT(A18), LEN(A18)=2), 1, IF(AND(A18=INT(A18), LEN(A18)=3), 2, LEN(A18) - FIND(".", A18) + 2) ) ), "") -> 3 | C18: Control Buidlings | D18: =REPT(" ", B18*2) & C18 -> Control Buidlings
A19: 214.31 | B19: 4 | C19: Local Control Buidling Structure | D19: =REPT(" ", B19*2) & C19 -> Local Control Buidling Structure | E19: standard | F19: Constant | G19: 1 | K19: =0.7*2653*(3.2808^2) -> 19989.172 | L19: $/m^2 | M19: MFG Local Control Building Area | N19: 1 | O19: m^2 | P19: 1 | Q19: 2025 | R19: Lab and Mat and Equip | S19: 100 value from MC30 Cost Estimation of Microreactor Facilities Inital Draft 5-6-2026.pdf, less 30% [temporary, want to add scaling equation] | W19: No Learning | X19: =0.9*$I19 -> 0 | Y19: =1.5*J19 -> 0 | Z19: Lognormal | AA19: =0.9*K19 -> 17990.255 | AB19: =1.3*K19 -> 25985.923 | AC19: Lognormal | AD19: 0.1 | AE19: 1 | AF19: 0 | AG19: Truncated Normal
A20: 22 | B20: =IF(ISNUMBER(A20), IF(AND(A20=INT(A20), MOD(A20, 10) = 0), 0, IF(AND(A20=INT(A20), LEN(A20)=2), 1, IF(AND(A20=INT(A20), LEN(A20)=3), 2, LEN(A20) - FIND(".", A20) + 2) ) ), "") -> 1 | C20: Main Facilities Estimated As Wholes | D20: =REPT(" ", B20*2) & C20 -> Main Facilities Estimated As Wholes
A21: 221 | B21: =IF(ISNUMBER(A21), IF(AND(A21=INT(A21), MOD(A21, 10) = 0), 0, IF(AND(A21=INT(A21), LEN(A21)=2), 1, IF(AND(A21=INT(A21), LEN(A21)=3), 2, LEN(A21) - FIND(".", A21) + 2) ) ), "") -> 2 | C21: Manufacturing Building | D21: =REPT(" ", B21*2) & C21 -> Manufacturing Building | E21: standard | K21: =62733028.09/N21 -> 62733.028 | M21: Production Rate | N21: 1000 | O21: Rx/yr | P21: 0.13827065 | Q21: 2025 | R21: Lab and Mat and Equip | W21: No Learning | X21: =0.9*$I21 -> 0 | Y21: =1.5*J21 -> 0 | Z21: Lognormal | AA21: =0.9*K21 -> 56459.725 | AB21: =1.3*K21 -> 81552.937 | AC21: Lognormal | AD21: 0.1 | AE21: 1 | AF21: 0 | AG21: Truncated Normal
A22: 222 | B22: =IF(ISNUMBER(A22), IF(AND(A22=INT(A22), MOD(A22, 10) = 0), 0, IF(AND(A22=INT(A22), LEN(A22)=2), 1, IF(AND(A22=INT(A22), LEN(A22)=3), 2, LEN(A22) - FIND(".", A22) + 2) ) ), "") -> 2 | C22: Fueling Building | D22: =REPT(" ", B22*2) & C22 -> Fueling Building | E22: standard | K22: =35766971.91/N22 -> 35766.972 | M22: Production Rate | N22: 1000 | O22: Rx/yr | P22: 0.13827065 | Q22: 2025 | R22: Lab and Mat and Equip | W22: No Learning | X22: =0.9*$I22 -> 0 | Y22: =1.5*J22 -> 0 | Z22: Lognormal | AA22: =0.9*K22 -> 32190.275 | AB22: =1.3*K22 -> 46497.063 | AC22: Lognormal | AD22: 0.1 | AE22: 1 | AF22: 0 | AG22: Truncated Normal
A23: 223 | B23: 2 | C23: Testing Building | D23: =REPT(" ", B23*2) & C23 -> Testing Building | W23: No Learning | X23: =0.9*$I23 -> 0 | Y23: =1.5*J23 -> 0 | Z23: Lognormal | AA23: =0.9*K23 -> 0 | AB23: =1.3*K23 -> 0 | AC23: Lognormal | AD23: 0.1 | AE23: 1 | AF23: 0 | AG23: Truncated Normal
A24: 224 | B24: =IF(ISNUMBER(A24), IF(AND(A24=INT(A24), MOD(A24, 10) = 0), 0, IF(AND(A24=INT(A24), LEN(A24)=2), 1, IF(AND(A24=INT(A24), LEN(A24)=3), 2, LEN(A24) - FIND(".", A24) + 2) ) ), "") -> 2 | C24: Warehouse | D24: =REPT(" ", B24*2) & C24 -> Warehouse | E24: standard | K24: 3842.71 | L24: $/m^2 | M24: MFG Warehouse Building Area | N24: 1 | O24: m^2 | P24: 1 | Q24: 2025 | R24: Lab and Mat and Equip | W24: No Learning | X24: =0.9*$I24 -> 0 | Y24: =1.5*J24 -> 0 | Z24: Lognormal | AA24: =0.9*K24 -> 3458.439 | AB24: =1.3*K24 -> 4995.523 | AC24: Lognormal | AD24: 0.1 | AE24: 1 | AF24: 0 | AG24: Truncated Normal
A25: 225 | B25: =IF(ISNUMBER(A25), IF(AND(A25=INT(A25), MOD(A25, 10) = 0), 0, IF(AND(A25=INT(A25), LEN(A25)=2), 1, IF(AND(A25=INT(A25), LEN(A25)=3), 2, LEN(A25) - FIND(".", A25) + 2) ) ), "") -> 2 | C25: Administrative Building | D25: =REPT(" ", B25*2) & C25 -> Administrative Building | E25: standard | K25: =0.7*1968*(3.2808^2) -> 14828.002 | L25: $/m^2 | M25: MFG Administration Building Area | N25: 1 | O25: m^2 | P25: 1 | Q25: 2025 | R25: Lab and Mat and Equip | S25: 100 value from MC30 Cost Estimation of Microreactor Facilities Inital Draft 5-6-2026.pdf, less 30% [temporary, want to add scaling equation] | W25: No Learning | X25: =0.9*$I25 -> 0 | Y25: =1.5*J25 -> 0 | Z25: Lognormal | AA25: =0.9*K25 -> 13345.202 | AB25: =1.3*K25 -> 19276.403 | AC25: Lognormal | AD25: 0.1 | AE25: 1 | AF25: 0 | AG25: Truncated Normal
A26: 23 | B26: =IF(ISNUMBER(A26), IF(AND(A26=INT(A26), MOD(A26, 10) = 0), 0, IF(AND(A26=INT(A26), LEN(A26)=2), 1, IF(AND(A26=INT(A26), LEN(A26)=3), 2, LEN(A26) - FIND(".", A26) + 2) ) ), "") -> 1 | C26: Equipment | D26: =REPT(" ", B26*2) & C26 -> Equipment
A27: 23.5 | B27: 2 | C27: Local Integrated Control Rooms | D27: =REPT(" ", B27*2) & C27 -> Local Integrated Control Rooms | E27: standard | F27: MFG Testing Line Count | G27: 1 | J27: 8500000 | Q27: 2023 | R27: Lab and Equip | S27: Shirvan et al., 2023 | T27: Shirvan et al,. (2023). UO2-fueled microreactors: Near-term solutions to emerging marktets. Nuclear Engineering and Design. | U27: https://doi.org/10.1016/j.nucengdes.2023.112470 | V27: Cost based on FOAK Digital I&C with 2-out-of-4 voting logic | W27: Factory Other | X27: =0.9*$H27 -> 0 | Y27: =1.5*J27 -> 12750000 | Z27: Lognormal | AA27: =0.9*K27 -> 0 | AB27: =1.3*K27 -> 0 | AC27: Lognormal | AD27: 0.1 | AE27: 1 | AF27: 0 | AG27: Truncated Normal
A28: 28 | B28: =IF(ISNUMBER(A28), IF(AND(A28=INT(A28), MOD(A28, 10) = 0), 0, IF(AND(A28=INT(A28), LEN(A28)=2), 1, IF(AND(A28=INT(A28), LEN(A28)=3), 2, LEN(A28) - FIND(".", A28) + 2) ) ), "") -> 1 | C28: Auxiliary Infrastructure Equipment | D28: =REPT(" ", B28*2) & C28 -> Auxiliary Infrastructure Equipment
A29: 281 | B29: =IF(ISNUMBER(A29), IF(AND(A29=INT(A29), MOD(A29, 10) = 0), 0, IF(AND(A29=INT(A29), LEN(A29)=2), 1, IF(AND(A29=INT(A29), LEN(A29)=3), 2, LEN(A29) - FIND(".", A29) + 2) ) ), "") -> 2 | C29: Emergency Power | D29: =REPT(" ", B29*2) & C29 -> Emergency Power | E29: standard | K29: =(1450000*5+1500000)/2.5 -> 3500000 | L29: $/MWe | M29: MFG Emergency Generator Power | N29: 1 | O29: MWe | P29: 1 | Q29: 2025 | R29: Equipment | S29: 2.5 MW generator cost from Central States Generators, nuclear multiple of 5, and guess for pad and connection to building (pad and connection have been requested with cost estimators)
A30: 283 | B30: =IF(ISNUMBER(A30), IF(AND(A30=INT(A30), MOD(A30, 10) = 0), 0, IF(AND(A30=INT(A30), LEN(A30)=2), 1, IF(AND(A30=INT(A30), LEN(A30)=3), 2, LEN(A30) - FIND(".", A30) + 2) ) ), "") -> 2 | C30: Fire Station | D30: =REPT(" ", B30*2) & C30 -> Fire Station | E30: standard | F30: MFG Fire Station Count | G30: 1 | J30: =0.7*20776500 -> 14543550 | Q30: 2025 | R30: Lab and Mat and Equip | S30: 100 value from MC30 Cost Estimation of Microreactor Facilities Inital Draft 5-6-2026.pdf, less 30% [temporary, want to add scaling equation] | W30: No Learning | X30: =0.9*$I30 -> 0 | Y30: =1.5*J30 -> 21815325 | Z30: Lognormal | AA30: =0.9*K30 -> 0 | AB30: =1.3*K30 -> 0 | AC30: Lognormal | AD30: 0.1 | AE30: 1 | AF30: 0 | AG30: Truncated Normal
A31: 284 | B31: =IF(ISNUMBER(A31), IF(AND(A31=INT(A31), MOD(A31, 10) = 0), 0, IF(AND(A31=INT(A31), LEN(A31)=2), 1, IF(AND(A31=INT(A31), LEN(A31)=3), 2, LEN(A31) - FIND(".", A31) + 2) ) ), "") -> 2 | C31: Security Building | D31: =REPT(" ", B31*2) & C31 -> Security Building | E31: standard | K31: =0.7*2548*(3.2808^2) -> 19198.044 | L31: $/m^2 | M31: MFG Security Building Area | N31: 1 | O31: m^2 | P31: 1 | Q31: 2025 | R31: Lab and Mat and Equip | S31: 100 value from MC30 Cost Estimation of Microreactor Facilities Inital Draft 5-6-2026.pdf, less 30% [temporary, want to add scaling equation] | W31: No Learning | X31: =0.9*$I31 -> 0 | Y31: =1.5*J31 -> 0 | Z31: Lognormal | AA31: =0.9*K31 -> 17278.239 | AB31: =1.3*K31 -> 24957.457 | AC31: Lognormal | AD31: 0.1 | AE31: 1 | AF31: 0 | AG31: Truncated Normal
A32: 285 | B32: =IF(ISNUMBER(A32), IF(AND(A32=INT(A32), MOD(A32, 10) = 0), 0, IF(AND(A32=INT(A32), LEN(A32)=2), 1, IF(AND(A32=INT(A32), LEN(A32)=3), 2, LEN(A32) - FIND(".", A32) + 2) ) ), "") -> 2 | C32: Switchyard | D32: =REPT(" ", B32*2) & C32 -> Switchyard | E32: standard | K32: =0.7*221450153/N32 -> 516717.02 | L32: $/MWe | M32: MFG Switchyard Rating | N32: 300 | O32: MWe | P32: 0.9968 | Q32: 2025 | R32: Lab and Mat and Equip | S32: Scaling relationship created from MC30 Cost Estimation of Microreactor Facilities Inital Draft 5-6-2026.pdf, less 30% | W32: No Learning | X32: =0.9*$I32 -> 0 | Y32: =1.5*J32 -> 0 | Z32: Lognormal | AA32: =0.9*K32 -> 465045.32 | AB32: =1.3*K32 -> 671732.13 | AC32: Lognormal | AD32: 0.1 | AE32: 1 | AF32: 0 | AG32: Truncated Normal
A33: 286 | B33: =IF(ISNUMBER(A33), IF(AND(A33=INT(A33), MOD(A33, 10) = 0), 0, IF(AND(A33=INT(A33), LEN(A33)=2), 1, IF(AND(A33=INT(A33), LEN(A33)=3), 2, LEN(A33) - FIND(".", A33) + 2) ) ), "") -> 2 | C33: Onsite Transport Equipment | D33: =REPT(" ", B33*2) & C33 -> Onsite Transport Equipment
A34: 286.1 | B34: =IF(ISNUMBER(A34), IF(AND(A34=INT(A34), MOD(A34, 10) = 0), 0, IF(AND(A34=INT(A34), LEN(A34)=2), 1, IF(AND(A34=INT(A34), LEN(A34)=3), 2, LEN(A34) - FIND(".", A34) + 2) ) ), "") -> 3 | C34: Local Reactor Transport Vehicles | D34: =REPT(" ", B34*2) & C34 -> Local Reactor Transport Vehicles | E34: standard | F34: MFG Local Transport Vehicle Count | G34: 1 | J34: 938000 | Q34: 2023 | R34: Equipment | S34: Lallemant report, Table 9, Considered price for 200 MT LTV | T34: Lallemant, Lucas. 2023 | W34: No Learning | X34: =0.9*$J34 -> 844200 | Y34: =1.5*J34 -> 1407000 | Z34: Lognormal | AA34: =0.9*K34 -> 0 | AB34: =1.3*K34 -> 0 | AC34: Lognormal | AD34: 0.1 | AE34: 1 | AF34: 0 | AG34: Truncated Normal
A35: 286.2 | B35: =IF(ISNUMBER(A35), IF(AND(A35=INT(A35), MOD(A35, 10) = 0), 0, IF(AND(A35=INT(A35), LEN(A35)=2), 1, IF(AND(A35=INT(A35), LEN(A35)=3), 2, LEN(A35) - FIND(".", A35) + 2) ) ), "") -> 3 | C35: Utility Vehicles | D35: =REPT(" ", B35*2) & C35 -> Utility Vehicles | E35: standard | F35: MFG Utility Vehicle Count | G35: 1 | J35: 50000 | Q35: 2024 | R35: Equipment | S35: assumption | W35: No Learning | X35: =0.9*$J35 -> 45000 | Y35: =1.5*J35 -> 75000 | Z35: Lognormal | AA35: =0.9*K35 -> 0 | AB35: =1.3*K35 -> 0 | AC35: Lognormal | AD35: 0.1 | AE35: 1 | AF35: 0 | AG35: Truncated Normal
A36: 288 | B36: =IF(ISNUMBER(A36), IF(AND(A36=INT(A36), MOD(A36, 10) = 0), 0, IF(AND(A36=INT(A36), LEN(A36)=2), 1, IF(AND(A36=INT(A36), LEN(A36)=3), 2, LEN(A36) - FIND(".", A36) + 2) ) ), "") -> 2 | C36: Dispered Infrastructure | D36: =REPT(" ", B36*2) & C36 -> Dispered Infrastructure | S36: assumption, guess
A37: 288.1 | B37: 3 | C37: Communication | D37: =REPT(" ", B37*2) & C37 -> Communication | E37: standard | K37: =12575250/N37 -> 11774.579 | L37: $/acres | M37: Manufacturing Campus Area | N37: 1068 | O37: acres | Q37: 2025 | R37: Equipment | S37: [to become a scaling relationship] MC30 Cost Estimation of Microreactor Facilities Inital Draft 5-6-2026.pdf
A38: 288.2 | B38: 3 | C38: Security Cameras | D38: =REPT(" ", B38*2) & C38 -> Security Cameras | E38: standard | F38: MFG Security Camera Count | G38: 1 | J38: 28431 | Q38: 2025 | R38: Equipment | S38: MC30 Cost Estimation of Microreactor Facilities Inital Draft 5-6-2026.pdf
A39: 288.3 | B39: 3 | C39: Motion Detectors | D39: =REPT(" ", B39*2) & C39 -> Motion Detectors | E39: standard | F39: MFG Motion Detector Count | G39: 1 | J39: 24057 | Q39: 2025 | R39: Equipment | S39: MC30 Cost Estimation of Microreactor Facilities Inital Draft 5-6-2026.pdf
A40: 288.4 | B40: 3 | C40: Guard Station | D40: =REPT(" ", B40*2) & C40 -> Guard Station | E40: standard | F40: MFG Guard Station Count | G40: 1 | J40: 6774250 | Q40: 2025 | R40: Equipment | S40: MC30 Cost Estimation of Microreactor Facilities Inital Draft 5-6-2026.pdf
A41: 30 | B41: =IF(ISNUMBER(A41), IF(AND(A41=INT(A41), MOD(A41, 10) = 0), 0, IF(AND(A41=INT(A41), LEN(A41)=2), 1, IF(AND(A41=INT(A41), LEN(A41)=3), 2, LEN(A41) - FIND(".", A41) + 2) ) ), "") -> 0 | C41: Capitalized Indirect Services Cost | D41: =REPT(" ", B41*2) & C41 -> Capitalized Indirect Services Cost
A42: 40 | B42: =IF(ISNUMBER(A42), IF(AND(A42=INT(A42), MOD(A42, 10) = 0), 0, IF(AND(A42=INT(A42), LEN(A42)=2), 1, IF(AND(A42=INT(A42), LEN(A42)=3), 2, LEN(A42) - FIND(".", A42) + 2) ) ), "") -> 0 | C42: Capitalized training costs | D42: =REPT(" ", B42*2) & C42 -> Capitalized training costs
A43: 41 | B43: =IF(ISNUMBER(A43), IF(AND(A43=INT(A43), MOD(A43, 10) = 0), 0, IF(AND(A43=INT(A43), LEN(A43)=2), 1, IF(AND(A43=INT(A43), LEN(A43)=3), 2, LEN(A43) - FIND(".", A43) + 2) ) ), "") -> 1 | C43: staff recruitment and training | D43: =REPT(" ", B43*2) & C43 -> staff recruitment and training | E43: standard | F43: Constant | G43: 1 | J43: 300000 | Q43: 2024 | R43: Labor | W43: No Learning | X43: =0.9*$J43 -> 270000 | Y43: =1.5*J43 -> 450000 | Z43: Lognormal | AA43: =0.9*K43 -> 0 | AB43: =1.3*K43 -> 0 | AC43: Lognormal | AD43: 0.1 | AE43: 1 | AF43: 0 | AG43: Truncated Normal
A44: 60 | B44: =IF(ISNUMBER(A44), IF(AND(A44=INT(A44), MOD(A44, 10) = 0), 0, IF(AND(A44=INT(A44), LEN(A44)=2), 1, IF(AND(A44=INT(A44), LEN(A44)=3), 2, LEN(A44) - FIND(".", A44) + 2) ) ), "") -> 0 | C44: Capitalized Financial Costs | D44: =REPT(" ", B44*2) & C44 -> Capitalized Financial Costs
A45: 62 | B45: =IF(ISNUMBER(A45), IF(AND(A45=INT(A45), MOD(A45, 10) = 0), 0, IF(AND(A45=INT(A45), LEN(A45)=2), 1, IF(AND(A45=INT(A45), LEN(A45)=3), 2, LEN(A45) - FIND(".", A45) + 2) ) ), "") -> 1 | C45: Interest | D45: =REPT(" ", B45*2) & C45 -> Interest
A46: 70 | B46: =IF(ISNUMBER(A46), IF(AND(A46=INT(A46), MOD(A46, 10) = 0), 0, IF(AND(A46=INT(A46), LEN(A46)=2), 1, IF(AND(A46=INT(A46), LEN(A46)=3), 2, LEN(A46) - FIND(".", A46) + 2) ) ), "") -> 0 | C46: Annualized O&M Cost | D46: =REPT(" ", B46*2) & C46 -> Annualized O&M Cost
A47: 71 | B47: =IF(ISNUMBER(A47), IF(AND(A47=INT(A47), MOD(A47, 10) = 0), 0, IF(AND(A47=INT(A47), LEN(A47)=2), 1, IF(AND(A47=INT(A47), LEN(A47)=3), 2, LEN(A47) - FIND(".", A47) + 2) ) ), "") -> 1 | C47: O&M Staff | D47: =REPT(" ", B47*2) & C47 -> O&M Staff
A48: 711 | B48: =IF(ISNUMBER(A48), IF(AND(A48=INT(A48), MOD(A48, 10) = 0), 0, IF(AND(A48=INT(A48), LEN(A48)=2), 1, IF(AND(A48=INT(A48), LEN(A48)=3), 2, LEN(A48) - FIND(".", A48) + 2) ) ), "") -> 2 | C48: Operators (Testing Only) | D48: =REPT(" ", B48*2) & C48 -> Operators (Testing Only) | E48: nonstandard | K48: 178500 | L48: $/FTE | M48: MFG Testing Number of Operators | P48: 1 | Q48: 2024 | R48: Labor | T48: de Candido, I., A. Al Rashdan, A. Abou-Jaoude, and J. Buongiorno. 2024. “Assessment of Technoeconomic Opportunities in Automation for Nuclear Microreactors.” Nuclear Science and Engineering, 1–20. https://doi.org/10.1080/00295639.2024.2372511. | W48: No Learning | X48: =0.9*$J48 -> 0 | Y48: =1.5*J48 -> 0 | Z48: Lognormal | AA48: =0.9*K48 -> 160650 | AB48: =1.3*K48 -> 232050 | AC48: Lognormal | AD48: 0.1 | AE48: 1 | AF48: 0 | AG48: Truncated Normal
A49: 712 | B49: =IF(ISNUMBER(A49), IF(AND(A49=INT(A49), MOD(A49, 10) = 0), 0, IF(AND(A49=INT(A49), LEN(A49)=2), 1, IF(AND(A49=INT(A49), LEN(A49)=3), 2, LEN(A49) - FIND(".", A49) + 2) ) ), "") -> 2 | C49: Warehouse Staff | D49: =REPT(" ", B49*2) & C49 -> Warehouse Staff | E49: nonstandard | K49: 113000 | L49: $/FTE | M49: MFG Warehouse Staff | P49: 1 | Q49: 2024 | R49: Labor | S49: Average of four occupations from Munro work: Forklift Drivers, Supervisors, Shipping/receiving personnel, and Materials Scheduler (high ends for all) | T49: INL Fueling - Manufacturing Parts and Equipment List Rev002.xlsx | W49: No Learning | X49: =0.9*$J49 -> 0 | Y49: =1.5*J49 -> 0 | Z49: Lognormal | AA49: =0.9*K49 -> 101700 | AB49: =1.3*K49 -> 146900 | AC49: Lognormal | AD49: 0.1 | AE49: 1 | AF49: 0 | AG49: Truncated Normal
A50: 713 | B50: =IF(ISNUMBER(A50), IF(AND(A50=INT(A50), MOD(A50, 10) = 0), 0, IF(AND(A50=INT(A50), LEN(A50)=2), 1, IF(AND(A50=INT(A50), LEN(A50)=3), 2, LEN(A50) - FIND(".", A50) + 2) ) ), "") -> 2 | C50: Security Staff | D50: =REPT(" ", B50*2) & C50 -> Security Staff | E50: nonstandard | K50: 178500 | L50: $/FTE | M50: MFG Security Staff Per Shift | P50: 1 | Q50: 2024 | R50: Labor | T50: de Candido, I., A. Al Rashdan, A. Abou-Jaoude, and J. Buongiorno. 2024. “Assessment of Technoeconomic Opportunities in Automation for Nuclear Microreactors.” Nuclear Science and Engineering, 1–20. https://doi.org/10.1080/00295639.2024.2372511. | W50: No Learning | X50: =0.9*$J50 -> 0 | Y50: =1.5*J50 -> 0 | Z50: Lognormal | AA50: =0.9*K50 -> 160650 | AB50: =1.3*K50 -> 232050 | AC50: Lognormal | AD50: 0.1 | AE50: 1 | AF50: 0 | AG50: Truncated Normal
A51: 714 | B51: =IF(ISNUMBER(A51), IF(AND(A51=INT(A51), MOD(A51, 10) = 0), 0, IF(AND(A51=INT(A51), LEN(A51)=2), 1, IF(AND(A51=INT(A51), LEN(A51)=3), 2, LEN(A51) - FIND(".", A51) + 2) ) ), "") -> 2 | C51: Maintenance Staff | D51: =REPT(" ", B51*2) & C51 -> Maintenance Staff | E51: nonstandard | K51: 178500 | L51: $/FTE | M51: MFG Maintenance Staff Headcount | P51: 1 | Q51: 2024 | R51: Labor | T51: de Candido, I., A. Al Rashdan, A. Abou-Jaoude, and J. Buongiorno. 2024. “Assessment of Technoeconomic Opportunities in Automation for Nuclear Microreactors.” Nuclear Science and Engineering, 1–20. https://doi.org/10.1080/00295639.2024.2372511. | W51: No Learning | X51: =0.9*$J51 -> 0 | Y51: =1.5*J51 -> 0 | Z51: Lognormal | AA51: =0.9*K51 -> 160650 | AB51: =1.3*K51 -> 232050 | AC51: Lognormal | AD51: 0.1 | AE51: 1 | AF51: 0 | AG51: Truncated Normal
A52: 715 | B52: =IF(ISNUMBER(A52), IF(AND(A52=INT(A52), MOD(A52, 10) = 0), 0, IF(AND(A52=INT(A52), LEN(A52)=2), 1, IF(AND(A52=INT(A52), LEN(A52)=3), 2, LEN(A52) - FIND(".", A52) + 2) ) ), "") -> 2 | C52: Engineering Staff (Testing Only) | D52: =REPT(" ", B52*2) & C52 -> Engineering Staff (Testing Only) | E52: nonstandard | K52: 200000 | L52: $/FTE | M52: MFG Testing Engineering Headcount | Q52: 2024 | R52: Labor | W52: No Learning | X52: =0.9*$J52 -> 0 | Y52: =1.5*J52 -> 0 | Z52: Lognormal | AA52: =0.9*K52 -> 180000 | AB52: =1.3*K52 -> 260000 | AC52: Lognormal | AD52: 0.1 | AE52: 1 | AF52: 0 | AG52: Truncated Normal
A53: 716 | B53: =IF(ISNUMBER(A53), IF(AND(A53=INT(A53), MOD(A53, 10) = 0), 0, IF(AND(A53=INT(A53), LEN(A53)=2), 1, IF(AND(A53=INT(A53), LEN(A53)=3), 2, LEN(A53) - FIND(".", A53) + 2) ) ), "") -> 2 | C53: Continuing Education and Staff Retraining | D53: =REPT(" ", B53*2) & C53 -> Continuing Education and Staff Retraining | R53: Labor | W53: No Learning | X53: =0.9*$J53 -> 0 | Y53: =1.5*J53 -> 0 | Z53: Lognormal | AA53: =0.9*K53 -> 0 | AB53: =1.3*K53 -> 0 | AC53: Lognormal | AD53: 0.1 | AE53: 1 | AF53: 0 | AG53: Truncated Normal
A54: 717 | B54: =IF(ISNUMBER(A54), IF(AND(A54=INT(A54), MOD(A54, 10) = 0), 0, IF(AND(A54=INT(A54), LEN(A54)=2), 1, IF(AND(A54=INT(A54), LEN(A54)=3), 2, LEN(A54) - FIND(".", A54) + 2) ) ), "") -> 2 | C54: Management Staff | D54: =REPT(" ", B54*2) & C54 -> Management Staff | R54: Labor | W54: No Learning | X54: =0.9*$J54 -> 0 | Y54: =1.5*J54 -> 0 | Z54: Lognormal | AA54: =0.9*K54 -> 0 | AB54: =1.3*K54 -> 0 | AC54: Lognormal | AD54: 0.1 | AE54: 1 | AF54: 0 | AG54: Truncated Normal
A55: 718 | B55: =IF(ISNUMBER(A55), IF(AND(A55=INT(A55), MOD(A55, 10) = 0), 0, IF(AND(A55=INT(A55), LEN(A55)=2), 1, IF(AND(A55=INT(A55), LEN(A55)=3), 2, LEN(A55) - FIND(".", A55) + 2) ) ), "") -> 2 | C55: Manfuacturing Building Staff | D55: =REPT(" ", B55*2) & C55 -> Manfuacturing Building Staff | E55: standard | K55: 2838754.4 | L55: unitless | M55: Production Rate | N55: 1 | O55: Rx/yr | P55: 0.147041 | Q55: 2025 | R55: Labor | W55: No Learning | X55: =0.9*$J55 -> 0 | Y55: =1.5*J55 -> 0 | Z55: Lognormal | AA55: =0.9*K55 -> 2554878.9 | AB55: =1.3*K55 -> 3690380.7 | AC55: Lognormal | AD55: 0.1 | AE55: 1 | AF55: 0 | AG55: Truncated Normal
A56: 719 | B56: =IF(ISNUMBER(A56), IF(AND(A56=INT(A56), MOD(A56, 10) = 0), 0, IF(AND(A56=INT(A56), LEN(A56)=2), 1, IF(AND(A56=INT(A56), LEN(A56)=3), 2, LEN(A56) - FIND(".", A56) + 2) ) ), "") -> 2 | C56: Fueling Building Staff | D56: =REPT(" ", B56*2) & C56 -> Fueling Building Staff | E56: standard | K56: 699358.86 | L56: unitless | M56: Production Rate | N56: 1 | O56: Rx/yr | P56: 0.29939 | Q56: 2025 | R56: Labor | W56: No Learning | X56: =0.9*$J56 -> 0 | Y56: =1.5*J56 -> 0 | Z56: Lognormal | AA56: =0.9*K56 -> 629422.97 | AB56: =1.3*K56 -> 909166.51 | AC56: Lognormal | AD56: 0.1 | AE56: 1 | AF56: 0 | AG56: Truncated Normal
A57: 74 | B57: =IF(ISNUMBER(A57), IF(AND(A57=INT(A57), MOD(A57, 10) = 0), 0, IF(AND(A57=INT(A57), LEN(A57)=2), 1, IF(AND(A57=INT(A57), LEN(A57)=3), 2, LEN(A57) - FIND(".", A57) + 2) ) ), "") -> 1 | C57: Fixed O&M Utilities and Materials | D57: =REPT(" ", B57*2) & C57 -> Fixed O&M Utilities and Materials
A58: 741 | B58: =IF(ISNUMBER(A58), IF(AND(A58=INT(A58), MOD(A58, 10) = 0), 0, IF(AND(A58=INT(A58), LEN(A58)=2), 1, IF(AND(A58=INT(A58), LEN(A58)=3), 2, LEN(A58) - FIND(".", A58) + 2) ) ), "") -> 2 | C58: Operating Chemicals and Lubricants (Except Manufacturing and Fueling) | D58: =REPT(" ", B58*2) & C58 -> Operating Chemicals and Lubricants (Except Manufacturing and Fueling) | W58: No Learning | X58: =0.9*$J58 -> 0 | Y58: =1.5*J58 -> 0 | Z58: Lognormal | AA58: =0.9*K58 -> 0 | AB58: =1.3*K58 -> 0 | AC58: Lognormal | AD58: 0.1 | AE58: 1 | AF58: 0 | AG58: Truncated Normal
A59: 742 | B59: =IF(ISNUMBER(A59), IF(AND(A59=INT(A59), MOD(A59, 10) = 0), 0, IF(AND(A59=INT(A59), LEN(A59)=2), 1, IF(AND(A59=INT(A59), LEN(A59)=3), 2, LEN(A59) - FIND(".", A59) + 2) ) ), "") -> 2 | C59: Spare Parts (Except Manufacturing and Fueling) | D59: =REPT(" ", B59*2) & C59 -> Spare Parts (Except Manufacturing and Fueling) | W59: No Learning | X59: =0.9*$J59 -> 0 | Y59: =1.5*J59 -> 0 | Z59: Lognormal | AA59: =0.9*K59 -> 0 | AB59: =1.3*K59 -> 0 | AC59: Lognormal | AD59: 0.1 | AE59: 1 | AF59: 0 | AG59: Truncated Normal
A60: 743 | B60: =IF(ISNUMBER(A60), IF(AND(A60=INT(A60), MOD(A60, 10) = 0), 0, IF(AND(A60=INT(A60), LEN(A60)=2), 1, IF(AND(A60=INT(A60), LEN(A60)=3), 2, LEN(A60) - FIND(".", A60) + 2) ) ), "") -> 2 | C60: Utilities except electricity, Supplies, and Consumables | D60: =REPT(" ", B60*2) & C60 -> Utilities except electricity, Supplies, and Consumables | W60: No Learning | X60: =0.9*$J60 -> 0 | Y60: =1.5*J60 -> 0 | Z60: Lognormal | AA60: =0.9*K60 -> 0 | AB60: =1.3*K60 -> 0 | AC60: Lognormal | AD60: 0.1 | AE60: 1 | AF60: 0 | AG60: Truncated Normal
A61: 744 | B61: =IF(ISNUMBER(A61), IF(AND(A61=INT(A61), MOD(A61, 10) = 0), 0, IF(AND(A61=INT(A61), LEN(A61)=2), 1, IF(AND(A61=INT(A61), LEN(A61)=3), 2, LEN(A61) - FIND(".", A61) + 2) ) ), "") -> 2 | C61: Electricity | D61: =REPT(" ", B61*2) & C61 -> Electricity | E61: nonstandard | F61: Constant | G61: 1 | K61: 90 | L61: $/MWeHour | M61: MFG Campus Power | P61: 1 | Q61: 2025 | R61: General | W61: No Learning | X61: =0.9*$J61 -> 0 | Y61: =1.5*J61 -> 0 | Z61: Lognormal | AA61: =0.9*K61 -> 81 | AB61: =1.3*K61 -> 117 | AC61: Lognormal | AD61: 0.1 | AE61: 1 | AF61: 0 | AG61: Truncated Normal
A62: 745 | B62: =IF(ISNUMBER(A62), IF(AND(A62=INT(A62), MOD(A62, 10) = 0), 0, IF(AND(A62=INT(A62), LEN(A62)=2), 1, IF(AND(A62=INT(A62), LEN(A62)=3), 2, LEN(A62) - FIND(".", A62) + 2) ) ), "") -> 2 | C62: Manufacturing Building Equipment | D62: =REPT(" ", B62*2) & C62 -> Manufacturing Building Equipment | E62: standard | K62: 405910.19 | L62: unitless | M62: Production Rate | N62: 1 | O62: Rx/yr | P62: 0.126887 | Q62: 2025 | R62: Equipment | W62: No Learning | X62: =0.9*$J62 -> 0 | Y62: =1.5*J62 -> 0 | Z62: Lognormal | AA62: =0.9*K62 -> 365319.17 | AB62: =1.3*K62 -> 527683.25 | AC62: Lognormal | AD62: 0.1 | AE62: 1 | AF62: 0 | AG62: Truncated Normal
A63: 746 | B63: =IF(ISNUMBER(A63), IF(AND(A63=INT(A63), MOD(A63, 10) = 0), 0, IF(AND(A63=INT(A63), LEN(A63)=2), 1, IF(AND(A63=INT(A63), LEN(A63)=3), 2, LEN(A63) - FIND(".", A63) + 2) ) ), "") -> 2 | C63: Fueling Building Equipment | D63: =REPT(" ", B63*2) & C63 -> Fueling Building Equipment | E63: standard | K63: 82100.296 | L63: unitless | M63: Production Rate | N63: 1 | O63: Rx/yr | P63: 0.159548 | Q63: 2025 | R63: Equipment | W63: No Learning | X63: =0.9*$J63 -> 0 | Y63: =1.5*J63 -> 0 | Z63: Lognormal | AA63: =0.9*K63 -> 73890.267 | AB63: =1.3*K63 -> 106730.38 | AC63: Lognormal | AD63: 0.1 | AE63: 1 | AF63: 0 | AG63: Truncated Normal
A64: 747 | B64: =IF(ISNUMBER(A64), IF(AND(A64=INT(A64), MOD(A64, 10) = 0), 0, IF(AND(A64=INT(A64), LEN(A64)=2), 1, IF(AND(A64=INT(A64), LEN(A64)=3), 2, LEN(A64) - FIND(".", A64) + 2) ) ), "") -> 2 | C64: Other annual costs | D64: =REPT(" ", B64*2) & C64 -> Other annual costs | W64: No Learning | X64: =0.9*$J64 -> 0 | Y64: =1.5*J64 -> 0 | Z64: Lognormal | AA64: =0.9*K64 -> 0 | AB64: =1.3*K64 -> 0 | AC64: Lognormal | AD64: 0.1 | AE64: 1 | AF64: 0 | AG64: Truncated Normal
A65: 747.1 | B65: =IF(ISNUMBER(A65), IF(AND(A65=INT(A65), MOD(A65, 10) = 0), 0, IF(AND(A65=INT(A65), LEN(A65)=2), 1, IF(AND(A65=INT(A65), LEN(A65)=3), 2, LEN(A65) - FIND(".", A65) + 2) ) ), "") -> 3 | C65: Annualized Transportation Costs | D65: =REPT(" ", B65*2) & C65 -> Annualized Transportation Costs | X65: =0.8*$I65 -> 0 | Y65: =2*J65 -> 0 | Z65: Lognormal | AA65: =0.8*K65 -> 0 | AB65: =2*K65 -> 0 | AC65: Lognormal | AD65: 0.1 | AE65: 1 | AF65: 0 | AG65: Truncated Normal
A66: 747.3 | B66: =IF(ISNUMBER(A66), IF(AND(A66=INT(A66), MOD(A66, 10) = 0), 0, IF(AND(A66=INT(A66), LEN(A66)=2), 1, IF(AND(A66=INT(A66), LEN(A66)=3), 2, LEN(A66) - FIND(".", A66) + 2) ) ), "") -> 3 | C66: Annualized Helium Replenishment | D66: =REPT(" ", B66*2) & C66 -> Annualized Helium Replenishment | E66: standard | F66: Production Rate | G66: 1 | K66: 170 | L66: $/Kg | M66: MFG Testing Coolant Allotment | O66: Kg | Q66: 2024 | R66: Equipment | S66: Fernandez de Losada. (2024). Assessment of the Lifecycle Cost of Nuclear-Grade Coolants for Advanced Reactors. ETHzurich. Swiss. | T66: Fernandez de Losada. (2024). Assessment of the Lifecycle Cost of Nuclear-Grade Coolants for Advanced Reactors. ETHzurich. Swiss. | U66: https://doi.org/10.3929/ethz-b-000709311 | V66: Vendor Quoate (Linde) for 3000 cylinders of 99.999% purity Helium. 3000 cylinders correspond to ~4 MT of He. | W66: No Learning | X66: 0 | Y66: 0 | Z66: Lognormal | AA66: =0.9*K66 -> 153 | AB66: =1.3*K66 -> 221 | AC66: Lognormal | AD66: 0.1 | AE66: 1 | AF66: 0 | AG66: Truncated Normal
A67: 747.4 | B67: =IF(ISNUMBER(A67), IF(AND(A67=INT(A67), MOD(A67, 10) = 0), 0, IF(AND(A67=INT(A67), LEN(A67)=2), 1, IF(AND(A67=INT(A67), LEN(A67)=3), 2, LEN(A67) - FIND(".", A67) + 2) ) ), "") -> 3 | C67: Annualized Other Supplies and Utilities | D67: =REPT(" ", B67*2) & C67 -> Annualized Other Supplies and Utilities | W67: No Learning | Z67: Lognormal | AA67: =0.9*K67 -> 0 | AB67: =1.3*K67 -> 0 | AC67: Lognormal | AD67: 0.1 | AE67: 1 | AF67: 0 | AG67: Truncated Normal
A68: 75 | B68: =IF(ISNUMBER(A68), IF(AND(A68=INT(A68), MOD(A68, 10) = 0), 0, IF(AND(A68=INT(A68), LEN(A68)=2), 1, IF(AND(A68=INT(A68), LEN(A68)=3), 2, LEN(A68) - FIND(".", A68) + 2) ) ), "") -> 1 | C68: Capital Plant Expenditures | D68: =REPT(" ", B68*2) & C68 -> Capital Plant Expenditures
A69: 78 | B69: =IF(ISNUMBER(A69), IF(AND(A69=INT(A69), MOD(A69, 10) = 0), 0, IF(AND(A69=INT(A69), LEN(A69)=2), 1, IF(AND(A69=INT(A69), LEN(A69)=3), 2, LEN(A69) - FIND(".", A69) + 2) ) ), "") -> 1 | C69: Annualized Decommissioning Cost | D69: =REPT(" ", B69*2) & C69 -> Annualized Decommissioning Cost

Sheet Servicing Campus Database
A1: Account | B1: Level | C1: Account Name | D1: Account Title | E1: Standard Cost Equation? | F1: Count Scaling Variable | G1: Count per Variable | H1: Optional Variable | I1: Optional Value | J1: Fixed Cost ($) | K1: Unit Cost | L1: Unit Cost (units) | M1: Scaling Variable | N1: Scaling Variable Ref Value | O1: Units | P1: Exponent | Q1: Dollar Year | R1: Type | S1: Source | T1: Ref | U1: Link | V1: Notes | W1: FOAK to NOAK Multiplier Type | X1: Fixed Cost Low End | Y1: Fixed Cost High End | Z1: Fixed Cost Distribution | AA1: Unit Cost Low End | AB1: Unit Cost High End | AC1: Unit Cost Distribution | AD1: Exponent std | AE1: Exponent Max | AF1: Exponent Min | AG1: Exponent Distribution
A2: 10 | B2: =IF(ISNUMBER(A2), IF(AND(A2=INT(A2), MOD(A2, 10) = 0), 0, IF(AND(A2=INT(A2), LEN(A2)=2), 1, IF(AND(A2=INT(A2), LEN(A2)=3), 2, LEN(A2) - FIND(".", A2) + 2) ) ), "") -> 0 | C2: Capitalized Pre-Construction Costs | D2: =REPT(" ", B2*2) & C2 -> Capitalized Pre-Construction Costs
A3: 11 | B3: =IF(ISNUMBER(A3), IF(AND(A3=INT(A3), MOD(A3, 10) = 0), 0, IF(AND(A3=INT(A3), LEN(A3)=2), 1, IF(AND(A3=INT(A3), LEN(A3)=3), 2, LEN(A3) - FIND(".", A3) + 2) ) ), "") -> 1 | C3: Land Cost | D3: =REPT(" ", B3*2) & C3 -> Land Cost | E3: standard | F3: Constant | G3: 1 | K3: 3800 | L3: $/acres | M3: SER Campus Area | O3: acres | Q3: 2022 | R3: General | S3: The average cost per acre for rural land in 2022 from the US Department of Agriculture | T3: Abou-Jaoude, A., Lohse, C. S., Larsen, L. M., Guaita, N., Trivedi, I., Joseck, F. C., ... & Stein, A. (2024). Meta-analysis of advanced nuclear reactor cost estimations (No. INL/RPT-24-77048-Rev001). Idaho National Laboratory (INL), Idaho Falls, ID (United States). | U3: https://inldigitallibrary.inl.gov/sites/sti/sti/Sort_107010.pdf | W3: No Learning | X3: =0.9*$J3 -> 0 | Y3: =1.5*J3 -> 0 | Z3: Lognormal | AA3: =0.9*K3 -> 3420 | AB3: =1.3*K3 -> 4940 | AC3: Lognormal | AD3: 0.1 | AE3: 1 | AF3: 0 | AG3: Truncated Normal
A4: 12 | B4: =IF(ISNUMBER(A4), IF(AND(A4=INT(A4), MOD(A4, 10) = 0), 0, IF(AND(A4=INT(A4), LEN(A4)=2), 1, IF(AND(A4=INT(A4), LEN(A4)=3), 2, LEN(A4) - FIND(".", A4) + 2) ) ), "") -> 1 | C4: Site Permits | D4: =REPT(" ", B4*2) & C4 -> Site Permits | E4: standard | F4: Constant | G4: 1 | K4: =10.03*1000 -> 10030 | L4: $/MWe | M4: SER Switchyard Rating | O4: MWe | Q4: 2022 | R4: Labor | S4: Data from SMR MHTGRs | W4: No Learning | X4: =0.9*$J4 -> 0 | Y4: =1.5*J4 -> 0 | Z4: Lognormal | AA4: =0.9*K4 -> 9027 | AB4: =1.3*K4 -> 13039 | AC4: Lognormal | AD4: 0.1 | AE4: 1 | AF4: 0 | AG4: Truncated Normal
A5: 13 | B5: =IF(ISNUMBER(A5), IF(AND(A5=INT(A5), MOD(A5, 10) = 0), 0, IF(AND(A5=INT(A5), LEN(A5)=2), 1, IF(AND(A5=INT(A5), LEN(A5)=3), 2, LEN(A5) - FIND(".", A5) + 2) ) ), "") -> 1 | C5: Plant Licensing | D5: =REPT(" ", B5*2) & C5 -> Plant Licensing | E5: standard | F5: Constant | G5: 1 | J5: =1000000*(45+70)/2 -> 57500000 | Q5: 2009 | R5: Labor | S5: NGNP project | T5: Gandrik, A., B. Wallace, L. Demick, S. Melancon and M. Patterson (2011). "Assessment of high temperature gas-cooled reactor (HTGR) capital and operating costs." Idaho National Laboratory, TEV-1196, Idaho Falls, ID. | U5: https://art.inl.gov/NGNP/INL%20Documents/Year%202012/Assessment%20of%20High%20Temperature%20Gas-Cooled%20Reactor%20-%20HTGR%20-%20Capital%20and%20Operating%20Costs.pdf | W5: No Learning | X5: =45*1000000 -> 45000000 | Y5: =70*1000000 -> 70000000 | Z5: Uniform | AA5: =0.9*K5 -> 0 | AB5: =1.3*K5 -> 0 | AC5: Lognormal | AD5: 0.1 | AE5: 1 | AF5: 0 | AG5: Truncated Normal
A6: 14 | B6: =IF(ISNUMBER(A6), IF(AND(A6=INT(A6), MOD(A6, 10) = 0), 0, IF(AND(A6=INT(A6), LEN(A6)=2), 1, IF(AND(A6=INT(A6), LEN(A6)=3), 2, LEN(A6) - FIND(".", A6) + 2) ) ), "") -> 1 | C6: Plant Permits | D6: =REPT(" ", B6*2) & C6 -> Plant Permits | E6: standard | F6: Constant | G6: 1 | J6: 3000000 | Q6: 2009 | R6: Labor | S6: NGNP project | W6: No Learning | X6: =0.9*$J6 -> 2700000 | Y6: =1.5*J6 -> 4500000 | Z6: Lognormal | AA6: =0.9*K6 -> 0 | AB6: =1.3*K6 -> 0 | AC6: Lognormal | AD6: 0.1 | AE6: 1 | AF6: 0 | AG6: Truncated Normal
A7: 15 | B7: =IF(ISNUMBER(A7), IF(AND(A7=INT(A7), MOD(A7, 10) = 0), 0, IF(AND(A7=INT(A7), LEN(A7)=2), 1, IF(AND(A7=INT(A7), LEN(A7)=3), 2, LEN(A7) - FIND(".", A7) + 2) ) ), "") -> 1 | C7: Plant Studies | D7: =REPT(" ", B7*2) & C7 -> Plant Studies | E7: standard | F7: Constant | G7: 1 | J7: =10*MARVEL_Cost!C4 -> 52104510 | Q7: 2024 | R7: Labor | S7: MARVEL Project (Labor-adjusted Cost) | T7: Hanna, B. N., Gonzaga de Oliveira, R. G., Mohammad Al Dawood, K. A., Patterson, M. D., Abou Jaoude, A., & Garcia, S. (2024). Technoeconomic Evaluation of Microreactor Using Detailed Bottom-up Estimate (No. INL/RPT-24-80433-Rev000). Idaho National Laboratory (INL), Idaho Falls, ID (United States). | U7: https://inldigitallibrary.inl.gov/sites/sti/sti/Sort_129862.pdf | V7: MARVEL's data were updated | W7: No Learning | X7: =0.9*$J7 -> 46894059 | Y7: =1.5*J7 -> 78156765 | Z7: Lognormal | AA7: =0.9*K7 -> 0 | AB7: =1.3*K7 -> 0 | AC7: Lognormal | AD7: 0.1 | AE7: 1 | AF7: 0 | AG7: Truncated Normal
A8: 20 | B8: =IF(ISNUMBER(A8), IF(AND(A8=INT(A8), MOD(A8, 10) = 0), 0, IF(AND(A8=INT(A8), LEN(A8)=2), 1, IF(AND(A8=INT(A8), LEN(A8)=3), 2, LEN(A8) - FIND(".", A8) + 2) ) ), "") -> 0 | C8: Capitalized Direct Costs | D8: =REPT(" ", B8*2) & C8 -> Capitalized Direct Costs | W8: 598
A9: 21 | B9: =IF(ISNUMBER(A9), IF(AND(A9=INT(A9), MOD(A9, 10) = 0), 0, IF(AND(A9=INT(A9), LEN(A9)=2), 1, IF(AND(A9=INT(A9), LEN(A9)=3), 2, LEN(A9) - FIND(".", A9) + 2) ) ), "") -> 1 | C9: Structures and Improvements | D9: =REPT(" ", B9*2) & C9 -> Structures and Improvements
A10: 211 | B10: =IF(ISNUMBER(A10), IF(AND(A10=INT(A10), MOD(A10, 10) = 0), 0, IF(AND(A10=INT(A10), LEN(A10)=2), 1, IF(AND(A10=INT(A10), LEN(A10)=3), 2, LEN(A10) - FIND(".", A10) + 2) ) ), "") -> 2 | C10: Site Preparation/ Yard Work | D10: =REPT(" ", B10*2) & C10 -> Site Preparation/ Yard Work
A11: 211.1 | B11: =IF(ISNUMBER(A11), IF(AND(A11=INT(A11), MOD(A11, 10) = 0), 0, IF(AND(A11=INT(A11), LEN(A11)=2), 1, IF(AND(A11=INT(A11), LEN(A11)=3), 2, LEN(A11) - FIND(".", A11) + 2) ) ), "") -> 3 | C11: Cleaning and Grubbing | D11: =REPT(" ", B11*2) & C11 -> Cleaning and Grubbing | E11: standard | F11: Constant | G11: 1 | K11: =4408.18*1.33 -> 5862.8794 | L11: $/acres | M11: SER Campus Land Area | O11: acres | Q11: 2024 | R11: Lab and Equip | S11: RSMeans software: a tool that primarily provides costs for non-nuclear work Nuclear Multiplier have been applied to adjust the costs for nuclear-site-related work | T11: GORDIAN. (2024). "RSMeans data. & Delene, J. G. and I. Hudson, C. R. (1993). Cost estimate guidelines for advanced nuclear power technologies. United States, Oak Ridge National Lab. (ORNL), Oak Ridge, TN (United States): Medium: ED; Size: 159 p. | U11: https://www.rsmeans.com/ & https://www.osti.gov/biblio/10176857 | W11: No Learning | X11: =0.9*$J11 -> 0 | Y11: =1.5*J11 -> 0 | Z11: Lognormal | AA11: =0.9*K11 -> 5276.5915 | AB11: =1.3*K11 -> 7621.7432 | AC11: Lognormal | AD11: 0.1 | AE11: 1 | AF11: 0 | AG11: Truncated Normal
A12: 211.2 | B12: =IF(ISNUMBER(A12), IF(AND(A12=INT(A12), MOD(A12, 10) = 0), 0, IF(AND(A12=INT(A12), LEN(A12)=2), 1, IF(AND(A12=INT(A12), LEN(A12)=3), 2, LEN(A12) - FIND(".", A12) + 2) ) ), "") -> 3 | C12: Stripping Topsoil | D12: =REPT(" ", B12*2) & C12 -> Stripping Topsoil | E12: standard | F12: Constant | G12: 1 | K12: =2565.2*1.33 -> 3411.716 | L12: $/acres | M12: SER Campus Land Area | O12: acres | Q12: 2024 | R12: Lab and Equip | W12: No Learning | X12: =0.9*$J12 -> 0 | Y12: =1.5*J12 -> 0 | Z12: Lognormal | AA12: =0.9*K12 -> 3070.5444 | AB12: =1.3*K12 -> 4435.2308 | AC12: Lognormal | AD12: 0.1 | AE12: 1 | AF12: 0 | AG12: Truncated Normal
A13: 211.4 | B13: =IF(ISNUMBER(A13), IF(AND(A13=INT(A13), MOD(A13, 10) = 0), 0, IF(AND(A13=INT(A13), LEN(A13)=2), 1, IF(AND(A13=INT(A13), LEN(A13)=3), 2, LEN(A13) - FIND(".", A13) + 2) ) ), "") -> 3 | C13: Roads | D13: =REPT(" ", B13*2) & C13 -> Roads | E13: standard | F13: Constant | G13: 1 | K13: =0.7*7873200*1.609/1000 -> 8867.5852 | L13: $/m | M13: SER Road Length | N13: 1 | P13: 1 | Q13: 2025 | R13: General | S13: MC30 Cost Estimation of Microreactor Facilities Inital Draft 5-6-2026.pdf, less 30% | W13: No Learning | X13: =0.9*$J13 -> 0 | Y13: =1.5*J13 -> 0 | Z13: Lognormal | AA13: =0.9*K13 -> 7980.8266 | AB13: =1.3*K13 -> 11527.861 | AC13: Lognormal | AD13: 0.1 | AE13: 1 | AF13: 0 | AG13: Truncated Normal
A14: 211.9 | B14: =IF(ISNUMBER(A14), IF(AND(A14=INT(A14), MOD(A14, 10) = 0), 0, IF(AND(A14=INT(A14), LEN(A14)=2), 1, IF(AND(A14=INT(A14), LEN(A14)=3), 2, LEN(A14) - FIND(".", A14) + 2) ) ), "") -> 3 | C14: Security Fencing | D14: =REPT(" ", B14*2) & C14 -> Security Fencing
A15: 211.91 | B15: =IF(ISNUMBER(A15), IF(AND(A15=INT(A15), MOD(A15, 10) = 0), 0, IF(AND(A15=INT(A15), LEN(A15)=2), 1, IF(AND(A15=INT(A15), LEN(A15)=3), 2, LEN(A15) - FIND(".", A15) + 2) ) ), "") -> 4 | C15: Security Fencing Limited | D15: =REPT(" ", B15*2) & C15 -> Security Fencing Limited | E15: standard | F15: Constant | G15: 1 | K15: =0.7*273 -> 191.1 | L15: $/ft | M15: SER Site Perimeter | Q15: 2025 | R15: Lab and Equip | S15: MC30 Cost Estimation of Microreactor Facilities Inital Draft 5-6-2026.pdf, less 30% | W15: No Learning | X15: =0.9*$J15 -> 0 | Y15: =1.5*J15 -> 0 | Z15: Lognormal | AA15: =0.9*K15 -> 171.99 | AB15: =1.3*K15 -> 248.43 | AC15: Lognormal | AD15: 0.1 | AE15: 1 | AF15: 0 | AG15: Truncated Normal
A16: 211.92 | B16: =IF(ISNUMBER(A16), IF(AND(A16=INT(A16), MOD(A16, 10) = 0), 0, IF(AND(A16=INT(A16), LEN(A16)=2), 1, IF(AND(A16=INT(A16), LEN(A16)=3), 2, LEN(A16) - FIND(".", A16) + 2) ) ), "") -> 4 | C16: Security Fencing Controlled | D16: =REPT(" ", B16*2) & C16 -> Security Fencing Controlled | E16: standard | F16: Constant | G16: 1 | K16: =0.7*328 -> 229.6 | L16: $/ft | M16: SER Controlled Perimeter | Q16: 2025 | R16: Lab and Equip | S16: MC30 Cost Estimation of Microreactor Facilities Inital Draft 5-6-2026.pdf, less 30% | W16: No Learning | X16: =0.9*$J16 -> 0 | Y16: =1.5*J16 -> 0 | Z16: Lognormal | AA16: =0.9*K16 -> 206.64 | AB16: =1.3*K16 -> 298.48 | AC16: Lognormal | AD16: 0.1 | AE16: 1 | AF16: 0 | AG16: Truncated Normal
A17: 211.93 | B17: =IF(ISNUMBER(A17), IF(AND(A17=INT(A17), MOD(A17, 10) = 0), 0, IF(AND(A17=INT(A17), LEN(A17)=2), 1, IF(AND(A17=INT(A17), LEN(A17)=3), 2, LEN(A17) - FIND(".", A17) + 2) ) ), "") -> 4 | C17: Security Fencing Protected | D17: =REPT(" ", B17*2) & C17 -> Security Fencing Protected | E17: standard | F17: Constant | G17: 1 | K17: =0.7*15746 -> 11022.2 | L17: $/ft | M17: SER Protected Perimeter | Q17: 2025 | R17: Lab and Equip | S17: MC30 Cost Estimation of Microreactor Facilities Inital Draft 5-6-2026.pdf, less 30% | W17: No Learning | X17: =0.9*$J17 -> 0 | Y17: =1.5*J17 -> 0 | Z17: Lognormal | AA17: =0.9*K17 -> 9919.98 | AB17: =1.3*K17 -> 14328.86 | AC17: Lognormal | AD17: 0.1 | AE17: 1 | AF17: 0 | AG17: Truncated Normal
A18: 214 | B18: =IF(ISNUMBER(A18), IF(AND(A18=INT(A18), MOD(A18, 10) = 0), 0, IF(AND(A18=INT(A18), LEN(A18)=2), 1, IF(AND(A18=INT(A18), LEN(A18)=3), 2, LEN(A18) - FIND(".", A18) + 2) ) ), "") -> 2 | C18: Servicing Facilities Structures | D18: =REPT(" ", B18*2) & C18 -> Servicing Facilities Structures
A19: 214.1 | B19: =IF(ISNUMBER(A19), IF(AND(A19=INT(A19), MOD(A19, 10) = 0), 0, IF(AND(A19=INT(A19), LEN(A19)=2), 1, IF(AND(A19=INT(A19), LEN(A19)=3), 2, LEN(A19) - FIND(".", A19) + 2) ) ), "") -> 3 | C19: Servicing Building | D19: =REPT(" ", B19*2) & C19 -> Servicing Building
A20: 214.11 | B20: =IF(ISNUMBER(A20), IF(AND(A20=INT(A20), MOD(A20, 10) = 0), 0, IF(AND(A20=INT(A20), LEN(A20)=2), 1, IF(AND(A20=INT(A20), LEN(A20)=3), 2, LEN(A20) - FIND(".", A20) + 2) ) ), "") -> 4 | C20: Servicing Hot Cell Building Structure | D20: =REPT(" ", B20*2) & C20 -> Servicing Hot Cell Building Structure | E20: standard | F20: Constant | G20: 1 | K20: =0.7*3328.51*3.2808^2 -> 25078.838 | L20: $/m^2 | M20: Servicing Hot Cell Building Area | N20: =338988/(3.2808^2) -> 31493.782 | O20: m^2 | P20: 0.951385 | Q20: 2025 | R20: Lab and Mat and Equip | S20: MC30 Cost Estimation of Microreactor Facilities Rev 1 Draft Backup Info 8-5-2026.xlsx, less 30% [temporary, want to add scaling equation] | W20: No Learning | X20: =0.8*$I20 -> 0 | Y20: =2*J20 -> 0 | Z20: Lognormal | AA20: =0.8*K20 -> 20063.071 | AB20: =2*K20 -> 50157.677 | AC20: Lognormal | AD20: 0.1 | AE20: 1 | AF20: 0 | AG20: Truncated Normal
A21: 214.2 | B21: =IF(ISNUMBER(A21), IF(AND(A21=INT(A21), MOD(A21, 10) = 0), 0, IF(AND(A21=INT(A21), LEN(A21)=2), 1, IF(AND(A21=INT(A21), LEN(A21)=3), 2, LEN(A21) - FIND(".", A21) + 2) ) ), "") -> 3 | C21: Helium Purification and Storage Building
A22: 214.21 | B22: =IF(ISNUMBER(A22), IF(AND(A22=INT(A22), MOD(A22, 10) = 0), 0, IF(AND(A22=INT(A22), LEN(A22)=2), 1, IF(AND(A22=INT(A22), LEN(A22)=3), 2, LEN(A22) - FIND(".", A22) + 2) ) ), "") -> 4 | C22: Helium Purification and Storage Building Structure | D22: =REPT(" ", B22*2) & C22 -> Helium Purification and Storage Building Structure | E22: standard | F22: Constant | G22: 1 | K22: =0.7*2919.24*(3.2808^2) -> 21995.172 | L22: $/m^2 | M22: Helium Purification and Storage Building Area | N22: 1 | O22: m^2 | P22: 1 | Q22: 2025 | R22: Lab and Mat and Equip | S22: MC30 Cost Estimation of Microreactor Facilities Rev 1 Draft Backup Info 8-5-2026.xlsx, less 30% [temporary, want to add scaling equation] | W22: No Learning | X22: =0.9*$I22 -> 0 | Y22: =1.5*J22 -> 0 | Z22: Lognormal | AA22: =0.9*K22 -> 19795.654 | AB22: =1.3*K22 -> 28593.723 | AC22: Lognormal | AD22: 0.1 | AE22: 1 | AF22: 0 | AG22: Truncated Normal
A23: 214.3 | B23: =IF(ISNUMBER(A23), IF(AND(A23=INT(A23), MOD(A23, 10) = 0), 0, IF(AND(A23=INT(A23), LEN(A23)=2), 1, IF(AND(A23=INT(A23), LEN(A23)=3), 2, LEN(A23) - FIND(".", A23) + 2) ) ), "") -> 3 | C23: Control Buidlings | D23: =REPT(" ", B23*2) & C23 -> Control Buidlings
A24: 214.31 | B24: 4 | C24: Local Control Building Structure | D24: =REPT(" ", B24*2) & C24 -> Local Control Building Structure | E24: standard | F24: Constant | G24: 1 | K24: =0.7*2653*(3.2808^2) -> 19989.172 | L24: $/m^2 | M24: SER Local Control Building Area | N24: 1 | O24: m^2 | P24: 1 | Q24: 2025 | R24: Lab and Mat and Equip | S24: 100 value from MC30 Cost Estimation of Microreactor Facilities Inital Draft 5-6-2026.pdf, less 30% [temporary, want to add scaling equation] | W24: No Learning | X24: =0.9*$I24 -> 0 | Y24: =1.5*J24 -> 0 | Z24: Lognormal | AA24: =0.9*K24 -> 17990.255 | AB24: =1.3*K24 -> 25985.923 | AC24: Lognormal | AD24: 0.1 | AE24: 1 | AF24: 0 | AG24: Truncated Normal
A25: 214.32 | B25: 4 | C25: Remote Control Center Structure | D25: =REPT(" ", B25*2) & C25 -> Remote Control Center Structure | E25: standard | F25: Constant | G25: 1 | K25: =0.7*2307*(3.2808^2) -> 17382.216 | L25: $/m^2 | M25: SER Remote Control Building Area | N25: 1 | O25: m^2 | P25: 1 | Q25: 2025 | R25: Lab and Mat and Equip | S25: 100 value from MC30 Cost Estimation of Microreactor Facilities Inital Draft 5-6-2026.pdf, less 30% [temporary, want to add scaling equation] | W25: No Learning | X25: =0.9*$I25 -> 0 | Y25: =1.5*J25 -> 0 | Z25: Lognormal | AA25: =0.9*K25 -> 15643.995 | AB25: =1.3*K25 -> 22596.881 | AC25: Lognormal | AD25: 0.1 | AE25: 1 | AF25: 0 | AG25: Truncated Normal
A26: 214.4 | B26: =IF(ISNUMBER(A26), IF(AND(A26=INT(A26), MOD(A26, 10) = 0), 0, IF(AND(A26=INT(A26), LEN(A26)=2), 1, IF(AND(A26=INT(A26), LEN(A26)=3), 2, LEN(A26) - FIND(".", A26) + 2) ) ), "") -> 3 | C26: Radioactive Waste Processing Building | D26: =REPT(" ", B26*2) & C26 -> Radioactive Waste Processing Building
A27: 214.41 | B27: =IF(ISNUMBER(A27), IF(AND(A27=INT(A27), MOD(A27, 10) = 0), 0, IF(AND(A27=INT(A27), LEN(A27)=2), 1, IF(AND(A27=INT(A27), LEN(A27)=3), 2, LEN(A27) - FIND(".", A27) + 2) ) ), "") -> 4 | C27: Radioactive Waste Processing Building Structure | D27: =REPT(" ", B27*2) & C27 -> Radioactive Waste Processing Building Structure | E27: standard | F27: Constant | G27: 1 | K27: =4354*(3.2808^2) -> 46864.926 | L27: $/m^2 | M27: SER Rad Waste Management Building Area | N27: 1 | O27: m^2 | P27: 1 | Q27: 2025 | R27: Lab and Mat and Equip | S27: 100 value from MC30 Cost Estimation of Microreactor Facilities Inital Draft 5-6-2026.pdf [temporary, want to add scaling equation] | W27: No Learning | X27: =0.9*$I27 -> 0 | Y27: =1.5*J27 -> 0 | Z27: Lognormal | AA27: =0.9*K27 -> 42178.434 | AB27: =1.3*K27 -> 60924.404 | AC27: Lognormal | AD27: 0.1 | AE27: 1 | AF27: 0 | AG27: Truncated Normal
A28: 214.6 | B28: =IF(ISNUMBER(A28), IF(AND(A28=INT(A28), MOD(A28, 10) = 0), 0, IF(AND(A28=INT(A28), LEN(A28)=2), 1, IF(AND(A28=INT(A28), LEN(A28)=3), 2, LEN(A28) - FIND(".", A28) + 2) ) ), "") -> 3 | C28: Used Fuel Storage Pads | D28: =REPT(" ", B28*2) & C28 -> Used Fuel Storage Pads | E28: standard | K28: 6171250 | L28: $/(reactors/year) | M28: Servicing Rate | N28: 1 | O28: reactors/year | P28: 1 | Q28: 2009 | R28: Lab and Mat and Equip | S28: Value for 40,000 MTU option in Cost Estimate for an Away-From-Reactor Generic Interim Storage Facility (GISF) for Spent Nuclear Fuel, EPRI report 1018722 | U28: https://www.epri.com/research/products/1018722 | W28: No Learning | X28: =0.9*$I28 -> 0 | Y28: =1.5*J28 -> 0 | Z28: Lognormal | AA28: =0.9*K28 -> 5554125 | AB28: =1.3*K28 -> 8022625 | AC28: Lognormal | AD28: 0.1 | AE28: 1 | AF28: 0 | AG28: Truncated Normal
A29: 214.7 | B29: =IF(ISNUMBER(A29), IF(AND(A29=INT(A29), MOD(A29, 10) = 0), 0, IF(AND(A29=INT(A29), LEN(A29)=2), 1, IF(AND(A29=INT(A29), LEN(A29)=3), 2, LEN(A29) - FIND(".", A29) + 2) ) ), "") -> 3 | C29: Rad Waste Storage Warehouses | D29: =REPT(" ", B29*2) & C29 -> Rad Waste Storage Warehouses | E29: standard | K29: =0.7*1121.28*(3.2808^2) -> 8448.3448 | L29: $/m^2 | M29: Radwaste Storage Warehouses Area | N29: 1 | O29: m^2 | P29: 1 | Q29: 2025 | R29: Lab and Mat and Equip | S29: MC30 Cost Estimation of Microreactor Facilities Rev 1 Draft Backup Info 8-5-2026.xlsx, less 30% [temporary, want to add scaling equation] | W29: No Learning | X29: =0.9*$I29 -> 0 | Y29: =1.5*J29 -> 0 | Z29: Lognormal | AA29: =0.9*K29 -> 7603.5103 | AB29: =1.3*K29 -> 10982.848 | AC29: Lognormal | AD29: 0.1 | AE29: 1 | AF29: 0 | AG29: Truncated Normal
A30: 215 | B30: =IF(ISNUMBER(A30), IF(AND(A30=INT(A30), MOD(A30, 10) = 0), 0, IF(AND(A30=INT(A30), LEN(A30)=2), 1, IF(AND(A30=INT(A30), LEN(A30)=3), 2, LEN(A30) - FIND(".", A30) + 2) ) ), "") -> 2 | C30: Air Tranport Hangar | D30: =REPT(" ", B30*2) & C30 -> Air Tranport Hangar
A31: 215.1 | B31: =IF(ISNUMBER(A31), IF(AND(A31=INT(A31), MOD(A31, 10) = 0), 0, IF(AND(A31=INT(A31), LEN(A31)=2), 1, IF(AND(A31=INT(A31), LEN(A31)=3), 2, LEN(A31) - FIND(".", A31) + 2) ) ), "") -> 3 | C31: Air Transport Hangar | D31: =REPT(" ", B31*2) & C31 -> Air Transport Hangar | E31: standard | J31: 10000000 | Q31: 2024 | R31: Equipment | S31: none | W31: No Learning | X31: =0.9*$I31 -> 0 | Y31: =1.5*J31 -> 15000000 | Z31: Lognormal | AA31: =0.9*K31 -> 0 | AB31: =1.3*K31 -> 0 | AC31: Lognormal | AD31: 0.1 | AE31: 1 | AF31: 0 | AG31: Truncated Normal
A32: 22 | B32: =IF(ISNUMBER(A32), IF(AND(A32=INT(A32), MOD(A32, 10) = 0), 0, IF(AND(A32=INT(A32), LEN(A32)=2), 1, IF(AND(A32=INT(A32), LEN(A32)=3), 2, LEN(A32) - FIND(".", A32) + 2) ) ), "") -> 1 | C32: Main Facilities Estimated As Wholes | D32: =REPT(" ", B32*2) & C32 -> Main Facilities Estimated As Wholes
A33: 221 | B33: 2 | C33: Reactor Cask Management Yard and Inspection Shop | D33: =REPT(" ", B33*2) & C33 -> Reactor Cask Management Yard and Inspection Shop | E33: standard | K33: =0.7*17946522/N33 -> 41875.218 | M33: Servicing Rate | N33: 300 | O33: Rx/yr | P33: 0.25048 | Q33: 2025 | R33: Lab and Mat and Equip | S33: Scaling relationship created from MC30 Cost Estimation of Microreactor Facilities Inital Draft 5-6-2026.pdf, less 30% | W33: No Learning | X33: =0.9*$I33 -> 0 | Y33: =1.5*J33 -> 0 | Z33: Lognormal | AA33: =0.9*K33 -> 37687.696 | AB33: =1.3*K33 -> 54437.783 | AC33: Lognormal | AD33: 0.1 | AE33: 1 | AF33: 0 | AG33: Truncated Normal
A34: 222 | B34: =IF(ISNUMBER(A34), IF(AND(A34=INT(A34), MOD(A34, 10) = 0), 0, IF(AND(A34=INT(A34), LEN(A34)=2), 1, IF(AND(A34=INT(A34), LEN(A34)=3), 2, LEN(A34) - FIND(".", A34) + 2) ) ), "") -> 2 | C34: Vehicle Depot and Mechanic Shop | D34: =REPT(" ", B34*2) & C34 -> Vehicle Depot and Mechanic Shop | E34: standard | K34: =0.7*58097655/N34 -> 135561.2 | M34: Servicing Rate | N34: 300 | O34: m^2 | P34: 0.266665 | Q34: 2025 | R34: Lab and Mat and Equip | S34: Scaling relationship created from MC30 Cost Estimation of Microreactor Facilities Inital Draft 5-6-2026.pdf, less 30% | W34: No Learning | X34: =0.9*$I34 -> 0 | Y34: =1.5*J34 -> 0 | Z34: Lognormal | AA34: =0.9*K34 -> 122005.08 | AB34: =1.3*K34 -> 176229.55 | AC34: Lognormal | AD34: 0.1 | AE34: 1 | AF34: 0 | AG34: Truncated Normal
A35: 224 | B35: =IF(ISNUMBER(A35), IF(AND(A35=INT(A35), MOD(A35, 10) = 0), 0, IF(AND(A35=INT(A35), LEN(A35)=2), 1, IF(AND(A35=INT(A35), LEN(A35)=3), 2, LEN(A35) - FIND(".", A35) + 2) ) ), "") -> 2 | C35: Parts Service Center and Warehouse | D35: =REPT(" ", B35*2) & C35 -> Parts Service Center and Warehouse | E35: standard | K35: 50000 | L35: $/m^2 | M35: Parts Service Center and Warehouse Building Area | N35: 1 | O35: m^2 | P35: 1 | Q35: 2025 | R35: Lab and Mat and Equip | S35: Judgement | W35: No Learning | X35: =0.9*$I35 -> 0 | Y35: =1.5*J35 -> 0 | Z35: Lognormal | AA35: =0.9*K35 -> 45000 | AB35: =1.3*K35 -> 65000 | AC35: Lognormal | AD35: 0.1 | AE35: 1 | AF35: 0 | AG35: Truncated Normal
A36: 225 | B36: =IF(ISNUMBER(A36), IF(AND(A36=INT(A36), MOD(A36, 10) = 0), 0, IF(AND(A36=INT(A36), LEN(A36)=2), 1, IF(AND(A36=INT(A36), LEN(A36)=3), 2, LEN(A36) - FIND(".", A36) + 2) ) ), "") -> 2 | C36: Administrative Building | D36: =REPT(" ", B36*2) & C36 -> Administrative Building | E36: standard | K36: =0.7*1890.9*(3.2808^2) -> 14247.088 | L36: $/m^2 | M36: SER Administration Building Area | N36: 1 | O36: m^2 | P36: 1 | Q36: 2025 | R36: Lab and Mat and Equip | S36: 100 value from MC30 Cost Estimation of Microreactor Facilities Inital Draft 5-6-2026.pdf, less 30% [temporary, want to add scaling equation] | W36: No Learning | X36: =0.9*$I36 -> 0 | Y36: =1.5*J36 -> 0 | Z36: Lognormal | AA36: =0.9*K36 -> 12822.379 | AB36: =1.3*K36 -> 18521.215 | AC36: Lognormal | AD36: 0.1 | AE36: 1 | AF36: 0 | AG36: Truncated Normal
A37: 23 | B37: =IF(ISNUMBER(A37), IF(AND(A37=INT(A37), MOD(A37, 10) = 0), 0, IF(AND(A37=INT(A37), LEN(A37)=2), 1, IF(AND(A37=INT(A37), LEN(A37)=3), 2, LEN(A37) - FIND(".", A37) + 2) ) ), "") -> 1 | C37: Equipment | D37: =REPT(" ", B37*2) & C37 -> Equipment
A38: 23.1 | B38: 2 | C38: Servicing Hot Cell | D38: =REPT(" ", B38*2) & C38 -> Servicing Hot Cell | E38: standard | F38: Servicing Hot Cell Count | G38: 1 | J38: 1000000000 | Q38: 2024 | R38: Lab and Mat and Equip | S38: assumption | W38: No Learning | X38: =0.8*$I38 -> 0 | Y38: =2*J38 -> 2000000000 | Z38: Lognormal | AA38: =0.8*K38 -> 0 | AB38: =2*K38 -> 0 | AC38: Lognormal | AD38: 0.1 | AE38: 1 | AF38: 0 | AG38: Truncated Normal
A39: 23.2 | B39: 2 | C39: Helium Purification Equipment | D39: =REPT(" ", B39*2) & C39 -> Helium Purification Equipment | E39: standard | F39: Constant | G39: 1 | K39: =10*((4700000+6000000)/2)/N39 -> 963000000 | M39: SER Helium Flowrate | N39: =200/3600 -> 0.055555556 | O39: kg/s | P39: 0.6 | Q39: 2024 | R39: Lab and Mat and Equip | S39: 0.6 is assumption. Cost is an average of the range given on p. 115 of the Ref. ((4700000+6000000)/2), and flowrate is 200 kg/h as given on p. 113 in the caption of Table 48. | T39: Fernandez de Losada, Lucas Javier. Assessment of the Lifecycle Cost of Nuclear-Grade Coolants for Advanced Reactors. (Master's thesis, ETH Zurich, 2024). https://doi.org/10.3929/ethz-b-000709311 | U39: https://doi.org/10.3929/ethz-b-000709311 | W39: No Learning | X39: =0.9*$I39 -> 0 | Y39: =1.5*J39 -> 0 | Z39: Lognormal | AA39: =0.9*K39 -> 866700000 | AB39: =1.3*K39 -> 1251900000 | AC39: Lognormal | AD39: 0.1 | AE39: 1 | AF39: 0 | AG39: Truncated Normal
A40: 23.4 | B40: 2 | C40: Radioactive Waste Processing Hot Cell | D40: =REPT(" ", B40*2) & C40 -> Radioactive Waste Processing Hot Cell | E40: standard | F40: Radioactive Waste Processing Hot Cell Count | G40: 1 | J40: 1000000000 | Q40: 2024 | R40: Equipment | S40: assumption | V40: Should process 5 generating sites' worth of radwaste | W40: No Learning | X40: =0.8*$I40 -> 0 | Y40: =2*J40 -> 2000000000 | Z40: Lognormal | AA40: =0.8*K40 -> 0 | AB40: =2*K40 -> 0 | AC40: Lognormal | AD40: 0.1 | AE40: 1 | AF40: 0 | AG40: Truncated Normal
A41: 23.5 | B41: 2 | C41: Local Integrated Control Rooms | D41: =REPT(" ", B41*2) & C41 -> Local Integrated Control Rooms | E41: standard | F41: Servicing Hot Cell Count | G41: 1 | J41: =21555270/2 -> 10777635 | Q41: 1987 | R41: Lab and Mat and Equip | S41: One-half the cost of the Reactor Instrumentation + Control System of the PWR-12-BE from the EEDB | T41: Report on the ACCERT Cost Algorithms Tool, ANL/NSE-19/10 | U41: https://publications.anl.gov/anlpubs/2019/06/152862.pdf | W41: No Learning | X41: =0.9*$I41 -> 0 | Y41: =1.5*J41 -> 16166452 | Z41: Lognormal | AA41: =0.9*K41 -> 0 | AB41: =1.3*K41 -> 0 | AC41: Lognormal | AD41: 0.1 | AE41: 1 | AF41: 0 | AG41: Truncated Normal
A42: 23.6 | B42: 2 | C42: Remote Control Rooms | D42: =REPT(" ", B42*2) & C42 -> Remote Control Rooms | E42: standard | F42: Constant | G42: 1 | K42: 1000000 | M42: Generating Sites Count | Q42: 2024 | R42: Lab and Mat and Equip | S42: Assumption: $1 million per reactor, to approximately match Enrique's engineering judgment that a total cost of the remote control room of $1 billion per 1,000 reactors monitored would be reasonable. | W42: No Learning | X42: =0.9*$I42 -> 0 | Y42: =1.5*J42 -> 0 | Z42: Lognormal | AA42: =0.9*K42 -> 900000 | AB42: =1.3*K42 -> 1300000 | AC42: Lognormal | AD42: 0.1 | AE42: 1 | AF42: 0 | AG42: Truncated Normal
A43: 23.8 | B43: 2 | C43: Reactor Transport Casks | D43: =REPT(" ", B43*2) & C43 -> Reactor Transport Casks | E43: standard | F43: Constant | G43: 1 | J43: 10000000 | M43: Reactor Transport Cask Count | Q43: 2024 | R43: Lab and Mat and Equip | S43: assumption | W43: No Learning | X43: =0.9*$I43 -> 0 | Y43: =1.5*J43 -> 15000000 | Z43: Lognormal | AA43: =0.9*K43 -> 0 | AB43: =1.3*K43 -> 0 | AC43: Lognormal | AD43: 0.1 | AE43: 1 | AF43: 0 | AG43: Truncated Normal
A44: 28 | B44: =IF(ISNUMBER(A44), IF(AND(A44=INT(A44), MOD(A44, 10) = 0), 0, IF(AND(A44=INT(A44), LEN(A44)=2), 1, IF(AND(A44=INT(A44), LEN(A44)=3), 2, LEN(A44) - FIND(".", A44) + 2) ) ), "") -> 1 | C44: Auxiliary Infrastructure Equipment | D44: =REPT(" ", B44*2) & C44 -> Auxiliary Infrastructure Equipment
A45: 281 | B45: =IF(ISNUMBER(A45), IF(AND(A45=INT(A45), MOD(A45, 10) = 0), 0, IF(AND(A45=INT(A45), LEN(A45)=2), 1, IF(AND(A45=INT(A45), LEN(A45)=3), 2, LEN(A45) - FIND(".", A45) + 2) ) ), "") -> 2 | C45: Emergency Power | D45: =REPT(" ", B45*2) & C45 -> Emergency Power | E45: standard | K45: =(1450000*5+1500000)/2.5 -> 3500000 | L45: $/MWe | M45: SER Emergency Generator Power | N45: 1 | O45: MWe | P45: 1 | Q45: 2025 | R45: Equipment | S45: 2.5 MW generator cost from Central States Generators, nuclear multiple of 5, and guess for pad and connection to building (pad and connection have been requested with cost estimators) | W45: No Learning | X45: =0.9*$I45 -> 0 | Y45: =1.5*J45 -> 0 | Z45: Lognormal | AA45: =0.9*K45 -> 3150000 | AB45: =1.3*K45 -> 4550000 | AC45: Lognormal | AD45: 0.1 | AE45: 1 | AF45: 0 | AG45: Truncated Normal
A46: 282 | B46: =IF(ISNUMBER(A46), IF(AND(A46=INT(A46), MOD(A46, 10) = 0), 0, IF(AND(A46=INT(A46), LEN(A46)=2), 1, IF(AND(A46=INT(A46), LEN(A46)=3), 2, LEN(A46) - FIND(".", A46) + 2) ) ), "") -> 2 | C46: Service Air Water Building | D46: =REPT(" ", B46*2) & C46 -> Service Air Water Building | E46: standard | F46: Service Air Water Building Count | G46: 1 | J46: 15090300 | Q46: 2025 | R46: Lab and Mat and Equip | S46: 100 value from MC30 Cost Estimation of Microreactor Facilities Inital Draft 5-6-2026.pdf [temporary, want to add scaling equation] | W46: No Learning | X46: =0.9*$I46 -> 0 | Y46: =1.5*J46 -> 22635450 | Z46: Lognormal | AA46: =0.9*K46 -> 0 | AB46: =1.3*K46 -> 0 | AC46: Lognormal | AD46: 0.1 | AE46: 1 | AF46: 0 | AG46: Truncated Normal
A47: 283 | B47: =IF(ISNUMBER(A47), IF(AND(A47=INT(A47), MOD(A47, 10) = 0), 0, IF(AND(A47=INT(A47), LEN(A47)=2), 1, IF(AND(A47=INT(A47), LEN(A47)=3), 2, LEN(A47) - FIND(".", A47) + 2) ) ), "") -> 2 | C47: Fire Station | D47: =REPT(" ", B47*2) & C47 -> Fire Station | E47: standard | F47: SER Fire Station Count | G47: 1 | J47: =0.7*20776500 -> 14543550 | Q47: 2025 | R47: Lab and Mat and Equip | S47: 100 value from MC30 Cost Estimation of Microreactor Facilities Inital Draft 5-6-2026.pdf, less 30% [temporary, want to add scaling equation] | W47: No Learning | X47: =0.9*$I47 -> 0 | Y47: =1.5*J47 -> 21815325 | Z47: Lognormal | AA47: =0.9*K47 -> 0 | AB47: =1.3*K47 -> 0 | AC47: Lognormal | AD47: 0.1 | AE47: 1 | AF47: 0 | AG47: Truncated Normal
A48: 284 | B48: =IF(ISNUMBER(A48), IF(AND(A48=INT(A48), MOD(A48, 10) = 0), 0, IF(AND(A48=INT(A48), LEN(A48)=2), 1, IF(AND(A48=INT(A48), LEN(A48)=3), 2, LEN(A48) - FIND(".", A48) + 2) ) ), "") -> 2 | C48: Security Building | D48: =REPT(" ", B48*2) & C48 -> Security Building | E48: standard | K48: =0.7*2548*(3.2808^2) -> 19198.044 | L48: $/m^2 | M48: SER Security Building Area | N48: 1 | O48: m^2 | P48: 1 | Q48: 2025 | R48: Lab and Mat and Equip | S48: 100 value from MC30 Cost Estimation of Microreactor Facilities Inital Draft 5-6-2026.pdf, less 30% [temporary, want to add scaling equation] | W48: No Learning | X48: =0.9*$I48 -> 0 | Y48: =1.5*J48 -> 0 | Z48: Lognormal | AA48: =0.9*K48 -> 17278.239 | AB48: =1.3*K48 -> 24957.457 | AC48: Lognormal | AD48: 0.1 | AE48: 1 | AF48: 0 | AG48: Truncated Normal
A49: 285 | B49: =IF(ISNUMBER(A49), IF(AND(A49=INT(A49), MOD(A49, 10) = 0), 0, IF(AND(A49=INT(A49), LEN(A49)=2), 1, IF(AND(A49=INT(A49), LEN(A49)=3), 2, LEN(A49) - FIND(".", A49) + 2) ) ), "") -> 2 | C49: Switchyard | D49: =REPT(" ", B49*2) & C49 -> Switchyard | E49: standard | K49: =0.7*221450153/N49 -> 516717.02 | L49: $/MWe | M49: SER Switchyard Rating | N49: 300 | O49: MWe | P49: 0.9968 | Q49: 2025 | R49: Lab and Mat and Equip | S49: Scaling relationship created from MC30 Cost Estimation of Microreactor Facilities Inital Draft 5-6-2026.pdf, less 30% | W49: No Learning | X49: =0.9*$I49 -> 0 | Y49: =1.5*J49 -> 0 | Z49: Lognormal | AA49: =0.9*K49 -> 465045.32 | AB49: =1.3*K49 -> 671732.13 | AC49: Lognormal | AD49: 0.1 | AE49: 1 | AF49: 0 | AG49: Truncated Normal
A50: 286 | B50: =IF(ISNUMBER(A50), IF(AND(A50=INT(A50), MOD(A50, 10) = 0), 0, IF(AND(A50=INT(A50), LEN(A50)=2), 1, IF(AND(A50=INT(A50), LEN(A50)=3), 2, LEN(A50) - FIND(".", A50) + 2) ) ), "") -> 2 | C50: Onsite Transport Equipment | D50: =REPT(" ", B50*2) & C50 -> Onsite Transport Equipment
A51: 286.1 | B51: =IF(ISNUMBER(A51), IF(AND(A51=INT(A51), MOD(A51, 10) = 0), 0, IF(AND(A51=INT(A51), LEN(A51)=2), 1, IF(AND(A51=INT(A51), LEN(A51)=3), 2, LEN(A51) - FIND(".", A51) + 2) ) ), "") -> 3 | C51: Local Reactor Transport Vehicles | D51: =REPT(" ", B51*2) & C51 -> Local Reactor Transport Vehicles | E51: standard | F51: SER Local Transport Vehicle Count | G51: 1 | J51: 938000 | Q51: 2023 | R51: Equipment | S51: Lallemant report, Table 9, Considered price for 200 MT LTV | T51: Lallemant, Lucas. 2023 | W51: No Learning | X51: =0.9*$J51 -> 844200 | Y51: =1.5*J51 -> 1407000 | Z51: Lognormal | AA51: =0.9*K51 -> 0 | AB51: =1.3*K51 -> 0 | AC51: Lognormal | AD51: 0.1 | AE51: 1 | AF51: 0 | AG51: Truncated Normal
A52: 286.2 | B52: =IF(ISNUMBER(A52), IF(AND(A52=INT(A52), MOD(A52, 10) = 0), 0, IF(AND(A52=INT(A52), LEN(A52)=2), 1, IF(AND(A52=INT(A52), LEN(A52)=3), 2, LEN(A52) - FIND(".", A52) + 2) ) ), "") -> 3 | C52: Utility Vehicles | D52: =REPT(" ", B52*2) & C52 -> Utility Vehicles | E52: standard | F52: SER Utility Vehicle Count | G52: 1 | J52: 50000 | Q52: 2024 | R52: Equipment | S52: assumption | W52: No Learning | X52: =0.9*$J52 -> 45000 | Y52: =1.5*J52 -> 75000 | Z52: Lognormal | AA52: =0.9*K52 -> 0 | AB52: =1.3*K52 -> 0 | AC52: Lognormal | AD52: 0.1 | AE52: 1 | AF52: 0 | AG52: Truncated Normal
A53: 287 | B53: =IF(ISNUMBER(A53), IF(AND(A53=INT(A53), MOD(A53, 10) = 0), 0, IF(AND(A53=INT(A53), LEN(A53)=2), 1, IF(AND(A53=INT(A53), LEN(A53)=3), 2, LEN(A53) - FIND(".", A53) + 2) ) ), "") -> 2 | C53: Offsite Transport Equipment | D53: =REPT(" ", B53*2) & C53 -> Offsite Transport Equipment
A54: 287.1 | B54: =IF(ISNUMBER(A54), IF(AND(A54=INT(A54), MOD(A54, 10) = 0), 0, IF(AND(A54=INT(A54), LEN(A54)=2), 1, IF(AND(A54=INT(A54), LEN(A54)=3), 2, LEN(A54) - FIND(".", A54) + 2) ) ), "") -> 3 | C54: Reactor Transport Vehicles | D54: =REPT(" ", B54*2) & C54 -> Reactor Transport Vehicles | E54: standard | F54: Reactor Transport Vehicle Count | G54: 1 | J54: 1000000 | Q54: 2024 | R54: Equipment | S54: assumption | W54: No Learning | X54: =0.9*$J54 -> 900000 | Y54: =1.5*J54 -> 1500000 | Z54: Lognormal | AA54: =0.9*K54 -> 0 | AB54: =1.3*K54 -> 0 | AC54: Lognormal | AD54: 0.1 | AE54: 1 | AF54: 0 | AG54: Truncated Normal
A55: 287.2 | B55: =IF(ISNUMBER(A55), IF(AND(A55=INT(A55), MOD(A55, 10) = 0), 0, IF(AND(A55=INT(A55), LEN(A55)=2), 1, IF(AND(A55=INT(A55), LEN(A55)=3), 2, LEN(A55) - FIND(".", A55) + 2) ) ), "") -> 3 | C55: Helium Transport Trucks | D55: =REPT(" ", B55*2) & C55 -> Helium Transport Trucks | E55: standard | F55: Helium Transport Truck Count | G55: 1 | J55: 500000 | Q55: 2024 | R55: Equipment | S55: assumption | W55: No Learning | X55: =0.9*$J55 -> 450000 | Y55: =1.5*J55 -> 750000 | Z55: Lognormal | AA55: =0.9*K55 -> 0 | AB55: =1.3*K55 -> 0 | AC55: Lognormal | AD55: 0.1 | AE55: 1 | AF55: 0 | AG55: Truncated Normal
A56: 287.3 | B56: =IF(ISNUMBER(A56), IF(AND(A56=INT(A56), MOD(A56, 10) = 0), 0, IF(AND(A56=INT(A56), LEN(A56)=2), 1, IF(AND(A56=INT(A56), LEN(A56)=3), 2, LEN(A56) - FIND(".", A56) + 2) ) ), "") -> 3 | C56: Water Tanker Trucks | D56: =REPT(" ", B56*2) & C56 -> Water Tanker Trucks | E56: standard | F56: Water Tanker Truck Count | G56: 1 | J56: 300000 | Q56: 2024 | R56: Equipment | S56: assumption | W56: No Learning | X56: =0.9*$J56 -> 270000 | Y56: =1.5*J56 -> 450000 | Z56: Lognormal | AA56: =0.9*K56 -> 0 | AB56: =1.3*K56 -> 0 | AC56: Lognormal | AD56: 0.1 | AE56: 1 | AF56: 0 | AG56: Truncated Normal
A57: 287.4 | B57: =IF(ISNUMBER(A57), IF(AND(A57=INT(A57), MOD(A57, 10) = 0), 0, IF(AND(A57=INT(A57), LEN(A57)=2), 1, IF(AND(A57=INT(A57), LEN(A57)=3), 2, LEN(A57) - FIND(".", A57) + 2) ) ), "") -> 3 | C57: Maintenance Trucks | D57: =REPT(" ", B57*2) & C57 -> Maintenance Trucks | E57: standard | F57: Maintenance Truck Count | G57: 1 | J57: 500000 | Q57: 2024 | R57: Equipment | S57: assumption | W57: No Learning | X57: =0.9*$J57 -> 450000 | Y57: =1.5*J57 -> 750000 | Z57: Lognormal | AA57: =0.9*K57 -> 0 | AB57: =1.3*K57 -> 0 | AC57: Lognormal | AD57: 0.1 | AE57: 1 | AF57: 0 | AG57: Truncated Normal
A58: 287.5 | B58: =IF(ISNUMBER(A58), IF(AND(A58=INT(A58), MOD(A58, 10) = 0), 0, IF(AND(A58=INT(A58), LEN(A58)=2), 1, IF(AND(A58=INT(A58), LEN(A58)=3), 2, LEN(A58) - FIND(".", A58) + 2) ) ), "") -> 3 | C58: Air Transport Equipment | D58: =REPT(" ", B58*2) & C58 -> Air Transport Equipment
A59: 287.51 | B59: =IF(ISNUMBER(A59), IF(AND(A59=INT(A59), MOD(A59, 10) = 0), 0, IF(AND(A59=INT(A59), LEN(A59)=2), 1, IF(AND(A59=INT(A59), LEN(A59)=3), 2, LEN(A59) - FIND(".", A59) + 2) ) ), "") -> 4 | C59: Heavy Lift Helicopters | D59: =REPT(" ", B59*2) & C59 -> Heavy Lift Helicopters | E59: standard | F59: Helicopter Count | G59: 1 | J59: 50000000 | Q59: 2024 | R59: Equipment | S59: none | W59: No Learning | X59: =0.9*$J59 -> 45000000 | Y59: =1.5*J59 -> 75000000 | Z59: Lognormal | AA59: =0.9*K59 -> 0 | AB59: =1.3*K59 -> 0 | AC59: Lognormal | AD59: 0.1 | AE59: 1 | AF59: 0 | AG59: Truncated Normal
A60: 287.52 | B60: =IF(ISNUMBER(A60), IF(AND(A60=INT(A60), MOD(A60, 10) = 0), 0, IF(AND(A60=INT(A60), LEN(A60)=2), 1, IF(AND(A60=INT(A60), LEN(A60)=3), 2, LEN(A60) - FIND(".", A60) + 2) ) ), "") -> 4 | C60: Aircraft Maintenance Equipment | D60: =REPT(" ", B60*2) & C60 -> Aircraft Maintenance Equipment | E60: standard | F60: Constant | G60: 1 | J60: 1000000 | Q60: 2024 | R60: Equipment | S60: none | W60: No Learning | X60: =0.9*$J60 -> 900000 | Y60: =1.5*J60 -> 1500000 | Z60: Lognormal | AA60: =0.9*K60 -> 0 | AB60: =1.3*K60 -> 0 | AC60: Lognormal | AD60: 0.1 | AE60: 1 | AF60: 0 | AG60: Truncated Normal
A61: 288 | B61: =IF(ISNUMBER(A61), IF(AND(A61=INT(A61), MOD(A61, 10) = 0), 0, IF(AND(A61=INT(A61), LEN(A61)=2), 1, IF(AND(A61=INT(A61), LEN(A61)=3), 2, LEN(A61) - FIND(".", A61) + 2) ) ), "") -> 2 | C61: Dispered Infrastructure | D61: =REPT(" ", B61*2) & C61 -> Dispered Infrastructure | S61: assumption, guess
A62: 288.1 | B62: 3 | C62: Communication | D62: =REPT(" ", B62*2) & C62 -> Communication | E62: standard | K62: =12575250/N62 -> 11774.579 | L62: $/acres | M62: SER Campus Land Area | N62: 1068 | O62: acres | Q62: 2025 | R62: Equipment | S62: [to become a scaling relationship] MC30 Cost Estimation of Microreactor Facilities Inital Draft 5-6-2026.pdf | W62: No Learning | X62: =0.9*$J62 -> 0 | Y62: =1.5*J62 -> 0 | Z62: Lognormal | AA62: =0.9*K62 -> 10597.121 | AB62: =1.3*K62 -> 15306.952 | AC62: Lognormal | AD62: 0.1 | AE62: 1 | AF62: 0 | AG62: Truncated Normal
A63: 288.2 | B63: 3 | C63: Security Cameras | D63: =REPT(" ", B63*2) & C63 -> Security Cameras | E63: standard | F63: SER Security Camera Count | G63: 1 | J63: 28431 | Q63: 2025 | R63: Equipment | S63: MC30 Cost Estimation of Microreactor Facilities Inital Draft 5-6-2026.pdf | W63: No Learning | X63: =0.9*$J63 -> 25587.9 | Y63: =1.5*J63 -> 42646.5 | Z63: Lognormal | AA63: =0.9*K63 -> 0 | AB63: =1.3*K63 -> 0 | AC63: Lognormal | AD63: 0.1 | AE63: 1 | AF63: 0 | AG63: Truncated Normal
A64: 288.3 | B64: 3 | C64: Motion Detectors | D64: =REPT(" ", B64*2) & C64 -> Motion Detectors | E64: standard | F64: SER Motion Detector Count | G64: 1 | J64: 24057 | Q64: 2025 | R64: Equipment | S64: MC30 Cost Estimation of Microreactor Facilities Inital Draft 5-6-2026.pdf | W64: No Learning | X64: =0.9*$J64 -> 21651.3 | Y64: =1.5*J64 -> 36085.5 | Z64: Lognormal | AA64: =0.9*K64 -> 0 | AB64: =1.3*K64 -> 0 | AC64: Lognormal | AD64: 0.1 | AE64: 1 | AF64: 0 | AG64: Truncated Normal
A65: 288.4 | B65: 3 | C65: Guard Station | D65: =REPT(" ", B65*2) & C65 -> Guard Station | E65: standard | F65: SER Guard Station Count | G65: 1 | J65: 6774250 | Q65: 2025 | R65: Equipment | S65: MC30 Cost Estimation of Microreactor Facilities Inital Draft 5-6-2026.pdf | W65: No Learning | X65: =0.9*$J65 -> 6096825 | Y65: =1.5*J65 -> 10161375 | Z65: Lognormal | AA65: =0.9*K65 -> 0 | AB65: =1.3*K65 -> 0 | AC65: Lognormal | AD65: 0.1 | AE65: 1 | AF65: 0 | AG65: Truncated Normal
A66: 288.5 | B66: 3 | C66: Radiation Monitors | D66: =REPT(" ", B66*2) & C66 -> Radiation Monitors | E66: standard | F66: SER Radiation Monitor Count | G66: 1 | J66: 656100 | Q66: 2025 | R66: Equipment | S66: MC30 Cost Estimation of Microreactor Facilities Inital Draft 5-6-2026.pdf | W66: No Learning | X66: =0.9*$J66 -> 590490 | Y66: =1.5*J66 -> 984150 | Z66: Lognormal | AA66: =0.9*K66 -> 0 | AB66: =1.3*K66 -> 0 | AC66: Lognormal | AD66: 0.1 | AE66: 1 | AF66: 0 | AG66: Truncated Normal
A67: 30 | B67: =IF(ISNUMBER(A67), IF(AND(A67=INT(A67), MOD(A67, 10) = 0), 0, IF(AND(A67=INT(A67), LEN(A67)=2), 1, IF(AND(A67=INT(A67), LEN(A67)=3), 2, LEN(A67) - FIND(".", A67) + 2) ) ), "") -> 0 | C67: Capitalized Indirect Services Cost | D67: =REPT(" ", B67*2) & C67 -> Capitalized Indirect Services Cost
A68: 40 | B68: =IF(ISNUMBER(A68), IF(AND(A68=INT(A68), MOD(A68, 10) = 0), 0, IF(AND(A68=INT(A68), LEN(A68)=2), 1, IF(AND(A68=INT(A68), LEN(A68)=3), 2, LEN(A68) - FIND(".", A68) + 2) ) ), "") -> 0 | C68: Capitalized training costs | D68: =REPT(" ", B68*2) & C68 -> Capitalized training costs
A69: 41 | B69: =IF(ISNUMBER(A69), IF(AND(A69=INT(A69), MOD(A69, 10) = 0), 0, IF(AND(A69=INT(A69), LEN(A69)=2), 1, IF(AND(A69=INT(A69), LEN(A69)=3), 2, LEN(A69) - FIND(".", A69) + 2) ) ), "") -> 1 | C69: staff recruitment and training | D69: =REPT(" ", B69*2) & C69 -> staff recruitment and training | E69: standard | F69: Constant | G69: 1 | J69: 300000 | Q69: 2024 | R69: Labor | W69: No Learning | X69: =0.9*$J69 -> 270000 | Y69: =1.5*J69 -> 450000 | Z69: Lognormal | AA69: =0.9*K69 -> 0 | AB69: =1.3*K69 -> 0 | AC69: Lognormal | AD69: 0.1 | AE69: 1 | AF69: 0 | AG69: Truncated Normal
A70: 60 | B70: =IF(ISNUMBER(A70), IF(AND(A70=INT(A70), MOD(A70, 10) = 0), 0, IF(AND(A70=INT(A70), LEN(A70)=2), 1, IF(AND(A70=INT(A70), LEN(A70)=3), 2, LEN(A70) - FIND(".", A70) + 2) ) ), "") -> 0 | C70: Capitalized Financial Costs | D70: =REPT(" ", B70*2) & C70 -> Capitalized Financial Costs
A71: 62 | B71: =IF(ISNUMBER(A71), IF(AND(A71=INT(A71), MOD(A71, 10) = 0), 0, IF(AND(A71=INT(A71), LEN(A71)=2), 1, IF(AND(A71=INT(A71), LEN(A71)=3), 2, LEN(A71) - FIND(".", A71) + 2) ) ), "") -> 1 | C71: Interest | D71: =REPT(" ", B71*2) & C71 -> Interest
A72: 70 | B72: =IF(ISNUMBER(A72), IF(AND(A72=INT(A72), MOD(A72, 10) = 0), 0, IF(AND(A72=INT(A72), LEN(A72)=2), 1, IF(AND(A72=INT(A72), LEN(A72)=3), 2, LEN(A72) - FIND(".", A72) + 2) ) ), "") -> 0 | C72: Annualized O&M Cost | D72: =REPT(" ", B72*2) & C72 -> Annualized O&M Cost
A73: 71 | B73: =IF(ISNUMBER(A73), IF(AND(A73=INT(A73), MOD(A73, 10) = 0), 0, IF(AND(A73=INT(A73), LEN(A73)=2), 1, IF(AND(A73=INT(A73), LEN(A73)=3), 2, LEN(A73) - FIND(".", A73) + 2) ) ), "") -> 1 | C73: O&M Staff | D73: =REPT(" ", B73*2) & C73 -> O&M Staff
A74: 711 | B74: =IF(ISNUMBER(A74), IF(AND(A74=INT(A74), MOD(A74, 10) = 0), 0, IF(AND(A74=INT(A74), LEN(A74)=2), 1, IF(AND(A74=INT(A74), LEN(A74)=3), 2, LEN(A74) - FIND(".", A74) + 2) ) ), "") -> 2 | C74: Operators | D74: =REPT(" ", B74*2) & C74 -> Operators | E74: nonstandard | G74: 1 | K74: 178500 | L74: $/FTE-year | M74: SER Operator FTEs Per Facility | P74: 1 | Q74: 2024 | R74: Labor | T74: de Candido, I., A. Al Rashdan, A. Abou-Jaoude, and J. Buongiorno. 2024. “Assessment of Technoeconomic Opportunities in Automation for Nuclear Microreactors.” Nuclear Science and Engineering, 1–20. https://doi.org/10.1080/00295639.2024.2372511. | W74: No Learning | X74: =0.9*$J74 -> 0 | Y74: =1.5*J74 -> 0 | Z74: Lognormal | AA74: =0.9*K74 -> 160650 | AB74: =1.3*K74 -> 232050 | AC74: Lognormal | AD74: 0.1 | AE74: 1 | AF74: 0 | AG74: Truncated Normal
A75: 712 | B75: =IF(ISNUMBER(A75), IF(AND(A75=INT(A75), MOD(A75, 10) = 0), 0, IF(AND(A75=INT(A75), LEN(A75)=2), 1, IF(AND(A75=INT(A75), LEN(A75)=3), 2, LEN(A75) - FIND(".", A75) + 2) ) ), "") -> 2 | C75: Remote Monitoring Technicians | D75: =REPT(" ", B75*2) & C75 -> Remote Monitoring Technicians | E75: nonstandard | F75: Reactors Monitored Per Operator | G75: 1 | K75: 178500 | L75: $/FTE | M75: Generating Sites Count | P75: 1 | Q75: 2024 | R75: Labor | T75: de Candido, I., A. Al Rashdan, A. Abou-Jaoude, and J. Buongiorno. 2024. “Assessment of Technoeconomic Opportunities in Automation for Nuclear Microreactors.” Nuclear Science and Engineering, 1–20. https://doi.org/10.1080/00295639.2024.2372511. | W75: No Learning | X75: =0.9*$J75 -> 0 | Y75: =1.5*J75 -> 0 | Z75: Lognormal | AA75: =0.9*K75 -> 160650 | AB75: =1.3*K75 -> 232050 | AC75: Lognormal | AD75: 0.1 | AE75: 1 | AF75: 0 | AG75: Truncated Normal
A76: 713 | B76: =IF(ISNUMBER(A76), IF(AND(A76=INT(A76), MOD(A76, 10) = 0), 0, IF(AND(A76=INT(A76), LEN(A76)=2), 1, IF(AND(A76=INT(A76), LEN(A76)=3), 2, LEN(A76) - FIND(".", A76) + 2) ) ), "") -> 2 | C76: Security Staff | D76: =REPT(" ", B76*2) & C76 -> Security Staff | E76: nonstandard | F76: Shift To Headcount | G76: 1 | K76: 178500 | L76: $/FTE | M76: SER Security Staff Per Shift | P76: 1 | Q76: 2024 | R76: Labor | T76: de Candido, I., A. Al Rashdan, A. Abou-Jaoude, and J. Buongiorno. 2024. “Assessment of Technoeconomic Opportunities in Automation for Nuclear Microreactors.” Nuclear Science and Engineering, 1–20. https://doi.org/10.1080/00295639.2024.2372511. | W76: No Learning | X76: =0.9*$J76 -> 0 | Y76: =1.5*J76 -> 0 | Z76: Lognormal | AA76: =0.9*K76 -> 160650 | AB76: =1.3*K76 -> 232050 | AC76: Lognormal | AD76: 0.1 | AE76: 1 | AF76: 0 | AG76: Truncated Normal
A77: 714 | B77: =IF(ISNUMBER(A77), IF(AND(A77=INT(A77), MOD(A77, 10) = 0), 0, IF(AND(A77=INT(A77), LEN(A77)=2), 1, IF(AND(A77=INT(A77), LEN(A77)=3), 2, LEN(A77) - FIND(".", A77) + 2) ) ), "") -> 2 | C77: Maintenance Staff | D77: =REPT(" ", B77*2) & C77 -> Maintenance Staff | E77: nonstandard | F77: Shift To Headcount | G77: 1 | K77: 178500 | L77: $/FTE | M77: SER Maintenance Staff Per Shift | P77: 1 | Q77: 2024 | R77: Labor | T77: de Candido, I., A. Al Rashdan, A. Abou-Jaoude, and J. Buongiorno. 2024. “Assessment of Technoeconomic Opportunities in Automation for Nuclear Microreactors.” Nuclear Science and Engineering, 1–20. https://doi.org/10.1080/00295639.2024.2372511. | W77: No Learning | X77: =0.9*$J77 -> 0 | Y77: =1.5*J77 -> 0 | Z77: Lognormal | AA77: =0.9*K77 -> 160650 | AB77: =1.3*K77 -> 232050 | AC77: Lognormal | AD77: 0.1 | AE77: 1 | AF77: 0 | AG77: Truncated Normal
A78: 715 | B78: =IF(ISNUMBER(A78), IF(AND(A78=INT(A78), MOD(A78, 10) = 0), 0, IF(AND(A78=INT(A78), LEN(A78)=2), 1, IF(AND(A78=INT(A78), LEN(A78)=3), 2, LEN(A78) - FIND(".", A78) + 2) ) ), "") -> 2 | C78: Engineering Staff | D78: =REPT(" ", B78*2) & C78 -> Engineering Staff | E78: nonstandard | K78: 200000 | L78: $/FTE | M78: SER Engineering Headcount | Q78: 2024 | R78: Labor | W78: No Learning | X78: =0.9*$J78 -> 0 | Y78: =1.5*J78 -> 0 | Z78: Lognormal | AA78: =0.9*K78 -> 180000 | AB78: =1.3*K78 -> 260000 | AC78: Lognormal | AD78: 0.1 | AE78: 1 | AF78: 0 | AG78: Truncated Normal
A79: 716 | B79: =IF(ISNUMBER(A79), IF(AND(A79=INT(A79), MOD(A79, 10) = 0), 0, IF(AND(A79=INT(A79), LEN(A79)=2), 1, IF(AND(A79=INT(A79), LEN(A79)=3), 2, LEN(A79) - FIND(".", A79) + 2) ) ), "") -> 2 | C79: Continuing Education and Staff Retraining | D79: =REPT(" ", B79*2) & C79 -> Continuing Education and Staff Retraining | R79: Labor | W79: No Learning | X79: =0.9*$J79 -> 0 | Y79: =1.5*J79 -> 0 | AA79: =0.9*K79 -> 0 | AB79: =1.3*K79 -> 0
A80: 717 | B80: =IF(ISNUMBER(A80), IF(AND(A80=INT(A80), MOD(A80, 10) = 0), 0, IF(AND(A80=INT(A80), LEN(A80)=2), 1, IF(AND(A80=INT(A80), LEN(A80)=3), 2, LEN(A80) - FIND(".", A80) + 2) ) ), "") -> 2 | C80: Management Staff | D80: =REPT(" ", B80*2) & C80 -> Management Staff | R80: Labor | W80: No Learning | X80: =0.9*$J80 -> 0 | Y80: =1.5*J80 -> 0 | AA80: =0.9*K80 -> 0 | AB80: =1.3*K80 -> 0
A81: 74 | B81: =IF(ISNUMBER(A81), IF(AND(A81=INT(A81), MOD(A81, 10) = 0), 0, IF(AND(A81=INT(A81), LEN(A81)=2), 1, IF(AND(A81=INT(A81), LEN(A81)=3), 2, LEN(A81) - FIND(".", A81) + 2) ) ), "") -> 1 | C81: Fixed O&M Utilities and Materials | D81: =REPT(" ", B81*2) & C81 -> Fixed O&M Utilities and Materials
A82: 741 | B82: =IF(ISNUMBER(A82), IF(AND(A82=INT(A82), MOD(A82, 10) = 0), 0, IF(AND(A82=INT(A82), LEN(A82)=2), 1, IF(AND(A82=INT(A82), LEN(A82)=3), 2, LEN(A82) - FIND(".", A82) + 2) ) ), "") -> 2 | C82: Operating Chemicals and Lubricants | D82: =REPT(" ", B82*2) & C82 -> Operating Chemicals and Lubricants | W82: No Learning | X82: =0.9*$J82 -> 0 | Y82: =1.5*J82 -> 0 | AA82: =0.9*K82 -> 0 | AB82: =1.3*K82 -> 0
A83: 742 | B83: =IF(ISNUMBER(A83), IF(AND(A83=INT(A83), MOD(A83, 10) = 0), 0, IF(AND(A83=INT(A83), LEN(A83)=2), 1, IF(AND(A83=INT(A83), LEN(A83)=3), 2, LEN(A83) - FIND(".", A83) + 2) ) ), "") -> 2 | C83: Spare Parts | D83: =REPT(" ", B83*2) & C83 -> Spare Parts | W83: No Learning | X83: =0.9*$J83 -> 0 | Y83: =1.5*J83 -> 0 | AA83: =0.9*K83 -> 0 | AB83: =1.3*K83 -> 0
A84: 743 | B84: =IF(ISNUMBER(A84), IF(AND(A84=INT(A84), MOD(A84, 10) = 0), 0, IF(AND(A84=INT(A84), LEN(A84)=2), 1, IF(AND(A84=INT(A84), LEN(A84)=3), 2, LEN(A84) - FIND(".", A84) + 2) ) ), "") -> 2 | C84: Utilities except electricity, Supplies, and Consumables | D84: =REPT(" ", B84*2) & C84 -> Utilities except electricity, Supplies, and Consumables | W84: No Learning | X84: =0.9*$J84 -> 0 | Y84: =1.5*J84 -> 0 | AA84: =0.9*K84 -> 0 | AB84: =1.3*K84 -> 0
A85: 744 | B85: =IF(ISNUMBER(A85), IF(AND(A85=INT(A85), MOD(A85, 10) = 0), 0, IF(AND(A85=INT(A85), LEN(A85)=2), 1, IF(AND(A85=INT(A85), LEN(A85)=3), 2, LEN(A85) - FIND(".", A85) + 2) ) ), "") -> 2 | C85: Electricity | D85: =REPT(" ", B85*2) & C85 -> Electricity | E85: nonstandard | F85: Constant | G85: 1 | K85: 90 | L85: $/MWeHour | M85: SER Switchyard Average Power | P85: 1 | Q85: 2025 | R85: General | W85: No Learning | X85: =0.9*$J85 -> 0 | Y85: =1.5*J85 -> 0 | Z85: Lognormal | AA85: =0.9*K85 -> 81 | AB85: =1.3*K85 -> 117 | AC85: Lognormal | AD85: 0.1 | AE85: 1 | AF85: 0 | AG85: Truncated Normal
A86: 747.1 | B86: =IF(ISNUMBER(A86), IF(AND(A86=INT(A86), MOD(A86, 10) = 0), 0, IF(AND(A86=INT(A86), LEN(A86)=2), 1, IF(AND(A86=INT(A86), LEN(A86)=3), 2, LEN(A86) - FIND(".", A86) + 2) ) ), "") -> 3 | C86: Annualized Transportation Costs | D86: =REPT(" ", B86*2) & C86 -> Annualized Transportation Costs | W86: No Learning | X86: =0.8*$I86 -> 0 | Y86: =2*J86 -> 0 | AA86: =0.8*K86 -> 0 | AB86: =2*K86 -> 0
A87: 747.2 | B87: =IF(ISNUMBER(A87), IF(AND(A87=INT(A87), MOD(A87, 10) = 0), 0, IF(AND(A87=INT(A87), LEN(A87)=2), 1, IF(AND(A87=INT(A87), LEN(A87)=3), 2, LEN(A87) - FIND(".", A87) + 2) ) ), "") -> 3 | C87: Annualized Cask Replacements | D87: =REPT(" ", B87*2) & C87 -> Annualized Cask Replacements
A88: 747.21 | B88: =IF(ISNUMBER(A88), IF(AND(A88=INT(A88), MOD(A88, 10) = 0), 0, IF(AND(A88=INT(A88), LEN(A88)=2), 1, IF(AND(A88=INT(A88), LEN(A88)=3), 2, LEN(A88) - FIND(".", A88) + 2) ) ), "") -> 4 | C88: Used Fuel Cask | D88: =REPT(" ", B88*2) & C88 -> Used Fuel Cask | E88: standard | F88: Annual Used Fuel Cask Consumption | G88: 1 | J88: 1159000 | Q88: 2023 | R88: Equipment | S88: MIT-ANP-TR-198 | V88: NUHOMS EOS 37 PTH ESC Cask | W88: No Learning | X88: 1008000 | Y88: 1310000 | Z88: Lognormal | AA88: =0.8*K88 -> 0 | AB88: =2*K88 -> 0 | AC88: Lognormal | AD88: 0.1 | AE88: 1 | AF88: 0 | AG88: Truncated Normal
A89: 747.22 | B89: =IF(ISNUMBER(A89), IF(AND(A89=INT(A89), MOD(A89, 10) = 0), 0, IF(AND(A89=INT(A89), LEN(A89)=2), 1, IF(AND(A89=INT(A89), LEN(A89)=3), 2, LEN(A89) - FIND(".", A89) + 2) ) ), "") -> 4 | C89: Reactor Transport Cask | D89: =REPT(" ", B89*2) & C89 -> Reactor Transport Cask | E89: standard | F89: Annual Reactor Cask Replacement | G89: 1 | J89: =J43 -> 10000000 | Q89: =Q43 -> 2024 | R89: =R43 -> Lab and Mat and Equip | S89: =S43 -> assumption | T89: =T43 -> 0 | U89: =U43 -> 0 | V89: =V43 -> 0 | W89: =W43 -> No Learning | X89: =X43 -> 0 | ... AG89: =AG43 -> Truncated Normal
A90: 747.23 | B90: =IF(ISNUMBER(A90), IF(AND(A90=INT(A90), MOD(A90, 10) = 0), 0, IF(AND(A90=INT(A90), LEN(A90)=2), 1, IF(AND(A90=INT(A90), LEN(A90)=3), 2, LEN(A90) - FIND(".", A90) + 2) ) ), "") -> 4 | C90: Radwaste Storage Cask | D90: =REPT(" ", B90*2) & C90 -> Radwaste Storage Cask | E90: standard | F90: Annual Radwaste Cask Consumption | G90: 1 | J90: 1159000 | Q90: 2023 | R90: Equipment | S90: MIT-ANP-TR-198 | V90: NUHOMS EOS 37 PTH ESC Cask | W90: No Learning | X90: 1008000 | Y90: 1310000 | Z90: Lognormal | AA90: =0.8*K90 -> 0 | AB90: =2*K90 -> 0 | AC90: Lognormal | AD90: 0.1 | AE90: 1 | AF90: 0 | AG90: Truncated Normal
A91: 747.24 | B91: =IF(ISNUMBER(A91),IF(AND(A91=INT(A91),MOD(A91,10)=0),0,IF(AND(A91=INT(A91),LEN(A91)=2),1,IF(AND(A91=INT(A91),LEN(A91)=3),2,LEN(A91)-FIND(".",A91)+2))),"") -> 4 | C91: Used Fuel Storage Additional Overpacks | D91: =REPT(" ",B91*2)&C91 -> Used Fuel Storage Additional Overpacks | E91: standard | K91: 200000 | L91: $/(reactors/year) | M91: Servicing Rate | N91: 1 | O91: reactors/year | P91: 1 | Q91: 2009 | R91: Equipment | U91: https://doi.org/10.3929/ethz-b-000709311 | W91: No Learning | X91: 0 | Y91: 0 | Z91: Lognormal | AA91: =0.8*K91 -> 160000 | AB91: =2*K91 -> 400000 | AC91: Lognormal | AD91: 0.1 | AE91: 1 | AF91: 0 | AG91: Truncated Normal
A92: 747.3 | B92: =IF(ISNUMBER(A92), IF(AND(A92=INT(A92), MOD(A92, 10) = 0), 0, IF(AND(A92=INT(A92), LEN(A92)=2), 1, IF(AND(A92=INT(A92), LEN(A92)=3), 2, LEN(A92) - FIND(".", A92) + 2) ) ), "") -> 3 | C92: Annualized Helium Replenishment | D92: =REPT(" ", B92*2) & C92 -> Annualized Helium Replenishment | E92: standard | F92: Constant | G92: 1 | K92: 170 | L92: $/Kg | M92: He Gas Replenishment | O92: Kg | Q92: 2024 | R92: Equipment | S92: Fernandez de Losada. (2024). Assessment of the Lifecycle Cost of Nuclear-Grade Coolants for Advanced Reactors. ETHzurich. Swiss. | T92: Fernandez de Losada. (2024). Assessment of the Lifecycle Cost of Nuclear-Grade Coolants for Advanced Reactors. ETHzurich. Swiss. | U92: https://doi.org/10.3929/ethz-b-000709311 | V92: Vendor Quoate (Linde) for 3000 cylinders of 99.999% purity Helium. 3000 cylinders correspond to ~4 MT of He. | W92: No Learning | X92: 0 | Y92: 0 | Z92: Lognormal | AA92: =0.9*K92 -> 153 | AB92: =1.3*K92 -> 221 | AC92: Lognormal | AD92: 0.1 | AE92: 1 | AF92: 0 | AG92: Truncated Normal
A93: 747.4 | B93: =IF(ISNUMBER(A93), IF(AND(A93=INT(A93), MOD(A93, 10) = 0), 0, IF(AND(A93=INT(A93), LEN(A93)=2), 1, IF(AND(A93=INT(A93), LEN(A93)=3), 2, LEN(A93) - FIND(".", A93) + 2) ) ), "") -> 3 | C93: Annualized Other Supplies and Utilities | D93: =REPT(" ", B93*2) & C93 -> Annualized Other Supplies and Utilities
A94: 747.5 | B94: =IF(ISNUMBER(A94), IF(AND(A94=INT(A94), MOD(A94, 10) = 0), 0, IF(AND(A94=INT(A94), LEN(A94)=2), 1, IF(AND(A94=INT(A94), LEN(A94)=3), 2, LEN(A94) - FIND(".", A94) + 2) ) ), "") -> 3 | C94: Servicing Vehicle O&M | D94: =REPT(" ", B94*2) & C94 -> Servicing Vehicle O&M
A95: 747.51 | B95: =IF(ISNUMBER(A95), IF(AND(A95=INT(A95), MOD(A95, 10) = 0), 0, IF(AND(A95=INT(A95), LEN(A95)=2), 1, IF(AND(A95=INT(A95), LEN(A95)=3), 2, LEN(A95) - FIND(".", A95) + 2) ) ), "") -> 4 | C95: Reactor Transport Vehicles O&M | D95: =REPT(" ", B95*2) & C95 -> Reactor Transport Vehicles O&M | E95: standard | F95: Reactor Transport Vehicle Count | G95: 1 | J95: =36*200000+1000000 -> 8200000 | Q95: 2024 | R95: Lab and Equip | W95: No Learning | X95: =0.9*$J95 -> 7380000 | Y95: =1.5*J95 -> 12300000 | Z95: Lognormal | AA95: =0.9*K95 -> 0 | AB95: =1.3*K95 -> 0 | AC95: Lognormal | AD95: 0.1 | AE95: 1 | AF95: 0 | AG95: Truncated Normal
A96: 747.52 | B96: =IF(ISNUMBER(A96), IF(AND(A96=INT(A96), MOD(A96, 10) = 0), 0, IF(AND(A96=INT(A96), LEN(A96)=2), 1, IF(AND(A96=INT(A96), LEN(A96)=3), 2, LEN(A96) - FIND(".", A96) + 2) ) ), "") -> 4 | C96: Helium Transport Trucks O&M | D96: =REPT(" ", B96*2) & C96 -> Helium Transport Trucks O&M | E96: standard | F96: Helium Transport Truck Count | G96: 1 | J96: =4*200000+500000 -> 1300000 | Q96: 2024 | R96: Lab and Equip | W96: No Learning | X96: =0.9*$J96 -> 1170000 | Y96: =1.5*J96 -> 1950000 | Z96: Lognormal | AA96: =0.9*K96 -> 0 | AB96: =1.3*K96 -> 0 | AC96: Lognormal | AD96: 0.1 | AE96: 1 | AF96: 0 | AG96: Truncated Normal
A97: 747.53 | B97: =IF(ISNUMBER(A97), IF(AND(A97=INT(A97), MOD(A97, 10) = 0), 0, IF(AND(A97=INT(A97), LEN(A97)=2), 1, IF(AND(A97=INT(A97), LEN(A97)=3), 2, LEN(A97) - FIND(".", A97) + 2) ) ), "") -> 4 | C97: Water Tanker Trucks O&M | D97: =REPT(" ", B97*2) & C97 -> Water Tanker Trucks O&M | E97: standard | F97: Water Tanker Truck Count | G97: 1 | J97: =4*200000+400000 -> 1200000 | Q97: 2024 | R97: Lab and Equip | W97: No Learning | X97: =0.9*$J97 -> 1080000 | Y97: =1.5*J97 -> 1800000 | Z97: Lognormal | AA97: =0.9*K97 -> 0 | AB97: =1.3*K97 -> 0 | AC97: Lognormal | AD97: 0.1 | AE97: 1 | AF97: 0 | AG97: Truncated Normal
A98: 747.54 | B98: =IF(ISNUMBER(A98), IF(AND(A98=INT(A98), MOD(A98, 10) = 0), 0, IF(AND(A98=INT(A98), LEN(A98)=2), 1, IF(AND(A98=INT(A98), LEN(A98)=3), 2, LEN(A98) - FIND(".", A98) + 2) ) ), "") -> 4 | C98: Maintenance Trucks O&M | D98: =REPT(" ", B98*2) & C98 -> Maintenance Trucks O&M | E98: standard | F98: Maintenance Truck Count | G98: 1 | J98: =10*2*200000+1000000 -> 5000000 | Q98: 2024 | R98: Lab and Equip | W98: No Learning | X98: =0.9*$J98 -> 4500000 | Y98: =1.5*J98 -> 7500000 | Z98: Lognormal | AA98: =0.9*K98 -> 0 | AB98: =1.3*K98 -> 0 | AC98: Lognormal | AD98: 0.1 | AE98: 1 | AF98: 0 | AG98: Truncated Normal
A99: 75 | B99: =IF(ISNUMBER(A99), IF(AND(A99=INT(A99), MOD(A99, 10) = 0), 0, IF(AND(A99=INT(A99), LEN(A99)=2), 1, IF(AND(A99=INT(A99), LEN(A99)=3), 2, LEN(A99) - FIND(".", A99) + 2) ) ), "") -> 1 | C99: Capital Plant Expenditures | D99: =REPT(" ", B99*2) & C99 -> Capital Plant Expenditures
A100: 78 | B100: =IF(ISNUMBER(A100),IF(AND(A100=INT(A100),MOD(A100,10)=0),0,IF(AND(A100=INT(A100),LEN(A100)=2),1,IF(AND(A100=INT(A100),LEN(A100)=3),2,LEN(A100)-FIND(".",A100)+2))),"") -> 1 | C100: Annualized Decommissioning Cost | D100: =REPT(" ",B100*2)&C100 -> Annualized Decommissioning Cost
